Workbook

Sheet How to Read
B1: EV Readiness & Impact Index
B8: {={"HOW TO READ THIS SPREADSHEET"; ""; "OVERVIEW"; "This spreadsheet contains the underlying data for the Africa EV Readiness and Impact Indices, comprehensive frameworks for assessing African countries' preparedness for electric vehicle adoption and potential benefits. Here's how to navigate the informa"&"tion:"; ""; "1. MAIN SHEET"; "• Contains raw data for all indicators across both indices"; "• Organized by major categories (Enabling Policies, Grid Infrastructure, etc.)"; "• Includes links to source data and methodology notes"; "• Shows latest available data for each indicator"; ""; "2. SCORING TABS"; ""; "Readiness Total Scores Tab:"; "• Shows normalized scores (1/3, 2/3, 3/3) for readiness indicators"; "• Calculates averages with and without enabling policies"; "• Provides category-level scores"; ""; "Impact Total Scores Tab:"; "• Shows normalized scores (1/3, 2/3, 3/3) for impact indicators"; "• Calculates overall impact averages"; ""; "3. INDICATOR-SPECIFIC TABS"; "• Each indicator has its own detailed tab"; "• Contains raw data, calculations, and methodological notes"; "• Features an information box (approx. cell C65) with:"; " - Index category and sub-category"; " - Detailed description"; " - Scoring methodology"; " - Data sources"; " - Key statistics"; ""; "4. INDACTOR SCORING METHODOLOGY"; "Full methodologies can be found in methodology note [link at the bottom of page]"; ""; "Readiness Indicators:"; "• Low Readiness: 1/3 (0.33)"; "• Medium Readiness: 2/3 (0.67)"; "• High Readiness: 3/3 (1.00)"; "• Some indicators use binary scoring (1/3 or 3/3 only)"; "• A country's aggregate readiness score is calculated by averaging indicator scores (equal weigthing)"; ""; "Impact Indicators:"; "• Low Impact: 1/3 (0.33)"; "• Medium Impact: 2/3 (0.67)"; "• High Impact: 3/3 (1.00)"; "• A country's aggregate readiness score is calculated by averaging indicator scores (equal weigthing)"; ""; "5. CATEGORY BREAKDOWN"; ""; "Readiness Categories:"; "• Enabling Policies: National targets and incentives"; "• Grid Infrastructure: Generation capacity and reliability"; "• Market: Current motorization and charging infrastructure"; "• Power Sector Maturity: Regulatory environment and financial health"; "• EV Affordability: Relative costs and financial access"; ""; "Impact Categories:"; "• Climate: Clean energy share and transport emissions"; "• Public Health: Urban air quality"; "• Financial: Import dependence and revenue potential"; "• Market Potential: Projected motorization rates"; ""; "6. DATA UPDATES"; "• Latest comprehensive update: 2024"; "• Individual indicator dates vary (see main tab)"}} -> HOW TO READ THIS SPREADSHEET
B10: OVERVIEW
B11: This spreadsheet contains the underlying data for the Africa EV Readiness and Impact Indices, comprehensive frameworks for assessing African countries' preparedness for electric vehicle adoption and potential benefits. Here's how to navigate the information:
B13: 1. MAIN SHEET
B14: • Contains raw data for all indicators across both indices
B15: • Organized by major categories (Enabling Policies, Grid Infrastructure, etc.)
B16: • Includes links to source data and methodology notes
B17: • Shows latest available data for each indicator
B19: 2. SCORING TABS
B21: Readiness Total Scores Tab:
B22: • Shows normalized scores (1/3, 2/3, 3/3) for readiness indicators
B23: • Calculates averages with and without enabling policies
B24: • Provides category-level scores
... B75: Full methodology

Sheet Overview
B1: MAIN SHEET
B2: Tab | C2: Summary | D2: Notes
B3: Main Sheet | C3: Synthesizes database | D3: Compares metrics for all 54 African countries
B5: CATEGORIES
B6: Tab | C6: Summary | D6: Notes
B7: Readiness | C7: 10 Indicators | D7: Summarizes readiness indicators
B8: Impact | C8: 7 Indicators | D8: Summarizes impact indicators
B10: Full information on data sources and other indicator details can be found in the methodology note [link to methodology note]
B12: READINESS INDICATORS
B13: Sub-Category | C13: Tab | D13: Summary
B14: Enabling Policies | C14: EV National Targets | D14: Official policies, ambitions, or targets to support EV deployment.
C15: EV Incentives | D15: Legally binding commitments such as standards, regulations, and exemptions.
B16: Grid Infrastructure | C16: Additional Capacity for 30% EVs | D16: Additional electricity generation necessary to meet the power demand of converting 30% of current road transportation to electric.
C17: Reliability | D17: Annual average duration of electricity outages in a country as reported in WB Enterprise Surveys OR SAIDI data reported in WB Doing Business.
B18: Market Potential | C18: Current rate of motorization | D18: The number of vehicles per 1,000 inhabitants as a proxy for potential market size (includes all vehicle classes).
C19: EV Charging infrastructure | D19: Number of public EV charging points as a proxy for EV deployment/penetration (Data was benchmarked against EV companies to account for non-traditional charging business models).
B20: Power Sector Maturity | C20: Electricity Regulatory Index | D20: AfDB’s composite index that assesses regulatory and legal dimensions of power sector development in African countries.
C21: Utility Financial Solvency | D21: Utility financial performance data from the World Bank, used as a proxy for utility quality.
B22: EV Affordability | C22: Relative Affordability of Electric Charging | D22: Cost ratio of electricity to gasoline needed for equivalent EV and ICE car models to travel 100 miles.
C23: Access to Finance Indicator | D23: % of population over the age of 15 years old that have borrowed money from a formal financial institution or using a mobile money account.
B25: IMPACT INDICATORS
B26: Sub-Category | C26: Tab | D26: Summary
B27: Climate | C27: % Electricity Generated from Clean Energy / Share of Clean Electricity Generation | D27: Percentage of electricity currently generated from clean energy sources.
C28: % CO2 from Transportation | D28: Percentage of CO2 from transportation calculated by Transport CO2/CO2 from fuel combustion*100.
B29: Public Health | C29: Urban Air Quality | D29: The Air Quality Index (AQI) is a common indicator (scale) for reporting daily air quality. The AQI measures carbon monoxide, nitrogen dioxide, sulfur dioxide, ozone, and 24-hour PM2.5 and PM10. Comprehensive urban AQI measurements for African countries is parse, with only real time data available for a select few countries. Due to the lack of real time data available, our indicator is a composite custom AQI constructed by getting a weighted average of the pollutants.
B30: Financial | C30: Fossil Fuel Import Dependence | D30: Current fossil fuel import burden as a proxy for energy security.
C31: Fossil Fuel Subsidy Burden | D31: Expenditure on explicit subsidies for gasoline and diesel consumers expressed as a % of GDP.
C32: Utility Revenue Potential | D32: Potential utility revenues from selling electricity if 30% of current road transport fleet is electrified.
B33: Cross-cutting | C33: Projected rate of motorization 2050 | D33: Projection of number of passenger cars per 1,000 inhabitants per country in 2050, with implications for scale. of impacts across all dimensions

Sheet Scoring - Readiness
B1: READINESS INDICATORS SCORING
B2: Link to full methodology [here]
B3: Sub-Category | C3: Indicator | D3: Low Readiness | E3: Medium Readiness | F3: High Readiness | G3: Scoring rationale
D4: 45294 | E4: 45325 | F4: 1
B5: Enabling Policies | C5: EV National Targets | D5: No | E5: - | F5: Yes | G5: High Readiness: At least one instance of the indicator is identified in the examined country Medium Readiness: N/A; this is a binary indicator Low Readiness: No instance of the indicator is identified in the examined country
C6: EV Incentives | D6: No | E6: - | F6: Yes | G6: High Readiness: At least one instance of the indicator is identified in the examined country Medium Readiness: N/A; this is a binary indicator Low Readiness: No instance of the indicator is identified in the examined country
B7: Grid Infrastrucutre | C7: Additional Generation for 30% EVs | D7: Large expansion [>1.25] | E7: Medium expansion [1.25-1.1] | F7: Modest expansion [<1.1] | G7: IEA projects Africa's overall electricity demand will grow 4% annually for the next two years (2024-26). In 10 years, a country's electricity demand will have grown ~50% at this rate. If meeting 30% EV penetration target requires more than half of this estimated 10 year growth, the readiness has been deemed as low.
C8: Grid Reliability | D8: Low WBES:[>250] SAIDI:[>20] | E8: Medium WBES:[50-250] SAIDI:[5-20] | F8: High WBES:[<50] SAIDI:[<5] | G8: Thresholds for WBES and SAIDI were benchmarked against EU + North America (High reliability) and Asia, Caribbean and South America (Medium reliability).
B9: Market | C9: Current Rate of Motorization | D9: Low [<100] | E9: Medium [100-200] | F9: High [>200] | G9: Most developed countries have a motorization rate north of 500, and many developing countries have rates below 150. Global average is 300 and developing country average is 180. Select examples: India 159; China 210; UK 579; EU average 560.
C10: EV Charging Infrastructure | D10: Low [<10] | E10: Medium [10-30] | F10: High [>30] | G10: Bounds are based on the spread of African EV charging point data (regional benchmarking).
B11: Power Sector Maturity | C11: Electricity Regulatory Index (as proxy for utility quality) | D11: Low [<0.5] | E11: Medium [0.5-0.8] | F11: High [>0.8] | G11: The ERI scores on AfDB’s Africa Energy Portal (AEP) are sorted into four categories. Our medium category is a combination of both ERI medium categories.
C12: Utility Cost Recovery | D12: Low [<85%] | E12: Medium [85-100%] | F12: High [>100%] | G12: Our scoring category cutoffs aligns with conventional cost recovery bounds. Mature utilities are profitable and cost recovery is the norm. The WB adopts this framework in their conclusion that the financial health of many Africa utilities is sub-par as they do not cover their costs.
B13: EV Affordability | C13: Relative Affordability | D13: EV pricier [>1] | E13: Comparable [0.75-1] | F13: EV cheaper [<0.75] | G13: This indicator compares the cost of operating an electric vehicle (EV) to that of a gasoline-powered internal combustion engine (ICE) vehicle, specifically looking at the cost to drive 100 miles. When EV charging is more expensive than gasoline, it reflects lower affordability for EVs in terms of operating costs. An "EV Pricier" rating means that the ICE vehicle is significantly cheaper to drive—costing 74.9% or less of what it would cost to drive an EV the same distance. "Parity" indicates that the operating costs of the two vehicle types are roughly equivalent, with the ICE vehicle costing between 75% and 100% of the EV's cost. When EVs are the more economical option, the indicator is labeled "EV Cheaper," meaning the ICE vehicle costs more than 100% of the EV's cost to drive 100 miles.
C14: Access to Finance Indicator - Borrowed any money from a formal financial institution or using a mobile money account (% age 15+) | D14: Low [<20%] | E14: Medium [20-40%] | F14: High [>40%] | G14: The world average in this indicator is 30% and has been chosen as a guide for the medium readiness category. The Middle East (11%), South Asia (12%), and SSA (14%) are on the lower ends and have guided the lower bounds of our indicator scoring in the low readiness category.

Sheet Scoring - Impact
B1: IMPACT INDICATORS SCORING
B2: Link to full methodology [here]
B3: Sub-Category | C3: Indicator | D3: Low Impact | E3: Medium Impact | F3: High Impact | G3: Scoring rationale
D4: 45294 | E4: 45325 | F4: 1
B5: Climate | C5: % Electricity Generated from Clean Energy | D5: Low [<33.33%] | E5: Medium [33.33-66.67%] | F5: High [>66.67%] | G5: The scoring has been divided into equal thirds, with more than two-thirds clean generation set as an ambitious bound for the highest category.
C6: % CO2 from Transportation | D6: Low [<33.33%] | E6: Medium [33-66.67%] | F6: High [>66.67%] | G6: he scoring has been divided into equal thirds.
B7: Public Health | C7: Urban Air Quality (AQI) | D7: Low [<100] | E7: Medium [100-200] | F7: High [>200] | G7: Custom AQI values were benchmarked against WHO interim air quality targets and categorized into low, moderate, high, very high, and serious. We further aggregated these into three high, medium and low categories.
B8: Financial | C8: Fossil Fuel Import Dependence | D8: Low [<33.33%] | E8: Medium [33.33-66.67%] | F8: High [>66.67%] | G8: The scoring has been divided into equal thirds.
C9: Subsidy Burden | D9: Low [0] | E9: Medium [>0-.5%] | F9: High [>0.5%] | G9: The average gasoline and diesel consumer subsidy burden in Africa is 0.57%, and has been used as a guide for the medium category. The low value is set at 0%, a decision guided by the fact that most countries are at 0% and the median is 0%.
C10: Utility Revenue Potential | D10: Low [<$30M] | E10: Medium [$30M-$110M] | F10: High [>$110M] | G10: Scoring categories have been selected based on the 33rd and 66th percentile to create low, medium, and high leverage categories (regional benchmarking). 33rd percentile: $30.3M, 66th percentile: 109.4M.
B11: Market Potential | C11: Projected Rate of Motorization (2050) | D11: Low [<100] | E11: Medium [100-200] | F11: High [>200] | G11: Most developed countries have a motorization rate north of 500, and many developing countries have rates below 150. Global average is 300 and developing country average is 180. Select examples: India 159; China 210; UK 579; EU average 560.

Sheet Main Sheet
A1: Country | B1: Readiness - Preparedness to adopt EVs at a large scale | L1: Impact - Broader benefits of EV adoption
B2: Enabling Policies | D2: Grid Infrastrucutre | F2: Market | H2: Power Sector Maturity | J2: EV Affordability | L2: Climate | N2: Public Health | O2: Financial | R2: Market Potential
B3: National Target (2023) | C3: EV Incentives (2023) | D3: Additional Generation for 30% EVs (multiplication factor) (2016-2022) | E3: Reliability (yearly average time without electricity, hours, various dates. SAIDI scores in yellow highlight. WBES scores w/o hightlight) (2010-2023) | F3: Current Rate of Motorization (2016) | G3: EV Charging Infrastructure (2024) | H3: ERI Score (2022) | I3: Utility Cost Recovery (Operating cost and debt service recovery, including subsidies) (2019) | J3: Relative Affordability - Gas vs Charging (EV cost per 100 miles / ICE cost per 100 miles) (2022-2024) | K3: Borrowed any money from a formal financial institution or using a mobile money account (% age 15+) (2014-2022) | L3: % Electricity generated from clean energy (2021) | M3: % CO2 Emissions from Transport (2020) | N3: Urban Air Quality (Custom AQI) (2019) | O3: Fossil Fuel Dependence (Ratio of transportation fuel consumption to net imports by country) (2021) | P3: Fossil Fuel Subsidy Burden (% of GDP, gasoline & diesel, explicit subsidies) (2023) | Q3: Utility Revenue Potential ($, 30% EVs) (2021) | R3: Projected rate of motorization (2050)
A4: Algeria | B4: =IF(countif('EV National Targets'!A:A,A4)>0, "1", "0") -> 1 | C4: =IF(countif('EV Incentives'!A:A,A4)>0, "1", "0") -> 0 | D4: {='Additional Generation For 30% E'!C2+1} -> 1.1664408 | E4: {='Grid Reliability'!K2} -> 4.2 | F4: {='Current Rate of Motorization'!B3} -> 30.183765 | G4: {='EV Charging Infrastructure'!B2} -> 6 | H4: {='Electricity Regulatory Index'!C2} -> 0.644 | I4: {=' Utility Cost Recovery'!B2} -> Not Found | J4: {='Relative Affordability'!F2} -> 0.26100215 | K4: {='Access to Finance'!C2} -> 0.04 | L4: {='Electricity Generated from Clea'!F2} -> 0.011696782 | M4: {='CO2 from Transportation'!E2} -> 0.30082794 | N4: {='Urban Air Quality'!I2} -> 193.23092 | O4: {='Fossil Fuel Import Dependence'!G2} -> -323.22222 | P4: {='Fossil Fuel Subsidy Burden'!E2} -> 0.074359566 | Q4: {='Utility Revenue Potential'!J2} -> 4.3874547e+08 | R4: {='Projected Rate of Motorization '!C2} -> 167.40233
A5: Angola | B5: =IF(countif('EV National Targets'!A:A,A5)>0, "1", "0") -> 0 | C5: =IF(countif('EV Incentives'!A:A,A5)>0, "1", "0") -> 1 | D5: {='Additional Generation For 30% E'!C3+1} -> 1.1015791 | E5: {='Grid Reliability'!K3} -> 12.8 | F5: {='Current Rate of Motorization'!B3} -> 30.183765 | G5: {='EV Charging Infrastructure'!B3} -> 2 | H5: {='Electricity Regulatory Index'!C3} -> 0.608 | I5: {=' Utility Cost Recovery'!B3} -> 0.73134225 | J5: {='Relative Affordability'!F3} -> 0.085032375 | K5: {='Access to Finance'!C3} -> Not Found | L5: {='Electricity Generated from Clea'!F3} -> 0.71323394 | M5: {='CO2 from Transportation'!E3} -> 0.37196201 | N5: {='Urban Air Quality'!I3} -> 320.40134 | O5: {='Fossil Fuel Import Dependence'!G3} -> 0.51760939 | P5: {='Fossil Fuel Subsidy Burden'!E3} -> 0.036522746 | Q5: {='Utility Revenue Potential'!J3} -> 20026599 | R5: {='Projected Rate of Motorization '!C3} -> 83.118222
A6: Benin | B6: =IF(countif('EV National Targets'!A:A,A6)>0, "1", "0") -> 0 | C6: =IF(countif('EV Incentives'!A:A,A6)>0, "1", "0") -> 1 | D6: {='Additional Generation For 30% E'!C4+1} -> 9.9972832 | E6: {='Grid Reliability'!F4} -> 1243.2 | F6: {='Current Rate of Motorization'!B4} -> 20.107308 | G6: {='EV Charging Infrastructure'!B4} -> Not Found | H6: {='Electricity Regulatory Index'!C4} -> 0.465 | I6: {=' Utility Cost Recovery'!B4} -> 0.92957926 | J6: {='Relative Affordability'!F4} -> 0.082832608 | K6: {='Access to Finance'!C4} -> 0.11 | L6: {='Electricity Generated from Clea'!F4} -> 0.033430489 | M6: {='CO2 from Transportation'!E4} -> 0.81071813 | N6: {='Urban Air Quality'!I4} -> 292.90165 | O6: {='Fossil Fuel Import Dependence'!G4} -> 0.99266324 | P6: {='Fossil Fuel Subsidy Burden'!E4} -> 0.005748186 | Q6: {='Utility Revenue Potential'!J4} -> 78092820 | R6: {='Projected Rate of Motorization '!C4} -> 122.42352
A7: Botswana | B7: =IF(countif('EV National Targets'!A:A,A7)>0, "1", "0") -> 0 | C7: =IF(countif('EV Incentives'!A:A,A7)>0, "1", "0") -> 0 | D7: {='Additional Generation For 30% E'!C5+1} -> 1.390465 | E7: {='Grid Reliability'!F5} -> 152.64 | F7: {='Current Rate of Motorization'!B5} -> 198.19921 | G7: {='EV Charging Infrastructure'!B5} -> 3 | H7: {='Electricity Regulatory Index'!C5} -> 0.527 | I7: {=' Utility Cost Recovery'!B5} -> 0.79266347 | J7: {='Relative Affordability'!F5} -> 0.26872867 | K7: {='Access to Finance'!C5} -> 0.11 | L7: {='Electricity Generated from Clea'!F5} -> 0.0027493322 | M7: {='CO2 from Transportation'!E5} -> 0.36920593 | N7: {='Urban Air Quality'!I5} -> 202.30469 | O7: {='Fossil Fuel Import Dependence'!G5} -> 0.82463856 | P7: {='Fossil Fuel Subsidy Burden'!E5} -> 0 | Q7: {='Utility Revenue Potential'!J5} -> 95438693 | R7: {='Projected Rate of Motorization '!C5} -> 399.46129
A8: Burkina Faso | B8: =IF(countif('EV National Targets'!A:A,A8)>0, "1", "0") -> 0 | C8: =IF(countif('EV Incentives'!A:A,A8)>0, "1", "0") -> 0 | D8: {='Additional Generation For 30% E'!C6+1} -> 1.5550016 | E8: {='Grid Reliability'!F6} -> 388.08 | F8: {='Current Rate of Motorization'!B6} -> 16.818502 | G8: {='EV Charging Infrastructure'!B6} -> 1 | H8: {='Electricity Regulatory Index'!C6} -> 0.495 | I8: {=' Utility Cost Recovery'!B6} -> 1.0414191 | J8: {='Relative Affordability'!F6} -> 0.82663283 | K8: {='Access to Finance'!C6} -> 0.09 | L8: {='Electricity Generated from Clea'!F6} -> 0.13299267 | M8: {='CO2 from Transportation'!E6} -> 0.54783967 | N8: {='Urban Air Quality'!I6} -> 251.65868 | O8: {='Fossil Fuel Import Dependence'!G6} -> 0.86084702 | P8: {='Fossil Fuel Subsidy Burden'!E6} -> 0.005313478 | Q8: {='Utility Revenue Potential'!J6} -> 4.3888597e+08 | R8: {='Projected Rate of Motorization '!C6} -> 67.572258
A9: Burundi | B9: =IF(countif('EV National Targets'!A:A,A9)>0, "1", "0") -> 0 | C9: =IF(countif('EV Incentives'!A:A,A9)>0, "1", "0") -> 0 | D9: {='Additional Generation For 30% E'!C7+1} -> 1.1524761 | E9: {='Grid Reliability'!F7} -> 956.16 | F9: {='Current Rate of Motorization'!B7} -> 4.0006138 | G9: {='EV Charging Infrastructure'!B7} -> Not Found | H9: {='Electricity Regulatory Index'!C7} -> 0.284 | I9: {=' Utility Cost Recovery'!B7} -> 1.1356048 | J9: {='Relative Affordability'!F7} -> 0.2892348 | K9: {='Access to Finance'!C7} -> Not Found | L9: {='Electricity Generated from Clea'!F7} -> 0.65305436 | M9: {='CO2 from Transportation'!E7} -> 0.79985925 | N9: {='Urban Air Quality'!I7} -> 281.19026 | O9: {='Fossil Fuel Import Dependence'!G7} -> 0.78947368 | P9: {='Fossil Fuel Subsidy Burden'!E7} -> 0 | Q9: {='Utility Revenue Potential'!J7} -> 8624416.7 | R9: {='Projected Rate of Motorization '!C7} -> 22.903843
A10: Cabo Verde | B10: =IF(countif('EV National Targets'!A:A,A10)>0, "1", "0") -> 1 | C10: =IF(countif('EV Incentives'!A:A,A10)>0, "1", "0") -> 1 | D10: {='Additional Generation For 30% E'!C8+1} -> 4.4049117 | E10: {='Grid Reliability'!K8} -> 18.3 | F10: {='Current Rate of Motorization'!B8} -> 4.2896671 | G10: {='EV Charging Infrastructure'!B8} -> Not Found | H10: {='Electricity Regulatory Index'!C8} -> 0.515 | I10: {=' Utility Cost Recovery'!B8} -> 0.96020938 | J10: {='Relative Affordability'!F8} -> 0.32589853 | K10: {='Access to Finance'!C8} -> Not Found | L10: {='Electricity Generated from Clea'!F8} -> 0.15977689 | M10: {='CO2 from Transportation'!E8} -> 0.46245569 | N10: {='Urban Air Quality'!I8} -> 179.60465 | O10: {='Fossil Fuel Import Dependence'!G8} -> 0.4966443 | P10: {='Fossil Fuel Subsidy Burden'!E8} -> 0 | Q10: {='Utility Revenue Potential'!J8} -> 14080887 | R10: {='Projected Rate of Motorization '!C8} -> 298.6468
A11: Cameroon | B11: =IF(countif('EV National Targets'!A:A,A11)>0, "1", "0") -> 0 | C11: =IF(countif('EV Incentives'!A:A,A11)>0, "1", "0") -> 0 | D11: {='Additional Generation For 30% E'!C9+1} -> 1.0087948 | E11: {='Grid Reliability'!F9} -> 793.44 | F11: {='Current Rate of Motorization'!B9} -> 116.32467 | G11: {='EV Charging Infrastructure'!B9} -> 5 | H11: {='Electricity Regulatory Index'!C9} -> 0.606 | I11: {=' Utility Cost Recovery'!B9} -> 0.69329753 | J11: {='Relative Affordability'!F9} -> 0.35545967 | K11: {='Access to Finance'!C9} -> 0.11 | L11: {='Electricity Generated from Clea'!F9} -> 0.62395322 | M11: {='CO2 from Transportation'!E9} -> 0.50090699 | N11: {='Urban Air Quality'!I9} -> 303.49876 | O11: {='Fossil Fuel Import Dependence'!G9} -> 1.0854922 | P11: {='Fossil Fuel Subsidy Burden'!E9} -> 0.0022912621 | Q11: {='Utility Revenue Potential'!J9} -> 2.3646186e+08 | R11: {='Projected Rate of Motorization '!C9} -> 102.64147
A12: Central African Republic | B12: =IF(countif('EV National Targets'!A:A,A12)>0, "1", "0") -> 0 | C12: =IF(countif('EV Incentives'!A:A,A12)>0, "1", "0") -> 0 | D12: {='Additional Generation For 30% E'!C10+1} -> 1.4951778 | E12: {='Grid Reliability'!F10} -> 2411.16 | F12: {='Current Rate of Motorization'!B10} -> 7.6414452 | G12: {='EV Charging Infrastructure'!B10} -> Not Found | H12: {='Electricity Regulatory Index'!C10} -> 0.292 | I12: {=' Utility Cost Recovery'!B10} -> 0.44246128 | J12: {='Relative Affordability'!F10} -> 0.21624707 | K12: {='Access to Finance'!C10} -> Not Found | L12: {='Electricity Generated from Clea'!F10} -> 0.99295663 | M12: {='CO2 from Transportation'!E10} -> 0.91293322 | N12: {='Urban Air Quality'!I10} -> 323.58562 | O12: {='Fossil Fuel Import Dependence'!G10} -> 0.83962264 | P12: {='Fossil Fuel Subsidy Burden'!E10} -> 0 | Q12: {='Utility Revenue Potential'!J10} -> 11369836 | R12: {='Projected Rate of Motorization '!C10} -> 20.600555
A13: Chad | B13: =IF(countif('EV National Targets'!A:A,A13)>0, "1", "0") -> 0 | C13: =IF(countif('EV Incentives'!A:A,A13)>0, "1", "0") -> 0 | D13: {='Additional Generation For 30% E'!C11+1} -> 2.2682715 | E13: {='Grid Reliability'!F11} -> 2881.08 | F13: {='Current Rate of Motorization'!B11} -> 77.025421 | G13: {='EV Charging Infrastructure'!B11} -> Not Found | H13: {='Electricity Regulatory Index'!C11} -> 0.147 | I13: {=' Utility Cost Recovery'!B11} -> 0.85134073 | J13: {='Relative Affordability'!F11} -> 0.47546416 | K13: {='Access to Finance'!C11} -> 0.1 | L13: {='Electricity Generated from Clea'!F11} -> 0.060813393 | M13: {='CO2 from Transportation'!E11} -> 0.76207426 | N13: {='Urban Air Quality'!I11} -> 274.25303 | O13: {='Fossil Fuel Import Dependence'!G11} -> -260.5 | P13: {='Fossil Fuel Subsidy Burden'!E11} -> 0 | Q13: {='Utility Revenue Potential'!J11} -> 60625647 | R13: {='Projected Rate of Motorization '!C11} -> 30.691011
A14: Comoros | B14: =IF(countif('EV National Targets'!A:A,A14)>0, "1", "0") -> 0 | C14: =IF(countif('EV Incentives'!A:A,A14)>0, "1", "0") -> 0 | D14: {='Additional Generation For 30% E'!C12+1} -> 1.1805057 | E14: {='Grid Reliability'!F12} -> Not Found | F14: {='Current Rate of Motorization'!B12} -> 46.765617 | G14: {='EV Charging Infrastructure'!B12} -> Not Found | H14: {='Electricity Regulatory Index'!C12} -> Not Found | I14: {=' Utility Cost Recovery'!B12} -> 1.0105691 | J14: {='Relative Affordability'!F12} -> 0.56517352 | K14: {='Access to Finance'!C12} -> 0.09 | L14: {='Electricity Generated from Clea'!F12} -> 0 | M14: {='CO2 from Transportation'!E12} -> 0.56611822 | N14: {='Urban Air Quality'!I12} -> 159.01925 | O14: {='Fossil Fuel Import Dependence'!G12} -> 0.81818182 | P14: {='Fossil Fuel Subsidy Burden'!E12} -> 0 | Q14: {='Utility Revenue Potential'!J12} -> 7530696.7 | R14: {='Projected Rate of Motorization '!C12} -> 103.05532
A15: Congo | B15: =IF(countif('EV National Targets'!A:A,A15)>0, "1", "0") -> 0 | C15: =IF(countif('EV Incentives'!A:A,A15)>0, "1", "0") -> 0 | D15: {='Additional Generation For 30% E'!C13+1} -> 1.1056025 | E15: {='Grid Reliability'!F13} -> 8849.4 | F15: {='Current Rate of Motorization'!B13} -> 4.3456265 | G15: {='EV Charging Infrastructure'!B13} -> 1 | H15: {='Electricity Regulatory Index'!C13} -> 0.101 | I15: {=' Utility Cost Recovery'!B13} -> Not Found | J15: {='Relative Affordability'!F13} -> 0.26079744 | K15: {='Access to Finance'!C13} -> 0.1 | L15: {='Electricity Generated from Clea'!F13} -> 0.2241695 | M15: {='CO2 from Transportation'!E13} -> 0.32391783 | N15: {='Urban Air Quality'!I13} -> 405.15523 | O15: {='Fossil Fuel Import Dependence'!G13} -> 3.4224138 | P15: {='Fossil Fuel Subsidy Burden'!E13} -> 0 | Q15: {='Utility Revenue Potential'!J13} -> 38633990 | R15: {='Projected Rate of Motorization '!C13} -> 125.87645
A16: Côte d'Ivoire | B16: =IF(countif('EV National Targets'!A:A,A16)>0, "1", "0") -> 0 | C16: =IF(countif('EV Incentives'!A:A,A16)>0, "1", "0") -> 0 | D16: {='Additional Generation For 30% E'!C14+1} -> 2.4488589 | E16: {='Grid Reliability'!F14} -> 155.4 | F16: {='Current Rate of Motorization'!B14} -> 3.0659601 | G16: {='EV Charging Infrastructure'!B14} -> 1 | H16: {='Electricity Regulatory Index'!C14} -> 0.573 | I16: {=' Utility Cost Recovery'!B14} -> 0.91329021 | J16: {='Relative Affordability'!F14} -> 0.38987418 | K16: {='Access to Finance'!C14} -> 0.08 | L16: {='Electricity Generated from Clea'!F15} -> 0.020963305 | M16: {='CO2 from Transportation'!E14} -> 0.38517422 | N16: {='Urban Air Quality'!I14} -> 302.3763 | O16: {='Fossil Fuel Import Dependence'!G14} -> -2.897281 | P16: {='Fossil Fuel Subsidy Burden'!E14} -> 0.0014281896 | Q16: {='Utility Revenue Potential'!J14} -> 3.3570532e+08 | R16: {='Projected Rate of Motorization '!C14} -> 214.39407
A17: Djibouti | B17: =IF(countif('EV National Targets'!A:A,A17)>0, "1", "0") -> 0 | C17: =IF(countif('EV Incentives'!A:A,A17)>0, "1", "0") -> 0 | D17: {='Additional Generation For 30% E'!C15+1} -> 1.060249 | E17: {='Grid Reliability'!F15} -> 28.8 | F17: {='Current Rate of Motorization'!B15} -> 39.090711 | G17: {='EV Charging Infrastructure'!B15} -> Not Found | H17: {='Electricity Regulatory Index'!C15} -> Not Found | I17: {=' Utility Cost Recovery'!B15} -> Not Found | J17: {='Relative Affordability'!F15} -> 0.5471275 | K17: {='Access to Finance'!C15} -> Not Found | L17: {='Electricity Generated from Clea'!F16} -> 0.999489 | M17: {='CO2 from Transportation'!E15} -> 0.41410218 | N17: {='Urban Air Quality'!I15} -> 161.86394 | O17: {='Fossil Fuel Import Dependence'!G15} -> 0.88571429 | P17: {='Fossil Fuel Subsidy Burden'!E15} -> 0 | Q17: {='Utility Revenue Potential'!J15} -> 24340829 | R17: {='Projected Rate of Motorization '!C15} -> 303.84345
A18: DR Congo | B18: =IF(countif('EV National Targets'!A:A,A18)>0, "1", "0") -> 0 | C18: =IF(countif('EV Incentives'!A:A,A18)>0, "1", "0") -> 1 | D18: {='Additional Generation For 30% E'!C16+1} -> 1.1505815 | E18: {='Grid Reliability'!F16} -> 826.56 | F18: {='Current Rate of Motorization'!B16} -> 0.72683642 | G18: {='EV Charging Infrastructure'!B16} -> 1 | H18: {='Electricity Regulatory Index'!C16} -> 0.527 | I18: {=' Utility Cost Recovery'!B16} -> 0.76470188 | J18: {='Relative Affordability'!F16} -> 0.1665452 | K18: {='Access to Finance'!C16} -> 0.05 | L18: {='Electricity Generated from Clea'!F14} -> 0.30148712 | M18: {='CO2 from Transportation'!E16} -> 0.99630822 | N18: {='Urban Air Quality'!I16} -> 293.77668 | O18: {='Fossil Fuel Import Dependence'!G16} -> 1 | P18: {='Fossil Fuel Subsidy Burden'!E16} -> 0 | Q18: {='Utility Revenue Potential'!J16} -> 51879930 | R18: {='Projected Rate of Motorization '!C16} -> 37.654797
A19: Egypt | B19: =IF(countif('EV National Targets'!A:A,A19)>0, "1", "0") -> 0 | C19: =IF(countif('EV Incentives'!A:A,A19)>0, "1", "0") -> 1 | D19: {='Additional Generation For 30% E'!C17+1} -> 1.0743223 | E19: {='Grid Reliability'!F17} -> 8.64 | F19: {='Current Rate of Motorization'!B17} -> 61.866593 | G19: {='EV Charging Infrastructure'!B17} -> 48 | H19: {='Electricity Regulatory Index'!C17} -> 0.785 | I19: {=' Utility Cost Recovery'!B17} -> Not Found | J19: {='Relative Affordability'!F17} -> 0.25654481 | K19: {='Access to Finance'!C17} -> 0.08 | L19: {='Electricity Generated from Clea'!F17} -> 0.11551545 | M19: {='CO2 from Transportation'!E17} -> 0.27374711 | N19: {='Urban Air Quality'!I17} -> 257.36063 | O19: {='Fossil Fuel Import Dependence'!G17} -> 4.0939879 | P19: {='Fossil Fuel Subsidy Burden'!E17} -> 0.031043672 | Q19: {='Utility Revenue Potential'!J17} -> 5.5618694e+08 | R19: {='Projected Rate of Motorization '!C17} -> 324.06148
A20: Equatorial Guinea | B20: =IF(countif('EV National Targets'!A:A,A20)>0, "1", "0") -> 0 | C20: =IF(countif('EV Incentives'!A:A,A20)>0, "1", "0") -> 0 | D20: {='Additional Generation For 30% E'!C18+1} -> 1.0185327 | E20: {='Grid Reliability'!F18} -> Not Found | F20: {='Current Rate of Motorization'!B18} -> 102.2212 | G20: {='EV Charging Infrastructure'!B18} -> Not Found | H20: {='Electricity Regulatory Index'!C18} -> Not Found | I20: {=' Utility Cost Recovery'!B18} -> Not Found | J20: {='Relative Affordability'!F18} -> 0.60900502 | K20: {='Access to Finance'!C18} -> Not Found | L20: {='Electricity Generated from Clea'!F18} -> 0.31026894 | M20: {='CO2 from Transportation'!E18} -> 0.11366801 | N20: {='Urban Air Quality'!I18} -> 295.8785 | O20: {='Fossil Fuel Import Dependence'!G18} -> 0.87837838 | P20: {='Fossil Fuel Subsidy Burden'!E18} -> 0.008312805 | Q20: {='Utility Revenue Potential'!J18} -> 4467876.4 | R20: {='Projected Rate of Motorization '!C18} -> 161.10185
A21: Eritrea | B21: =IF(countif('EV National Targets'!A:A,A21)>0, "1", "0") -> 0 | C21: =IF(countif('EV Incentives'!A:A,A21)>0, "1", "0") -> 0 | D21: {='Additional Generation For 30% E'!C19+1} -> 1.2142775 | E21: {='Grid Reliability'!F19} -> 16.8 | F21: {='Current Rate of Motorization'!B19} -> 21.515253 | G21: {='EV Charging Infrastructure'!B19} -> 2 | H21: {='Electricity Regulatory Index'!C19} -> Not Found | I21: {=' Utility Cost Recovery'!B19} -> Not Found | J21: {='Relative Affordability'!F19} -> 0.30951784 | K21: {='Access to Finance'!C19} -> Not Found | L21: {='Electricity Generated from Clea'!F19} -> 0.037538075 | M21: {='CO2 from Transportation'!E19} -> 0.36377321 | N21: {='Urban Air Quality'!I19} -> 154.57531 | O21: {='Fossil Fuel Import Dependence'!G19} -> 0.16666667 | P21: {='Fossil Fuel Subsidy Burden'!E19} -> Not Found | Q21: {='Utility Revenue Potential'!J19} -> 23289564 | R21: {='Projected Rate of Motorization '!C19} -> Not Found
A22: Eswatini | B22: =IF(countif('EV National Targets'!A:A,A22)>0, "1", "0") -> 0 | C22: =IF(countif('EV Incentives'!A:A,A22)>0, "1", "0") -> 0 | D22: {='Additional Generation For 30% E'!C20+1} -> 1.3148713 | E22: {='Grid Reliability'!K20} -> 164.28 | F22: {='Current Rate of Motorization'!B20} -> 87.37672 | G22: {='EV Charging Infrastructure'!B20} -> Not Found | H22: {='Electricity Regulatory Index'!C20} -> 0.621 | I22: {=' Utility Cost Recovery'!B20} -> 1.1157487 | J22: {='Relative Affordability'!F20} -> 0.1424021 | K22: {='Access to Finance'!C20} -> 0.33 | L22: {='Electricity Generated from Clea'!F20} -> 0.5930843 | M22: {='CO2 from Transportation'!E20} -> 0.61854143 | N22: {='Urban Air Quality'!I20} -> 220.02144 | O22: {='Fossil Fuel Import Dependence'!G20} -> 0.91954023 | P22: {='Fossil Fuel Subsidy Burden'!E20} -> Not Found | Q22: {='Utility Revenue Potential'!J20} -> 14539804 | R22: {='Projected Rate of Motorization '!C20} -> 180.1834
A23: Ethiopia | B23: =IF(countif('EV National Targets'!A:A,A23)>0, "1", "0") -> 1 | C23: =IF(countif('EV Incentives'!A:A,A23)>0, "1", "0") -> 1 | D23: {='Additional Generation For 30% E'!C21+1} -> 1.1463412 | E23: {='Grid Reliability'!F21} -> 570.72 | F23: {='Current Rate of Motorization'!B21} -> 6.7280939 | G23: {='EV Charging Infrastructure'!B21} -> 10 | H23: {='Electricity Regulatory Index'!C21} -> 0.561 | I23: {=' Utility Cost Recovery'!B21} -> 1.0270192 | J23: {='Relative Affordability'!F21} -> 0.047120138 | K23: {='Access to Finance'!C21} -> 0.05 | L23: {='Electricity Generated from Clea'!F21} -> 0.99965588 | M23: {='CO2 from Transportation'!E21} -> 0.51590766 | N23: {='Urban Air Quality'!I21} -> 143.28886 | O23: {='Fossil Fuel Import Dependence'!G21} -> 0.67662566 | P23: {='Fossil Fuel Subsidy Burden'!E21} -> 0.020507405 | Q23: {='Utility Revenue Potential'!J21} -> 49404403 | R23: {='Projected Rate of Motorization '!C21} -> 123.99302
A24: Gabon | B24: =IF(countif('EV National Targets'!A:A,A24)>0, "1", "0") -> 0 | C24: =IF(countif('EV Incentives'!A:A,A24)>0, "1", "0") -> 0 | D24: {='Additional Generation For 30% E'!C22+1} -> 1.1472259 | E24: {='Grid Reliability'!K22} -> 47.5 | F24: {='Current Rate of Motorization'!B22} -> 27.13059 | G24: {='EV Charging Infrastructure'!B22} -> Not Found | H24: {='Electricity Regulatory Index'!C22} -> 0.168 | I24: {=' Utility Cost Recovery'!B22} -> 0.90680841 | J24: {='Relative Affordability'!F22} -> 0.49154455 | K24: {='Access to Finance'!C22} -> 0.12 | L24: {='Electricity Generated from Clea'!F22} -> 0.44326082 | M24: {='CO2 from Transportation'!E22} -> 0.075063412 | N24: {='Urban Air Quality'!I22} -> 354.71596 | O24: {='Fossil Fuel Import Dependence'!G22} -> 0.28078818 | P24: {='Fossil Fuel Subsidy Burden'!E22} -> 0 | Q24: {='Utility Revenue Potential'!J22} -> 63955326 | R24: {='Projected Rate of Motorization '!C22} -> 271.31349
A25: Gambia | B25: =IF(countif('EV National Targets'!A:A,A25)>0, "1", "0") -> 1 | C25: =IF(countif('EV Incentives'!A:A,A25)>0, "1", "0") -> 0 | D25: {='Additional Generation For 30% E'!C23+1} -> 1.2199459 | E25: {='Grid Reliability'!F23} -> 191.52 | F25: {='Current Rate of Motorization'!B23} -> 36.66614 | G25: {='EV Charging Infrastructure'!B23} -> Not Found | H25: {='Electricity Regulatory Index'!C23} -> 0.298 | I25: {=' Utility Cost Recovery'!B23} -> 0.66677307 | J25: {='Relative Affordability'!F23} -> 0.4371721 | K25: {='Access to Finance'!C23} -> 0.06 | L25: {='Electricity Generated from Clea'!F23} -> 0.010067491 | M25: {='CO2 from Transportation'!E23} -> 0.1329735 | N25: {='Urban Air Quality'!I23} -> 205.18757 | O25: {='Fossil Fuel Import Dependence'!G23} -> 0.61206897 | P25: {='Fossil Fuel Subsidy Burden'!E23} -> 0 | Q25: {='Utility Revenue Potential'!J23} -> 13545146 | R25: {='Projected Rate of Motorization '!C23} -> 67.692365
A26: Ghana | B26: =IF(countif('EV National Targets'!A:A,A26)>0, "1", "0") -> 1 | C26: =IF(countif('EV Incentives'!A:A,A26)>0, "1", "0") -> 1 | D26: {='Additional Generation For 30% E'!C24+1} -> 1.122764 | E26: {='Grid Reliability'!F24} -> 107.88 | F26: {='Current Rate of Motorization'!B24} -> 69.417844 | G26: {='EV Charging Infrastructure'!B24} -> 3 | H26: {='Electricity Regulatory Index'!C24} -> 0.709 | I26: {=' Utility Cost Recovery'!B24} -> 1.0328751 | J26: {='Relative Affordability'!F24} -> 0.19721569 | K26: {='Access to Finance'!C24} -> 0.17 | L26: {='Electricity Generated from Clea'!F24} -> 0.34829234 | M26: {='CO2 from Transportation'!E24} -> 0.48124547 | N26: {='Urban Air Quality'!I24} -> 284.85389 | O26: {='Fossil Fuel Import Dependence'!G24} -> 0.94673395 | P26: {='Fossil Fuel Subsidy Burden'!E24} -> 0 | Q26: {='Utility Revenue Potential'!J24} -> 2.2868856e+08 | R26: {='Projected Rate of Motorization '!C24} -> 170.54704
A27: Guinea | B27: =IF(countif('EV National Targets'!A:A,A27)>0, "1", "0") -> 0 | C27: =IF(countif('EV Incentives'!A:A,A27)>0, "1", "0") -> 0 | D27: {='Additional Generation For 30% E'!C25+1} -> 1.1658849 | E27: {='Grid Reliability'!F25} -> 172.8 | F27: {='Current Rate of Motorization'!B25} -> 26.758394 | G27: {='EV Charging Infrastructure'!B25} -> Not Found | H27: {='Electricity Regulatory Index'!C25} -> 0.306 | I27: {=' Utility Cost Recovery'!B25} -> 0.65530793 | J27: {='Relative Affordability'!F25} -> 0.4222773 | K27: {='Access to Finance'!C25} -> 0.08 | L27: {='Electricity Generated from Clea'!F25} -> 0.72732588 | M27: {='CO2 from Transportation'!E25} -> 0.45490205 | N27: {='Urban Air Quality'!I25} -> 296.69464 | O27: {='Fossil Fuel Import Dependence'!G25} -> 0.80291971 | P27: {='Fossil Fuel Subsidy Burden'!E25} -> 0 | Q27: {='Utility Revenue Potential'!J25} -> 85273769 | R27: {='Projected Rate of Motorization '!C25} -> 105.88811
A28: Guinea-Bissau | B28: =IF(countif('EV National Targets'!A:A,A28)>0, "1", "0") -> 0 | C28: =IF(countif('EV Incentives'!A:A,A28)>0, "1", "0") -> 0 | D28: {='Additional Generation For 30% E'!C26+1} -> 1.4901597 | E28: {='Grid Reliability'!F26} -> 1116.96 | F28: {='Current Rate of Motorization'!B26} -> 33.925994 | G28: {='EV Charging Infrastructure'!B26} -> Not Found | H28: {='Electricity Regulatory Index'!C26} -> Not Found | I28: {=' Utility Cost Recovery'!B26} -> 0.81999098 | J28: {='Relative Affordability'!F26} -> 0.88300887 | K28: {='Access to Finance'!C26} -> Not Found | L28: {='Electricity Generated from Clea'!F26} -> 0.024254772 | M28: {='CO2 from Transportation'!E26} -> 0.36109422 | N28: {='Urban Air Quality'!I26} -> 241.04054 | O28: {='Fossil Fuel Import Dependence'!G26} -> 0.57746479 | P28: {='Fossil Fuel Subsidy Burden'!E26} -> 0 | Q28: {='Utility Revenue Potential'!J26} -> 15364643 | R28: {='Projected Rate of Motorization '!C26} -> 63.827001
A29: Kenya | B29: =IF(countif('EV National Targets'!A:A,A29)>0, "1", "0") -> 1 | C29: =IF(countif('EV Incentives'!A:A,A29)>0, "1", "0") -> 1 | D29: {='Additional Generation For 30% E'!C27+1} -> 1.2520136 | E29: {='Grid Reliability'!F27} -> 264.48 | F29: {='Current Rate of Motorization'!B27} -> 53.906771 | G29: {='EV Charging Infrastructure'!B27} -> 18 | H29: {='Electricity Regulatory Index'!C27} -> 0.695 | I29: {=' Utility Cost Recovery'!B27} -> 0.89335742 | J29: {='Relative Affordability'!F27} -> 0.2728122 | K29: {='Access to Finance'!C27} -> 0.4 | L29: {='Electricity Generated from Clea'!F27} -> 0.91985277 | M29: {='CO2 from Transportation'!E27} -> 0.66008455 | N29: {='Urban Air Quality'!I27} -> 150.175 | O29: {='Fossil Fuel Import Dependence'!G27} -> 0.85497889 | P29: {='Fossil Fuel Subsidy Burden'!E27} -> 0 | Q29: {='Utility Revenue Potential'!J27} -> 4.2641938e+08 | R29: {='Projected Rate of Motorization '!C27} -> 173.87863
A30: Lesotho | B30: =IF(countif('EV National Targets'!A:A,A30)>0, "1", "0") -> 0 | C30: =IF(countif('EV Incentives'!A:A,A30)>0, "1", "0") -> 0 | D30: {='Additional Generation For 30% E'!C28+1} -> 1.3166286 | E30: {='Grid Reliability'!F28} -> 98.04 | F30: {='Current Rate of Motorization'!B28} -> 390.28683 | G30: {='EV Charging Infrastructure'!B28} -> Not Found | H30: {='Electricity Regulatory Index'!C28} -> 0.49 | I30: {=' Utility Cost Recovery'!B28} -> 0.9839143 | J30: {='Relative Affordability'!F28} -> 0.043254185 | K30: {='Access to Finance'!C28} -> 0.19 | L30: {='Electricity Generated from Clea'!F28} -> 1 | M30: {='CO2 from Transportation'!E28} -> 0.23275228 | N30: {='Urban Air Quality'!I28} -> 177.97847 | O30: {='Fossil Fuel Import Dependence'!G28} -> 0.77729258 | P30: {='Fossil Fuel Subsidy Burden'!E28} -> 0 | Q30: {='Utility Revenue Potential'!J28} -> 3015311.2 | R30: {='Projected Rate of Motorization '!C28} -> 64.130654
A31: Liberia | B31: =IF(countif('EV National Targets'!A:A,A31)>0, "1", "0") -> 0 | C31: =IF(countif('EV Incentives'!A:A,A31)>0, "1", "0") -> 0 | D31: {='Additional Generation For 30% E'!C29+1} -> 1.0977625 | E31: {='Grid Reliability'!F29} -> 448.2 | F31: {='Current Rate of Motorization'!B29} -> 13.386889 | G31: {='EV Charging Infrastructure'!B29} -> Not Found | H31: {='Electricity Regulatory Index'!C29} -> 0.628 | I31: {=' Utility Cost Recovery'!B29} -> 0.96066649 | J31: {='Relative Affordability'!F29} -> 0.66403651 | K31: {='Access to Finance'!C29} -> 0.17 | L31: {='Electricity Generated from Clea'!F29} -> 0.58028845 | M31: {='CO2 from Transportation'!E29} -> 0.61121477 | N31: {='Urban Air Quality'!I29} -> 278.72428 | O31: {='Fossil Fuel Import Dependence'!G29} -> 0.47058824 | P31: {='Fossil Fuel Subsidy Burden'!E29} -> 0 | Q31: {='Utility Revenue Potential'!J29} -> 21771295 | R31: {='Projected Rate of Motorization '!C29} -> 75.529086
A32: Libya | B32: =IF(countif('EV National Targets'!A:A,A32)>0, "1", "0") -> 0 | C32: =IF(countif('EV Incentives'!A:A,A32)>0, "1", "0") -> 0 | D32: {='Additional Generation For 30% E'!C30+1} -> 1.4325801 | E32: {='Grid Reliability'!K30} -> 1883.4 | F32: {='Current Rate of Motorization'!B30} -> 436.15322 | G32: {='EV Charging Infrastructure'!B30} -> 10 | H32: {='Electricity Regulatory Index'!C30} -> Not Found | I32: {=' Utility Cost Recovery'!B30} -> Not Found | J32: {='Relative Affordability'!F30} -> 3.4113526 | K32: {='Access to Finance'!C30} -> Not Found | L32: {='Electricity Generated from Clea'!F30} -> 0.00024984004 | M32: {='CO2 from Transportation'!E30} -> 0.42673024 | N32: {='Urban Air Quality'!I30} -> 194.2928 | O32: {='Fossil Fuel Import Dependence'!G30} -> 1.0972273 | P32: {='Fossil Fuel Subsidy Burden'!E30} -> 0.037156573 | Q32: {='Utility Revenue Potential'!J30} -> 5.6790854e+08 | R32: {='Projected Rate of Motorization '!C30} -> 342.88149
A33: Madagascar | B33: =IF(countif('EV National Targets'!A:A,A33)>0, "1", "0") -> 0 | C33: =IF(countif('EV Incentives'!A:A,A33)>0, "1", "0") -> 1 | D33: {='Additional Generation For 30% E'!C31+1} -> 1.3351523 | E33: {='Grid Reliability'!F31} -> 294.84 | F33: {='Current Rate of Motorization'!B31} -> 9.2925868 | G33: {='EV Charging Infrastructure'!B31} -> 2 | H33: {='Electricity Regulatory Index'!C31} -> 0.329 | I33: {=' Utility Cost Recovery'!B31} -> 0.66304927 | J33: {='Relative Affordability'!F31} -> 0.1935474 | K33: {='Access to Finance'!C31} -> 0.09 | L33: {='Electricity Generated from Clea'!F31} -> 0.35519559 | M33: {='CO2 from Transportation'!E31} -> 0.44038867 | N33: {='Urban Air Quality'!I31} -> 187.95872 | O33: {='Fossil Fuel Import Dependence'!G31} -> 0.75560081 | P33: {='Fossil Fuel Subsidy Burden'!E31} -> 0.0065371471 | Q33: {='Utility Revenue Potential'!J31} -> 68748691 | R33: {='Projected Rate of Motorization '!C31} -> 40.539373
A34: Malawi | B34: =IF(countif('EV National Targets'!A:A,A34)>0, "1", "0") -> 0 | C34: =IF(countif('EV Incentives'!A:A,A34)>0, "1", "0") -> 1 | D34: {='Additional Generation For 30% E'!C32+1} -> 1.156827 | E34: {='Grid Reliability'!F32} -> 345.72 | F34: {='Current Rate of Motorization'!B32} -> 16.715 | G34: {='EV Charging Infrastructure'!B32} -> Not Found | H34: {='Electricity Regulatory Index'!C32} -> 0.479 | I34: {=' Utility Cost Recovery'!B32} -> 0.9244442 | J34: {='Relative Affordability'!F32} -> 0.23069653 | K34: {='Access to Finance'!C32} -> 0.1 | L34: {='Electricity Generated from Clea'!F32} -> 0.85957368 | M34: {='CO2 from Transportation'!E32} -> 0.75303907 | N34: {='Urban Air Quality'!I32} -> 229.79604 | O34: {='Fossil Fuel Import Dependence'!G32} -> 0.74233129 | P34: {='Fossil Fuel Subsidy Burden'!E32} -> 0 | Q34: {='Utility Revenue Potential'!J32} -> 32168710 | R34: {='Projected Rate of Motorization '!C32} -> 46.351633
A35: Mali | B35: =IF(countif('EV National Targets'!A:A,A35)>0, "1", "0") -> 0 | C35: =IF(countif('EV Incentives'!A:A,A35)>0, "1", "0") -> 0 | D35: {='Additional Generation For 30% E'!C33+1} -> 1.2231562 | E35: {='Grid Reliability'!F33} -> 257.04 | F35: {='Current Rate of Motorization'!B33} -> 18.414067 | G35: {='EV Charging Infrastructure'!B33} -> 2 | H35: {='Electricity Regulatory Index'!C33} -> 0.45 | I35: {=' Utility Cost Recovery'!B33} -> 0.83303821 | J35: {='Relative Affordability'!F33} -> 0.28197141 | K35: {='Access to Finance'!C33} -> 0.13 | L35: {='Electricity Generated from Clea'!F33} -> 0.3225882 | M35: {='CO2 from Transportation'!E33} -> 0.4200028 | N35: {='Urban Air Quality'!I33} -> 251.7394 | O35: {='Fossil Fuel Import Dependence'!G33} -> 0.77553311 | P35: {='Fossil Fuel Subsidy Burden'!E33} -> 0 | Q35: {='Utility Revenue Potential'!J33} -> 1.1795194e+08 | R35: {='Projected Rate of Motorization '!C33} -> 57.348575
A36: Mauritania | B36: =IF(countif('EV National Targets'!A:A,A36)>0, "1", "0") -> 0 | C36: =IF(countif('EV Incentives'!A:A,A36)>0, "1", "0") -> 0 | D36: {='Additional Generation For 30% E'!C34+1} -> 1.1724362 | E36: {='Grid Reliability'!F34} -> 165.36 | F36: {='Current Rate of Motorization'!B34} -> 10.118735 | G36: {='EV Charging Infrastructure'!B34} -> 5 | H36: {='Electricity Regulatory Index'!C34} -> 0.226 | I36: {=' Utility Cost Recovery'!B34} -> 0.46432605 | J36: {='Relative Affordability'!F34} -> 0.36977796 | K36: {='Access to Finance'!C34} -> 0.12 | L36: {='Electricity Generated from Clea'!F34} -> 0.2659655 | M36: {='CO2 from Transportation'!E34} -> 0.44233319 | N36: {='Urban Air Quality'!I34} -> 188.39258 | O36: {='Fossil Fuel Import Dependence'!G34} -> 0.60697306 | P36: {='Fossil Fuel Subsidy Burden'!E34} -> 0 | Q36: {='Utility Revenue Potential'!J34} -> 52401519 | R36: {='Projected Rate of Motorization '!C34} -> 82.68596
A37: Mauritius | B37: =IF(countif('EV National Targets'!A:A,A37)>0, "1", "0") -> 0 | C37: =IF(countif('EV Incentives'!A:A,A37)>0, "1", "0") -> 1 | D37: {='Additional Generation For 30% E'!C35+1} -> 1.1247071 | E37: {='Grid Reliability'!F35} -> 48 | F37: {='Current Rate of Motorization'!B35} -> 401.72281 | G37: {='EV Charging Infrastructure'!B35} -> 31 | H37: {='Electricity Regulatory Index'!C35} -> 0.32 | I37: {=' Utility Cost Recovery'!B35} -> 1.0551605 | J37: {='Relative Affordability'!F35} -> 0.20246605 | K37: {='Access to Finance'!C35} -> 0.2 | L37: {='Electricity Generated from Clea'!F35} -> 0.23920742 | M37: {='CO2 from Transportation'!E35} -> 0.27210903 | N37: {='Urban Air Quality'!I35} -> 192.98179 | O37: {='Fossil Fuel Import Dependence'!G35} -> 0.79318735 | P37: {='Fossil Fuel Subsidy Burden'!E35} -> 0 | Q37: {='Utility Revenue Potential'!J35} -> 42822877 | R37: {='Projected Rate of Motorization '!C35} -> 642.65853
A38: Morocco | B38: =IF(countif('EV National Targets'!A:A,A38)>0, "1", "0") -> 1 | C38: =IF(countif('EV Incentives'!A:A,A38)>0, "1", "0") -> 1 | D38: {='Additional Generation For 30% E'!C36+1} -> 1.1397201 | E38: {='Grid Reliability'!F36} -> 0.72 | F38: {='Current Rate of Motorization'!B36} -> 104.79005 | G38: T | H38: {='Electricity Regulatory Index'!C36} -> Not Found | I38: {=' Utility Cost Recovery'!B36} -> 1.1086 | J38: {='Relative Affordability'!F36} -> 0.18461001 | K38: {='Access to Finance'!C36} -> 0.05 | L38: {='Electricity Generated from Clea'!F36} -> 0.19879636 | M38: {='CO2 from Transportation'!E36} -> 0.26739569 | N38: {='Urban Air Quality'!I36} -> 171.0313 | O38: {='Fossil Fuel Import Dependence'!G36} -> 0.84156408 | P38: {='Fossil Fuel Subsidy Burden'!E36} -> 0 | Q38: {='Utility Revenue Potential'!J36} -> 6.0945878e+08 | R38: {='Projected Rate of Motorization '!C36} -> 223.2537
A39: Mozambique | B39: =IF(countif('EV National Targets'!A:A,A39)>0, "1", "0") -> 1 | C39: =IF(countif('EV Incentives'!A:A,A39)>0, "1", "0") -> 0 | D39: {='Additional Generation For 30% E'!C37+1} -> 1.0680904 | E39: {='Grid Reliability'!F37} -> 103.68 | F39: {='Current Rate of Motorization'!B37} -> 25.232942 | G39: {='EV Charging Infrastructure'!B37} -> Not Found | H39: {='Electricity Regulatory Index'!C37} -> 0.372 | I39: {=' Utility Cost Recovery'!B37} -> 1.0694158 | J39: {='Relative Affordability'!F37} -> 0.15284832 | K39: {='Access to Finance'!C37} -> 0.15 | L39: {='Electricity Generated from Clea'!F37} -> 0.81325134 | M39: {='CO2 from Transportation'!E37} -> 0.56015526 | N39: {='Urban Air Quality'!I37} -> 235.89201 | O39: {='Fossil Fuel Import Dependence'!G37} -> 0.93195021 | P39: {='Fossil Fuel Subsidy Burden'!E37} -> 0 | Q39: {='Utility Revenue Potential'!J37} -> 1.0844203e+08 | R39: {='Projected Rate of Motorization '!C37} -> 74.91192
A40: Namibia | B40: =IF(countif('EV National Targets'!A:A,A40)>0, "1", "0") -> 1 | C40: =IF(countif('EV Incentives'!A:A,A40)>0, "1", "0") -> 0 | D40: {='Additional Generation For 30% E'!C38+1} -> 1.4798864 | E40: {='Grid Reliability'!F38} -> 41.76 | F40: {='Current Rate of Motorization'!B38} -> 152.94023 | G40: {='EV Charging Infrastructure'!B38} -> 6 | H40: {='Electricity Regulatory Index'!C38} -> 0.618 | I40: {=' Utility Cost Recovery'!B38} -> 1.0610175 | J40: {='Relative Affordability'!F38} -> 0.28745382 | K40: {='Access to Finance'!C38} -> 0.23 | L40: {='Electricity Generated from Clea'!F38} -> 0.95586922 | M40: {='CO2 from Transportation'!E38} -> 0.53451195 | N40: {='Urban Air Quality'!I38} -> 173.39559 | O40: {='Fossil Fuel Import Dependence'!G38} -> 0.56798457 | P40: {='Fossil Fuel Subsidy Burden'!E38} -> 0 | Q40: {='Utility Revenue Potential'!J38} -> 1.1130471e+08 | R40: {='Projected Rate of Motorization '!C38} -> 205.31589
A41: Niger | B41: =IF(countif('EV National Targets'!A:A,A41)>0, "1", "0") -> 0 | C41: =IF(countif('EV Incentives'!A:A,A41)>0, "1", "0") -> 0 | D41: {='Additional Generation For 30% E'!C39+1} -> 1.7286688 | E41: {='Grid Reliability'!F39} -> 1372.8 | F41: {='Current Rate of Motorization'!B39} -> 20.864418 | G41: {='EV Charging Infrastructure'!B39} -> 1 | H41: {='Electricity Regulatory Index'!C39} -> 0.478 | I41: {=' Utility Cost Recovery'!B39} -> 1.0209632 | J41: {='Relative Affordability'!F39} -> 0.69967635 | K41: {='Access to Finance'!C39} -> 0.04 | L41: {='Electricity Generated from Clea'!F39} -> 0.10202905 | M41: {='CO2 from Transportation'!E39} -> 0.53569226 | N41: {='Urban Air Quality'!I39} -> 223.30344 | O41: {='Fossil Fuel Import Dependence'!G39} -> -1.24 | P41: {='Fossil Fuel Subsidy Burden'!E39} -> 0 | Q41: {='Utility Revenue Potential'!J39} -> 77530797 | R41: {='Projected Rate of Motorization '!C39} -> 45.312236
A42: Nigeria | B42: =IF(countif('EV National Targets'!A:A,A42)>0, "1", "0") -> 1 | C42: =IF(countif('EV Incentives'!A:A,A42)>0, "1", "0") -> 1 | D42: {='Additional Generation For 30% E'!C40+1} -> 1.444269 | E42: {='Grid Reliability'!F40} -> 4565.76 | F42: {='Current Rate of Motorization'!B40} -> 62.191211 | G42: {='EV Charging Infrastructure'!B40} -> 2 | H42: {='Electricity Regulatory Index'!C40} -> 0.588 | I42: {=' Utility Cost Recovery'!B40} -> 0.9611 | J42: {='Relative Affordability'!F40} -> 0.46808602 | K42: {='Access to Finance'!C40} -> 0.07 | L42: {='Electricity Generated from Clea'!F40} -> 0.25640636 | M42: {='CO2 from Transportation'!E40} -> 0.57859885 | N42: {='Urban Air Quality'!I40} -> 296.19052 | O42: {='Fossil Fuel Import Dependence'!G40} -> 0.7434236 | P42: {='Fossil Fuel Subsidy Burden'!E40} -> 0.007617039 | Q42: {='Utility Revenue Potential'!J40} -> 2026485219 | R42: {='Projected Rate of Motorization '!C40} -> 102.86223
A43: Rwanda | B43: =IF(countif('EV National Targets'!A:A,A43)>0, "1", "0") -> 1 | C43: =IF(countif('EV Incentives'!A:A,A43)>0, "1", "0") -> 1 | D43: {='Additional Generation For 30% E'!C41+1} -> 1.0780611 | E43: {='Grid Reliability'!F41} -> 97.2 | F43: {='Current Rate of Motorization'!B41} -> 15.216288 | G43: {='EV Charging Infrastructure'!B41} -> 4 | H43: {='Electricity Regulatory Index'!C41} -> 0.605 | I43: {=' Utility Cost Recovery'!B41} -> 0.89122473 | J43: {='Relative Affordability'!F41} -> 0.1518347 | K43: {='Access to Finance'!C41} -> Not Found | L43: {='Electricity Generated from Clea'!F41} -> 0.59439453 | M43: {='CO2 from Transportation'!E41} -> 0.47128022 | N43: {='Urban Air Quality'!I41} -> 223.74065 | O43: {='Fossil Fuel Import Dependence'!G41} -> 0.74015748 | P43: {='Fossil Fuel Subsidy Burden'!E41} -> 0 | Q43: {='Utility Revenue Potential'!J41} -> 5403906.7 | R43: {='Projected Rate of Motorization '!C41} -> 126.40596
A44: Sao Tome & Principe | B44: =IF(countif('EV National Targets'!A:A,A44)>0, "1", "0") -> 0 | C44: =IF(countif('EV Incentives'!A:A,A44)>0, "1", "0") -> 0 | D44: {='Additional Generation For 30% E'!C42+1} -> 1.1507954 | E44: {='Grid Reliability'!F42} -> Not Found | F44: {='Current Rate of Motorization'!B42} -> 166.39626 | G44: {='EV Charging Infrastructure'!B42} -> Not Found | H44: {='Electricity Regulatory Index'!C42} -> 0.16 | I44: {=' Utility Cost Recovery'!B42} -> 0.51202814 | J44: {='Relative Affordability'!F42} -> 0.2796848 | K44: {='Access to Finance'!C42} -> Not Found | L44: {='Electricity Generated from Clea'!F42} -> 0.099456569 | M44: {='CO2 from Transportation'!E42} -> 0.24450744 | N44: {='Urban Air Quality'!I42} -> 286.65642 | O44: {='Fossil Fuel Import Dependence'!G42} -> 0.34693878 | P44: {='Fossil Fuel Subsidy Burden'!E42} -> 0 | Q44: {='Utility Revenue Potential'!J42} -> 2729245.8 | R44: {='Projected Rate of Motorization '!C42} -> 116.21168
A45: Senegal | B45: =IF(countif('EV National Targets'!A:A,A45)>0, "1", "0") -> 0 | C45: =IF(countif('EV Incentives'!A:A,A45)>0, "1", "0") -> 0 | D45: {='Additional Generation For 30% E'!C43+1} -> 1.1585806 | E45: {='Grid Reliability'!F43} -> 129.6 | F45: {='Current Rate of Motorization'!B43} -> 34.387686 | G45: {='EV Charging Infrastructure'!B43} -> 4 | H45: {='Electricity Regulatory Index'!C43} -> 0.71 | I45: {=' Utility Cost Recovery'!B43} -> 0.833239 | J45: {='Relative Affordability'!F43} -> 0.33210069 | K45: {='Access to Finance'!C43} -> 0.13 | L45: {='Electricity Generated from Clea'!F43} -> 0.202356 | M45: {='CO2 from Transportation'!E43} -> 0.35966718 | N45: {='Urban Air Quality'!I43} -> 201.30486 | O45: {='Fossil Fuel Import Dependence'!G43} -> 2.034642 | P45: {='Fossil Fuel Subsidy Burden'!E43} -> 0 | Q45: {='Utility Revenue Potential'!J43} -> 1.8701399e+08 | R45: {='Projected Rate of Motorization '!C43} -> 100.09576
A46: Seychelles | B46: =IF(countif('EV National Targets'!A:A,A46)>0, "1", "0") -> 1 | C46: =IF(countif('EV Incentives'!A:A,A46)>0, "1", "0") -> 1 | D46: {='Additional Generation For 30% E'!C44+1} -> 1.1131563 | E46: {='Grid Reliability'!F44} -> 24 | F46: {='Current Rate of Motorization'!B44} -> 243.73396 | G46: {='EV Charging Infrastructure'!B44} -> Not Found | H46: {='Electricity Regulatory Index'!C44} -> 0.294 | I46: {=' Utility Cost Recovery'!B44} -> 1.076025 | J46: {='Relative Affordability'!F44} -> 0.48044463 | K46: {='Access to Finance'!C44} -> Not Found | L46: {='Electricity Generated from Clea'!F44} -> 0.12124194 | M46: {='CO2 from Transportation'!E44} -> 0.28779021 | N46: {='Urban Air Quality'!I44} -> 191.83003 | O46: {='Fossil Fuel Import Dependence'!G44} -> 0.25407166 | P46: {='Fossil Fuel Subsidy Burden'!E44} -> 0 | Q46: {='Utility Revenue Potential'!J44} -> 21324507 | R46: {='Projected Rate of Motorization '!C44} -> 739.29645
A47: Sierra Leone | B47: =IF(countif('EV National Targets'!A:A,A47)>0, "1", "0") -> 0 | C47: =IF(countif('EV Incentives'!A:A,A47)>0, "1", "0") -> 0 | D47: {='Additional Generation For 30% E'!C45+1} -> 2.1864109 | E47: {='Grid Reliability'!F45} -> 427.2 | F47: {='Current Rate of Motorization'!B45} -> 6.1564633 | G47: {='EV Charging Infrastructure'!B45} -> Not Found | H47: {='Electricity Regulatory Index'!C45} -> 0.658 | I47: {=' Utility Cost Recovery'!B45} -> 0.71313651 | J47: {='Relative Affordability'!F45} -> 0.34729364 | K47: {='Access to Finance'!C45} -> 0.06 | L47: {='Electricity Generated from Clea'!F45} -> 0.91366707 | M47: {='CO2 from Transportation'!E45} -> 0.64131679 | N47: {='Urban Air Quality'!I45} -> 417.95776 | O47: {='Fossil Fuel Import Dependence'!G45} -> 0.48263889 | P47: {='Fossil Fuel Subsidy Burden'!E45} -> 0 | Q47: {='Utility Revenue Potential'!J45} -> 42175945 | R47: {='Projected Rate of Motorization '!C45} -> 50.176892
A48: Somalia | B48: =IF(countif('EV National Targets'!A:A,A48)>0, "1", "0") -> 0 | C48: =IF(countif('EV Incentives'!A:A,A48)>0, "1", "0") -> 0 | D48: {='Additional Generation For 30% E'!C46+1} -> 1.0693912 | E48: {='Grid Reliability'!F46} -> Not Found | F48: {='Current Rate of Motorization'!B46} -> 4.159913 | G48: {='EV Charging Infrastructure'!B46} -> 11 | H48: {='Electricity Regulatory Index'!C46} -> Not Found | I48: {=' Utility Cost Recovery'!B46} -> Not Found | J48: {='Relative Affordability'!F46} -> 0.19783098 | K48: {='Access to Finance'!C46} -> Not Found | L48: {='Electricity Generated from Clea'!F46} -> 0.086986369 | M48: {='CO2 from Transportation'!E46} -> 0.21532405 | N48: {='Urban Air Quality'!I46} -> 141.51007 | O48: {='Fossil Fuel Import Dependence'!G46} -> 0.34117647 | P48: {='Fossil Fuel Subsidy Burden'!E46} -> 0 | Q48: {='Utility Revenue Potential'!J46} -> 2235959.9 | R48: {='Projected Rate of Motorization '!C46} -> 38.699564
A49: South Africa | B49: =IF(countif('EV National Targets'!A:A,A49)>0, "1", "0") -> 1 | C49: =IF(countif('EV Incentives'!A:A,A49)>0, "1", "0") -> 1 | D49: {='Additional Generation For 30% E'!C47+1} -> 1.0816973 | E49: {='Grid Reliability'!F47} -> 212.52 | F49: {='Current Rate of Motorization'!B47} -> 186.72057 | G49: {='EV Charging Infrastructure'!B47} -> 81 | H49: {='Electricity Regulatory Index'!C47} -> 0.55 | I49: {=' Utility Cost Recovery'!B47} -> 0.86023995 | J49: {='Relative Affordability'!F47} -> 0.15272262 | K49: {='Access to Finance'!C47} -> 0.19 | L49: {='Electricity Generated from Clea'!F47} -> 0.13085952 | M49: {='CO2 from Transportation'!E47} -> 0.11604514 | N49: {='Urban Air Quality'!I47} -> 199.26057 | O49: {='Fossil Fuel Import Dependence'!G47} -> 2.3336589 | P49: {='Fossil Fuel Subsidy Burden'!E47} -> 0 | Q49: {='Utility Revenue Potential'!J47} -> 1302905552 | R49: {='Projected Rate of Motorization '!C47} -> 227.28079
A50: South Sudan | B50: =IF(countif('EV National Targets'!A:A,A50)>0, "1", "0") -> 0 | C50: =IF(countif('EV Incentives'!A:A,A50)>0, "1", "0") -> 0 | D50: {='Additional Generation For 30% E'!C48+1} -> 1.5255501 | E50: {='Grid Reliability'!F48} -> 84.6 | F50: {='Current Rate of Motorization'!B48} -> 6.293723 | G50: {='EV Charging Infrastructure'!B48} -> 1 | H50: {='Electricity Regulatory Index'!C48} -> Not Found | I50: {=' Utility Cost Recovery'!B48} -> Not Found | J50: {='Relative Affordability'!F48} -> 0.77379461 | K50: {='Access to Finance'!C48} -> 0.03 | L50: {='Electricity Generated from Clea'!F48} -> 0.017564706 | M50: {='CO2 from Transportation'!E48} -> 0.51649739 | N50: {='Urban Air Quality'!I48} -> 224.00878 | O50: {='Fossil Fuel Import Dependence'!G48} -> 0.6 | P50: {='Fossil Fuel Subsidy Burden'!E48} -> 0 | Q50: {='Utility Revenue Potential'!J48} -> 1.2566661e+08 | R50: {='Projected Rate of Motorization '!C48} -> Not Found
... A57: Zimbabwe | B57: =IF(countif('EV National Targets'!A:A,A57)>0, "1", "0") -> 1 | C57: =IF(countif('EV Incentives'!A:A,A57)>0, "1", "0") -> 1 | D57: {='Additional Generation For 30% E'!C55+1} -> 1.1022048 | E57: {='Grid Reliability'!F55} -> 280.8 | F57: {='Current Rate of Motorization'!B55} -> 71.795769 | G57: {='EV Charging Infrastructure'!B55} -> 1 | H57: {='Electricity Regulatory Index'!C55} -> 0.686 | I57: {=' Utility Cost Recovery'!B55} -> 0.61835259 | J57: {='Relative Affordability'!F55} -> 0.17943063 | K57: {='Access to Finance'!C55} -> 0.15 | L57: {='Electricity Generated from Clea'!F55} -> 0.51566724 | M57: {='CO2 from Transportation'!E55} -> 0.26481162 | N57: {='Urban Air Quality'!I55} -> 237.76449 | O57: {='Fossil Fuel Import Dependence'!G55} -> 0.60059465 | P57: {='Fossil Fuel Subsidy Burden'!E55} -> 0 | Q57: {='Utility Revenue Potential'!J55} -> 91929085 | R57: {='Projected Rate of Motorization '!C55} -> 86.017142

Sheet EV National Targets
A1: Country | B1: Level | C1: Policy type | D1: Key policy measures and targets | E1: Year announced | F1: Category | G1: Source | H1: Source 2
A2: Algeria | B2: National | C2: Target | D2: 1,000 charging stations by 2024 | E2: 2023 | G2: Source | H2: Climatescope
A3: Cabo Verde | B3: Multi-national | C3: Ambition | D3: COP26 Declaration: Work towards all sales of new cars and vans being zero emission globally by 2040, or by no later than 2035 in leading markets. | E3: 2022 | F3: LDV | G3: Accelerating to Zero Coalition | H3: IEA
A4: Cabo Verde | B4: National | C4: Target | D4: 50% share of EVs in urban bus sales by 2025, 75% by 2030 and 100% by 2040. | E4: 2019 | F4: Bus | G4: Government of Cabo Verde | H4: IEA
A5: Cabo Verde | B5: National | C5: Target | D5: 35% share of passenger LDV sales to be EVs by 2025, 70% by 2030 and 100% by 2035. | E5: 2019 | F5: LDV | G5: Government of Cabo Verde | H5: IEA
A6: Cabo Verde | B6: National | C6: Target | D6: 25% share of EVs in heavy truck sales by 2030 and 100% by 2035. | E6: 2019 | F6: M/HDV | G6: Government of Cabo Verde | H6: IEA
A7: Cabo Verde | B7: National | C7: Target | D7: 15% share of EVs in medium truck sales by 2025, 35% by 2030 and 100% by 2035. | E7: 2019 | F7: M/HDV | G7: Government of Cabo Verde | H7: IEA
A8: Cabo Verde | B8: National | C8: Target | D8: 100% EVs in government LDV stock by 2035. | E8: 2019 | F8: LDV | G8: Government of Cabo Verde, source | H8: IEA
A9: Ethiopia | B9: National | C9: Target | D9: Introduce 500,000 EVs in the Ethiopian market by 2030 | E9: 2024 | G9: Source, Source
A10: Gambia | B10: National | C10: Target | D10: Promote low emission fuel and HEVs, introduce an age limit of a maximum of 3 years for imported vehicles. | E10: 2022 | F10: LDV | G10: Government of Gambia | H10: IEA
A11: Ghana | B11: National | C11: Target | D11: Build 1,000 electric vehicle charging stations across the country within five years | E11: 2023 | G11: Source | H11: Climatescope
A12: Ghana | B12: National | C12: Ambition | D12: 4%, 16%, and 32% of cars sold to be EVs in 2025, 2030, and 2050 respectively. | E12: 2022 | F12: LDV | G12: Government of Ghana | H12: IEA
A13: Ghana | B13: National | C13: Ambition | D13: 4%, 16%, and 32% of buses sold to be EVs in 2025, 2030, and 2050 respectively. | E13: 2022 | F13: Bus | G13: Government of Ghana | H13: IEA
A14: Ghana | B14: Multi-national | C14: Ambition | D14: COP26 Declaration: Work intensely towards accelerated proliferation and adoption of zero-emission vehicles. | E14: 2022 | F14: LDV | G14: Accelerating to Zero Coalition | H14: IEA
A15: Kenya | B15: Multi-national | C15: Ambition | D15: COP26 Declaration: Work intensely towards accelerated proliferation and adoption of zero-emission vehicles. | E15: 2022 | F15: LDV | G15: Accelerating to Zero Coalition | H15: IEA
A16: Kenya | B16: Natiional | C16: Target | D16: 200,000 electric motorcycles on its roads by end of 2024 | E16: 2023 | G16: Source, Source | H16: Non-IEA
A17: Kenya | B17: National | C17: Ambition | D17: 5% share of electric/hybrid vehicles in total vehicles imported by 2025. | E17: 2020 | F17: Multiple | G17: Government of Kenya | H17: IEA
A18: Morocco | B18: Multi-national | C18: Ambition | D18: COP26 Declaration: Work intensely towards accelerated proliferation and adoption of zero-emission vehicles. | E18: 2022 | F18: LDV | G18: Accelerating to Zero Coalition | H18: IEA
A19: Mozambique | B19: National | C19: Ambition | D19: Set up an electric bus assembly plant in the country to assemble around 1,000 buses in first phase | E19: 2023 | G19: Source | H19: Climatescope
A20: Namibia | B20: National | C20: Target | D20: Aims to have 96,500 light vehicles converted to BEVs by 2025 | E20: 2024 | G20: Source
A21: Nigeria | B21: National | C21: Ambition | D21: 100% transition to EV by 2060 with interim targets of 1% EV and 2% HEV by 2030, and 60% EV and 20% HEV by 2050. | E21: 2020 | F21: LDV | G21: Government of Nigeria | H21: IEA
A22: Rwanda | B22: Multi-national | C22: Ambition | D22: COP26 Declaration: Work intensely towards accelerated proliferation and adoption of zero-emission vehicles. | E22: 2022 | F22: LDV | G22: Accelerating to Zero Coalition | H22: IEA
A23: Seychelles | B23: National | C23: Target | D23: 30% of new private vehicle sales to be electric by 2030 | E23: 2022 | F23: LDV | G23: Government of Seychelles | H23: IEA
A24: Seychelles | B24: National | C24: Target | D24: 100% of public bus stock to be electric by 2050. | E24: 2022 | F24: Bus | G24: Government of Seychelles | H24: IEA
A25: South Africa | B25: National | C25: Target | D25: Convert 5% of the public and national fleet to cleaner alternative fuel and efficient technology vehicles by 2025, with annual increase of 2% thereafter. | E25: 2018 | F25: Multiple | G25: Government of South Africa | H25: IEA
A26: South Africa | B26: National | C26: Target | D26: Add 40 solar powered public EV charging stations per annum. | E26: 2018 | F26: EVSE | G26: Government of South Africa
A27: Tunisia | B27: National | C27: Target | D27: 130,000 EVs by 2030 | E27: 2023 | G27: Source
A28: Zimbabwe | B28: National | C28: Target (draft) | D28: 33% market penetration of e-vehicles by 2030 | E28: 2022 | G28: Source
C30: Link to methodology
C31: {={"INDICATOR INFORMATION"; "Index Category: "&CHAR(10)& "EV Readiness Index - Measures country preparedness to adopt EVs at large scale"; ""; "Sub-Category: "&CHAR(10)& "Enabling Policies"; ""; "Indicator Name: "&CHAR(10)& "EV National Targets"; ""; "Description: "&CHAR(10)& "Records key ambitions and targets that support the deployment of electric vehicles (EVs) in Africa."; ""; "Scoring Categories: "&CHAR(10)& "• No EV-specific targets = Low Readiness (1/3)"&CHAR(10)& "• Has EV-specific targets = High Readiness (3/3)"; ""; "Focus: "&CHAR(10)& "• EV-specific ambitions and penetration targets"; ""; "Data Categories: "&CHAR(10)& "• National Targets"&CHAR(10)& "• National Ambitions"&CHAR(10)& "• Multi-national Commitments"; ""; "Last Updated: 2022"; ""; "Primary Sources: "&CHAR(10)& "• IEA"&CHAR(10)& "• Government Documents"&CHAR(10)& "• Climatescope"}} -> INDICATOR INFORMATION
C32: Index Category: EV Readiness Index - Measures country preparedness to adopt EVs at large scale
C34: Sub-Category: Enabling Policies
C36: Indicator Name: EV National Targets
C38: Description: Records key ambitions and targets that support the deployment of electric vehicles (EVs) in Africa.
C40: Scoring Categories: • No EV-specific targets = Low Readiness (1/3) • Has EV-specific targets = High Readiness (3/3)
C42: Focus: • EV-specific ambitions and penetration targets
C44: Data Categories: • National Targets • National Ambitions • Multi-national Commitments
C46: Last Updated: 2022
C48: Primary Sources: • IEA • Government Documents • Climatescope

Sheet EV Incentives
A1: Country | B1: Level | C1: Policy type | D1: Key policy measures and targets | E1: Year announced | F1: Category | G1: Source | H1: Source
A2: Angola | B2: National | C2: Legislation | D2: 50% reduction of both import duty and vehicle tax for EVs. | E2: 2022 | F2: Multiple | G2: Government of Angola | H2: IEA
A3: Angola | B3: National | C3: Legislation | D3: 50% reduction in import customs duty and motor vehicle tax for EVs until 2032 | E3: 2022 | G3: Source | H3: Climatescope
A4: Benin | B4: National | C4: Legislation | D4: Exempt 100% EVs from VAT and custom duties | E4: 2023 | G4: Source
A5: Cabo Verde | B5: National | C5: Legislation | D5: Exemption from VAT and excise duties on the import of EVs, including two-wheeler vehicles | E5: 2022 | F5: EVSE | G5: ICCT
A6: DR Congo | B6: Multi-national | C6: Legislation (agreement) | D6: Afreximbank and ECA sign Framework Agreement towards establishing Special Economic Zones for the production of Battery Electric Vehicles in DRC and Zambia | E6: 2023 | G6: Source
A7: Egypt | B7: National | C7: Legislation | D7: Ministerial Resolution 255/2018 exempts EVs from customs duties and allowed the import of EVs that are no older than three years | E7: 2018 | G7: Source | H7: Climatescope
A8: Egypt | B8: National | C8: Legislation (announced) | D8: Financial support up to EGP 50,000 for buyers of locally-manufactured electric cars | E8: 2021 | G8: Source | H8: Climatescope
A9: Ethiopia | B9: National | C9: Legislation | D9: EVs are not subject to import duties if locally assembled, reduced rates apply for partially and fully assembled imports, also exempt from VAT, surtax, and excise tax. | E9: 2022 | F9: Multiple | G9: Government of Ethiopia | H9: IEA
A10: Ethiopia | B10: National | C10: Legislation | D10: Exempts EVs from VAT, excise tax, and surtaxes, reduces import tax | E10: 2022 | G10: Source | H10: Climatescope
A11: Ethiopia | B11: National | C11: Legislation (announced) | D11: An immediate ban on all ICE vehicle imports | E11: 2024 | G11: Source
A12: Ethiopia | B12: National | C12: Legislation | D12: National 10-year strategic plan: Importing 439,000 EVs by 2030 | E12: 2020 | G12: Source
A13: Ghana | B13: National | C13: Legislation | D13: Waive import duties on import of EVs for public transportation for 8 years | E13: 2023 | F13: EVSE | G13: Clean Technica | H13: ITA
A14: Kenya | B14: National | C14: Legislation | D14: Finance Bill of 2019 proposed reduction on the excise duty for all vehicles with only electric motor for propulsion (BEVs) from 20% to 10%. | E14: 2019 | G14: Source
A15: Kenya | B15: National | C15: Legislation | D15: Kenya released draft of National E-mobility policy that will institure ZEVs sales targets and investment criteria for domestic manafacturers and assemblers to be eligible for gov incentives | E15: 2024 | G15: Source | H15: Policy
A16: Madagascar | B16: National | C16: Legislation | D16: Exempts electric and hybrid vehicles from VAT | E16: 2024 | G16: Source
A17: Malawi | B17: National | C17: Legislation | D17: Removal of 30% Import Duty and 25% Import Excise on electric motorcycles. Standard rate of 16.5% VAT will be charged. | E17: 2024 | H17: Policy
A18: Mauritius | B18: National | C18: Legislation | D18: Introduced a rebate on the excise duty scheme of 10% for the purchase of electric vehicles by individuals up to a maximum of Rs 200,000 ($4,500). | E18: 2022 | G18: Source
A19: Mauritius | B19: National | C19: Legislation | D19: Allow duty free imports of electric and hybrid vehicles into Mauritius from July 2022 to June 2024 | E19: 2023 | G19: Source, Source
A20: Morocco | B20: National | C20: Legislation | D20: Owners of EVs and hybrids exempt from paying circulation tax | E20: 2017 | G20: Source | H20: IEA
A21: Nigeria | B21: National | C21: Legislation | D21: 10-year tax relief for EV manufacturers in Nigeria | E21: 2023 | G21: Source
A22: Rwanda | B22: National | C22: Legislation | D22: VAT, withholding tax, and import duty exemptions for EVs and associated parts/equipment. | E22: 2021 | F22: Multiple | G22: Government of Rwanda | H22: IEA
A23: Rwanda | B23: National | C23: Legislation | D23: Tariffs at charging stations are capped at industrial rates, with lower off-peak tariffs; provision of charging stations including planning codes. | E23: 2021 | F23: EVSE | G23: Government of Rwanda | H23: IEA
A24: Rwanda | B24: National | C24: Legislation | D24: Introduction of a carbon tax, establishment of restricted zones for green transport, and further preferential treatment for EVs. | E24: 2021 | F24: Multiple | G24: Government of Rwanda | H24: IEA
A25: Rwanda | B25: National | C25: Legislation | D25: Exempts electric vehicles from import duties and VAT | E25: 2023 | G25: Source, Source | H25: Climatescope
A26: Seychelles | B26: National | C26: Legislation | D26: Excises are waived 100% for BEVs | E26: 2015 | G26: Source
A27: South Africa | B27: National | C27: Legislation | D27: 150% tax deduction for investments in the production of electric and hydrogen-powered vehicles | E27: 2024 | G27: Source
A28: Togo | B28: National | C28: Legislation | D28: Togo exempted EVs from import taxes | E28: 2022 | G28: Source | H28: Climatescope
A29: Tunisia | B29: National | C29: Legislation | D29: Customs duties rates are reduced to 10% and value-added tax rate to 7% levied on electric car chargers. | E29: 2022 | F29: EVSE | G29: Government of Tunisia | H29: IEA
A30: Tunisia | B30: National | C30: Legislation | D30: Motorists offered TD10,000 ($3,200) per car to switch to EVs | E30: 2023 | G30: Source
A31: Uganda | B31: National | C31: Legislation | D31: Exempt hybrid and electric vehicles from import duty | E31: 2023 | G31: Source
A32: Zambia | B32: National | C32: Legislation | D32: Reduction of customs duty on electric vehicles from 30% to 15% and on electric motorcycles from 25% to 15% | E32: 2023 | G32: Source | H32: Climatescope
A33: Zimbabwe | B33: National | C33: Legislation (draft) | D33: VAT reduction from 14.5% to 4.5% for 2022-2030 | E33: 2022 | G33: Source
C35: Link to methodology
C36: {={"INDICATOR INFORMATION"; "Index Category: "&CHAR(10)& "EV Readiness Index - Measures country preparedness to adopt EVs at large scale"; ""; "Sub-Category: "&CHAR(10)& "Enabling Policies"; ""; "Indicator Name: "&CHAR(10)& "EV Incentives"; ""; "Description: "&CHAR(10)& "Records legislation that supports the deployment of electric vehicles (EVs) and zero-emission vehicles (ZEVs) in Africa."; ""; "Scoring Categories: "&CHAR(10)& "• No EV incentives = Low Readiness (1/3)"&CHAR(10)& "• Has EV incentives = High Readiness (3/3)"; ""; "Data Categories: "&CHAR(10)& "• Tax Incentives"&CHAR(10)& "• Import Duties"&CHAR(10)& "• Financial Support"&CHAR(10)& "• Manufacturing Incentives"; ""; "Last Updated: 2023"; ""; "Primary Sources: "&CHAR(10)& "• IEA"&CHAR(10)& "• Government Documents"&CHAR(10)& "• Climatescope"}} -> INDICATOR INFORMATION
C37: Index Category: EV Readiness Index - Measures country preparedness to adopt EVs at large scale
C39: Sub-Category: Enabling Policies
C41: Indicator Name: EV Incentives
C43: Description: Records legislation that supports the deployment of electric vehicles (EVs) and zero-emission vehicles (ZEVs) in Africa.
C45: Scoring Categories: • No EV incentives = Low Readiness (1/3) • Has EV incentives = High Readiness (3/3)
C47: Data Categories: • Tax Incentives • Import Duties • Financial Support • Manufacturing Incentives
C49: Last Updated: 2023
C51: Primary Sources: • IEA • Government Documents • Climatescope

Sheet Additional Generation For 30% E
A1: Country | B1: Percent added generation required 100% (GWh) | C1: Percent added generation required (GWh) (30%) | D1: Multiplication factor for 30% EVs | E1: Score: Low readiness (25% +), Medium readiness (25%-10%), High readiness (10%-0) | F1: Score | G1: Updated data from May 27, 2024 | H1: Source
A2: Algeria | B2: =(G2/30)*100 -> 55.480274 | C2: =(B2/100)*0.3 -> 0.16644082 | D2: =1+C2 -> 1.1664408 | E2: =IF(D2<1.1, "Modest Expansion (high readiness)", IF(D2<=1.25, "Medium Expansion (medium readiness)", "Large expansion (low readiness)")) -> Medium Expansion (medium readiness) | F2: =IF(D2<1.1, 1, IF(D2<=1.25, (2/3), (1/3))) -> 0.66666667 | G2: 16.644082 | H2: AFREC
A3: Angola | B3: =(G3/30)*100 -> 33.859712 | C3: =(B3/100)*0.3 -> 0.10157914 | D3: =1+C3 -> 1.1015791 | E3: =IF(D3<1.1, "Modest Expansion (high readiness)", IF(D3<=1.25, "Medium Expansion (medium readiness)", "Large expansion (low readiness)")) -> Medium Expansion (medium readiness) | F3: =IF(D3<1.1, 1, IF(D3<=1.25, (2/3), (1/3))) -> 0.66666667 | G3: 10.157914
A4: Benin | B4: =(G4/30)*100 -> 2999.0944 | C4: =(B4/100)*0.3 -> 8.9972832 | D4: =1+C4 -> 9.9972832 | E4: =IF(D4<1.1, "Modest Expansion (high readiness)", IF(D4<=1.25, "Medium Expansion (medium readiness)", "Large expansion (low readiness)")) -> Large expansion (low readiness) | F4: =IF(D4<1.1, 1, IF(D4<=1.25, (2/3), (1/3))) -> 0.33333333 | G4: 899.72832
A5: Botswana | B5: =(G5/30)*100 -> 130.15498 | C5: =(B5/100)*0.3 -> 0.39046495 | D5: =1+C5 -> 1.390465 | E5: =IF(D5<1.1, "Modest Expansion (high readiness)", IF(D5<=1.25, "Medium Expansion (medium readiness)", "Large expansion (low readiness)")) -> Large expansion (low readiness) | F5: =IF(D5<1.1, 1, IF(D5<=1.25, (2/3), (1/3))) -> 0.33333333 | G5: 39.046495
A6: Burkina Faso | B6: =(G6/30)*100 -> 185.00053 | C6: =(B6/100)*0.3 -> 0.55500158 | D6: =1+C6 -> 1.5550016 | E6: =IF(D6<1.1, "Modest Expansion (high readiness)", IF(D6<=1.25, "Medium Expansion (medium readiness)", "Large expansion (low readiness)")) -> Large expansion (low readiness) | F6: =IF(D6<1.1, 1, IF(D6<=1.25, (2/3), (1/3))) -> 0.33333333 | G6: 55.500158
A7: Burundi | B7: =(G7/30)*100 -> 50.825364 | C7: =(B7/100)*0.3 -> 0.15247609 | D7: =1+C7 -> 1.1524761 | E7: =IF(D7<1.1, "Modest Expansion (high readiness)", IF(D7<=1.25, "Medium Expansion (medium readiness)", "Large expansion (low readiness)")) -> Medium Expansion (medium readiness) | F7: =IF(D7<1.1, 1, IF(D7<=1.25, (2/3), (1/3))) -> 0.66666667 | G7: 15.247609
A8: Cabo Verde | B8: =(G8/30)*100 -> 1134.9706 | C8: =(B8/100)*0.3 -> 3.4049117 | D8: =1+C8 -> 4.4049117 | E8: =IF(D8<1.1, "Modest Expansion (high readiness)", IF(D8<=1.25, "Medium Expansion (medium readiness)", "Large expansion (low readiness)")) -> Large expansion (low readiness) | F8: =IF(D8<1.1, 1, IF(D8<=1.25, (2/3), (1/3))) -> 0.33333333 | G8: 340.49117
A9: Cameroon | B9: =(G9/30)*100 -> 2.9315969 | C9: =(B9/100)*0.3 -> 0.0087947906 | D9: =1+C9 -> 1.0087948 | E9: =IF(D9<1.1, "Modest Expansion (high readiness)", IF(D9<=1.25, "Medium Expansion (medium readiness)", "Large expansion (low readiness)")) -> Modest Expansion (high readiness) | F9: =IF(D9<1.1, 1, IF(D9<=1.25, (2/3), (1/3))) -> 1 | G9: 0.87947906
A10: Central African Republic | B10: =(G10/30)*100 -> 165.05925 | C10: =(B10/100)*0.3 -> 0.49517775 | D10: =1+C10 -> 1.4951778 | E10: =IF(D10<1.1, "Modest Expansion (high readiness)", IF(D10<=1.25, "Medium Expansion (medium readiness)", "Large expansion (low readiness)")) -> Large expansion (low readiness) | F10: =IF(D10<1.1, 1, IF(D10<=1.25, (2/3), (1/3))) -> 0.33333333 | G10: 49.517775
A11: Chad | B11: =(G11/30)*100 -> 422.75716 | C11: =(B11/100)*0.3 -> 1.2682715 | D11: =1+C11 -> 2.2682715 | E11: =IF(D11<1.1, "Modest Expansion (high readiness)", IF(D11<=1.25, "Medium Expansion (medium readiness)", "Large expansion (low readiness)")) -> Large expansion (low readiness) | F11: =IF(D11<1.1, 1, IF(D11<=1.25, (2/3), (1/3))) -> 0.33333333 | G11: 126.82715
A12: Comoros | B12: =(G12/30)*100 -> 60.168558 | C12: =(B12/100)*0.3 -> 0.18050567 | D12: =1+C12 -> 1.1805057 | E12: =IF(D12<1.1, "Modest Expansion (high readiness)", IF(D12<=1.25, "Medium Expansion (medium readiness)", "Large expansion (low readiness)")) -> Medium Expansion (medium readiness) | F12: =IF(D12<1.1, 1, IF(D12<=1.25, (2/3), (1/3))) -> 0.66666667 | G12: 18.050567
A13: Congo | B13: =(G13/30)*100 -> 35.20082 | C13: =(B13/100)*0.3 -> 0.10560246 | D13: =1+C13 -> 1.1056025 | E13: =IF(D13<1.1, "Modest Expansion (high readiness)", IF(D13<=1.25, "Medium Expansion (medium readiness)", "Large expansion (low readiness)")) -> Medium Expansion (medium readiness) | F13: =IF(D13<1.1, 1, IF(D13<=1.25, (2/3), (1/3))) -> 0.66666667 | G13: 10.560246
A14: Côte d'Ivoire | B14: =(G14/30)*100 -> 482.95296 | C14: =(B14/100)*0.3 -> 1.4488589 | D14: =1+C14 -> 2.4488589 | E14: =IF(D14<1.1, "Modest Expansion (high readiness)", IF(D14<=1.25, "Medium Expansion (medium readiness)", "Large expansion (low readiness)")) -> Large expansion (low readiness) | F14: =IF(D14<1.1, 1, IF(D14<=1.25, (2/3), (1/3))) -> 0.33333333 | G14: 144.88589
... A55: Zimbabwe | B55: =(G55/30)*100 -> 34.068262 | C55: =(B55/100)*0.3 -> 0.10220479 | D55: =1+C55 -> 1.1022048 | E55: =IF(D55<1.1, "Modest Expansion (high readiness)", IF(D55<=1.25, "Medium Expansion (medium readiness)", "Large expansion (low readiness)")) -> Medium Expansion (medium readiness) | F55: =IF(D55<1.1, 1, IF(D55<=1.25, (2/3), (1/3))) -> 0.66666667 | G55: 10.220479
C57: Summary statistics [Percent added generation required (GWh) (30%)] | E57: Country name
C58: Max | D58: =MAX(C2:C55) -> 8.9972832 | E58: Benin
C59: Min | D59: =MIN(C2:C55) -> 0.0087947906 | E59: Cameroon
C60: Average | D60: =AVERAGE(C2:C55) -> 0.50573105
C61: Median | D61: =MEDIAN(C2:C55) -> 0.16943851
C63: Link to methodology
C64: {={"INDICATOR INFORMATION"; "Index Category: "&CHAR(10)& "EV Readiness Index - Measures country preparedness to adopt EVs at large scale"; ""; "Sub-Category: "&CHAR(10)& "Grid Infrastructure"; ""; "Indicator Name: "&CHAR(10)& "Additional Generation for 30% EVs"; ""; "Description: "&CHAR(10)& "Evaluates the additional electricity generation capacity needed to support 30% EV adoption relative to current capacity"; ""; "Calculation Method: "&CHAR(10)& "See methodology note"; ""; "Scoring Categories: "&CHAR(10)& "• Large expansion (>25%) = Low Readiness (1/3)"&CHAR(10)& "• Medium expansion (25-10%) = Medium Readiness (2/3)"&CHAR(10)& "• Modest expansion (<10%) = High Readiness (3/3)"; ""; "Key Statistics: "&CHAR(10)& "• Minimum value: Cameroon (0.88%)"&CHAR(10)& "• Maximum value: Benin (899.73%)"&CHAR(10)& "• Median: 16.94%"; ""; "Data Sources: "&CHAR(10)& "• Fuel consumption: Africa Energy Commission (2018)"&CHAR(10)& "• Electricity generation: U.S. EIA (2021)"}} -> INDICATOR INFORMATION
C65: Index Category: EV Readiness Index - Measures country preparedness to adopt EVs at large scale
C67: Sub-Category: Grid Infrastructure
C69: Indicator Name: Additional Generation for 30% EVs
C71: Description: Evaluates the additional electricity generation capacity needed to support 30% EV adoption relative to current capacity
C73: Calculation Method: See methodology note
C75: Scoring Categories: • Large expansion (>25%) = Low Readiness (1/3) • Medium expansion (25-10%) = Medium Readiness (2/3) • Modest expansion (<10%) = High Readiness (3/3)
C77: Key Statistics: • Minimum value: Cameroon (0.88%) • Maximum value: Benin (899.73%) • Median: 16.94%
C79: Data Sources: • Fuel consumption: Africa Energy Commission (2018) • Electricity generation: U.S. EIA (2021)

Sheet Grid Reliability
A1: Country | B1: Percent of firms experiencing electrical outages | C1: Number of electrical outages in a typical month | D1: If there were outages, average duration of a typical electrical outage (hours) | E1: Average time without electricity (hours) in a typical month | F1: Yearly average time without electricity (hours) | G1: Scoring: WBES: Low: 250+, Medium: 50-249, High:<50 SAIDI: Low: 20+, Medium: 5-20, High: 0-5 | H1: Score - WBES only | I1: WBES dates | J1: SAIDI dates | K1: WBES & SAIDI Criteria: Use SAIDI data if Enterprise data is missing, Enterprise data is from 2010 or before, and a more recent SAIDI value is available, otherwise Enterprise data is used | L1: Score WBES & SAIDI | M1: Source(s) | N1: DIVIDER | O1: WB SAIDI (2014-2019) | P1: WB SAIDI (added June 11th) | Q1: WB SAIDI source
A2: Algeria | B2: Not Found | C2: Not Found | D2: Not Found | E2: Not Found | F2: Not Found | G2: Not Found | H2: Not Found | I2: Not Found | J2: 2019 | K2: =O2 -> 4.2 | L2: =IF(P2>20, (1/3), IF(P2>5, (2/3), 1)) -> 1 | M2: World Bank | N2: WB SAIDI --> | O2: 4.2 | P2: 4.2
A3: Angola | B3: 87.7 | C3: 4.7 | D3: 13.5 | E3: =(C3*D3) -> 63.45 | F3: =E3*12 -> 761.4 | G3: =IF(F3>=250, "Low reliability", IF(F3>=50, "Medium reliability", "High reliability")) -> Low reliability | H3: =IF(F3>250, (1/3), IF(F3> 50, (2/3), 1)) -> 0.33333333 | I3: 2010 | J3: 2019 | K3: =O3 -> 12.8 | L3: =IF(P3>20, (1/3), IF(P3>5, (2/3), 1)) -> 0.66666667 | M3: World Bank | O3: 12.8 | P3: 12.8
A4: Benin | B4: 95.6 | C4: 28 | D4: 3.7 | E4: =(C4*D4) -> 103.6 | F4: =E4*12 -> 1243.2 | G4: =IF(F4>=250, "Low reliability", IF(F4>=50, "Medium reliability", "High reliability")) -> Low reliability | H4: =IF(F4>250, (1/3), IF(F4> 50, (2/3), 1)) -> 0.33333333 | I4: 2016 | J4: Not Found | K4: =F4 -> 1243.2 | L4: =IF(F4>250, (1/3), IF(F4> 50, (2/3), 1)) -> 0.33333333 | O4: Not Found | P4: Not Found
A5: Botswana | B5: 64.2 | C5: 2.4 | D5: 5.3 | E5: =(C5*D5) -> 12.72 | F5: =E5*12 -> 152.64 | G5: =IF(F5>=250, "Low reliability", IF(F5>=50, "Medium reliability", "High reliability")) -> Medium reliability | H5: =IF(F5>250, (1/3), IF(F5> 50, (2/3), 1)) -> 0.66666667 | I5: 2023 | J5: Not Found | K5: =F5 -> 152.64 | L5: =IF(F5>250, (1/3), IF(F5> 50, (2/3), 1)) -> 0.66666667 | O5: Not Found | P5: Not Found
A6: Burkina Faso | B6: 91.9 | C6: 9.8 | D6: 3.3 | E6: =(C6*D6) -> 32.34 | F6: =E6*12 -> 388.08 | G6: =IF(F6>=250, "Low reliability", IF(F6>=50, "Medium reliability", "High reliability")) -> Low reliability | H6: =IF(F6>250, (1/3), IF(F6> 50, (2/3), 1)) -> 0.33333333 | I6: 2009 | J6: Not Found | K6: =F6 -> 388.08 | L6: =IF(F6>250, (1/3), IF(F6> 50, (2/3), 1)) -> 0.33333333 | O6: Not Found | P6: Not Found
A7: Burundi | B7: 85.1 | C7: 16.6 | D7: 4.8 | E7: =(C7*D7) -> 79.68 | F7: =E7*12 -> 956.16 | G7: =IF(F7>=250, "Low reliability", IF(F7>=50, "Medium reliability", "High reliability")) -> Low reliability | H7: =IF(F7>250, (1/3), IF(F7> 50, (2/3), 1)) -> 0.33333333 | I7: 2014 | J7: 2014 | K7: =F7 -> 956.16 | L7: =IF(F7>250, (1/3), IF(F7> 50, (2/3), 1)) -> 0.33333333 | O7: 660 | P7: 660
A8: Cabo Verde | B8: 74 | C8: 3.2 | D8: 9.2 | E8: =(C8*D8) -> 29.44 | F8: =E8*12 -> 353.28 | G8: =IF(F8>=250, "Low reliability", IF(F8>=50, "Medium reliability", "High reliability")) -> Low reliability | H8: =IF(F8>250, (1/3), IF(F8> 50, (2/3), 1)) -> 0.33333333 | I8: 2009 | J8: 2019 | K8: =O8 -> 18.3 | L8: =IF(P8>20, (1/3), IF(P8>5, (2/3), 1)) -> 0.66666667 | O8: 18.3 | P8: 18.3
A9: Cameroon | B9: 92.5 | C9: 7.6 | D9: 8.7 | E9: =(C9*D9) -> 66.12 | F9: =E9*12 -> 793.44 | G9: =IF(F9>=250, "Low reliability", IF(F9>=50, "Medium reliability", "High reliability")) -> Low reliability | H9: =IF(F9>250, (1/3), IF(F9> 50, (2/3), 1)) -> 0.33333333 | I9: 2016 | J9: Not Found | K9: =F9 -> 793.44 | L9: =IF(F9>250, (1/3), IF(F9> 50, (2/3), 1)) -> 0.33333333 | O9: Not Found | P9: Not Found
A10: Central African Republic | B10: 89.3 | C10: 28.3 | D10: 7.1 | E10: =(C10*D10) -> 200.93 | F10: =E10*12 -> 2411.16 | G10: =IF(F10>=250, "Low reliability", IF(F10>=50, "Medium reliability", "High reliability")) -> Low reliability | H10: =IF(F10>250, (1/3), IF(F10> 50, (2/3), 1)) -> 0.33333333 | I10: 2023 | J10: Not Found | K10: =F10 -> 2411.16 | L10: =IF(F10>250, (1/3), IF(F10> 50, (2/3), 1)) -> 0.33333333 | O10: Not Found | P10: Not Found
A11: Chad | B11: 96.2 | C11: 15.9 | D11: 15.1 | E11: =(C11*D11) -> 240.09 | F11: =E11*12 -> 2881.08 | G11: =IF(F11>=250, "Low reliability", IF(F11>=50, "Medium reliability", "High reliability")) -> Low reliability | H11: =IF(F11>250, (1/3), IF(F11> 50, (2/3), 1)) -> 0.33333333 | I11: 2023 | J11: Not Found | K11: =F11 -> 2881.08 | L11: =IF(F11>250, (1/3), IF(F11> 50, (2/3), 1)) -> 0.33333333 | O11: Not Found | P11: Not Found
A12: Comoros | B12: Not Found | C12: Not Found | D12: Not Found | E12: Not Found | F12: Not Found | G12: Not Found | H12: Not Found | I12: Not Found | J12: Not Found | K12: Not Found | L12: Not Found | O12: Not Found | P12: Not Found
A13: Congo | B13: 89.7 | C13: 21.5 | D13: 34.3 | E13: =(C13*D13) -> 737.45 | F13: =E13*12 -> 8849.4 | G13: =IF(F13>=250, "Low reliability", IF(F13>=50, "Medium reliability", "High reliability")) -> Low reliability | H13: =IF(F13>250, (1/3), IF(F13> 50, (2/3), 1)) -> 0.33333333 | I13: 2009 | J13: Not Found | K13: =F13 -> 8849.4 | L13: =IF(F13>250, (1/3), IF(F13> 50, (2/3), 1)) -> 0.33333333 | O13: Not Found | P13: Not Found
A14: Côte d'Ivoire | B14: 80.3 | C14: 3.5 | D14: 3.7 | E14: =(C14*D14) -> 12.95 | F14: =E14*12 -> 155.4 | G14: =IF(F14>=250, "Low reliability", IF(F14>=50, "Medium reliability", "High reliability")) -> Medium reliability | H14: =IF(F14>250, (1/3), IF(F14> 50, (2/3), 1)) -> 0.66666667 | I14: 2023 | J14: 2019 | K14: =F14 -> 155.4 | L14: =IF(F14>250, (1/3), IF(F14> 50, (2/3), 1)) -> 0.66666667 | O14: 14.4 | P14: 14.4
A15: Djibouti | B15: 80.2 | C15: 1.6 | D15: 1.5 | E15: =(C15*D15) -> 2.4 | F15: =E15*12 -> 28.8 | G15: =IF(F15>=250, "Low reliability", IF(F15>=50, "Medium reliability", "High reliability")) -> High reliability | H15: =IF(F15>250, (1/3), IF(F15> 50, (2/3), 1)) -> 1 | I15: 2013 | J15: Not Found | K15: =F15 -> 28.8 | L15: =IF(F15>250, (1/3), IF(F15> 50, (2/3), 1)) -> 1 | N15: WB ENTERPRISE SURVEYS <-- | O15: Not Found | P15: Not Found
A16: DR Congo | B16: 89.3 | C16: 12.3 | D16: 5.6 | E16: =(C16*D16) -> 68.88 | F16: =E16*12 -> 826.56 | G16: =IF(F16>=250, "Low reliability", IF(F16>=50, "Medium reliability", "High reliability")) -> Low reliability | H16: =IF(F16>250, (1/3), IF(F16> 50, (2/3), 1)) -> 0.33333333 | I16: 2013 | J16: Not Found | K16: =F16 -> 826.56 | L16: =IF(F16>250, (1/3), IF(F16> 50, (2/3), 1)) -> 0.33333333 | O16: Not Found | P16: Not Found
A17: Egypt | B17: 28.2 | C17: 0.8 | D17: 0.9 | E17: =(C17*D17) -> 0.72 | F17: =E17*12 -> 8.64 | G17: =IF(F17>=250, "Low reliability", IF(F17>=50, "Medium reliability", "High reliability")) -> High reliability | H17: =IF(F17>250, (1/3), IF(F17> 50, (2/3), 1)) -> 1 | I17: 2020 | J17: 2019 | K17: =F17 -> 8.64 | L17: =IF(F17>250, (1/3), IF(F17> 50, (2/3), 1)) -> 1 | O17: 2 | P17: 2
A18: Equatorial Guinea | B18: Not Found | C18: Not Found | D18: Not Found | E18: Not Found | F18: Not Found | G18: Not Found | H18: Not Found | I18: Not Found | J18: Not Found | K18: Not Found | L18: Not Found | O18: Not Found | P18: Not Found
A19: Eritrea | B19: 20.5 | C19: 0.5 | D19: 2.8 | E19: =(C19*D19) -> 1.4 | F19: =E19*12 -> 16.8 | G19: =IF(F19>=250, "Low reliability", IF(F19>=50, "Medium reliability", "High reliability")) -> High reliability | H19: =IF(F19>250, (1/3), IF(F19> 50, (2/3), 1)) -> 1 | I19: 2009 | J19: 2014 | K19: =O19 -> 900 | L19: =IF(P19>20, (1/3), IF(P19>5, (2/3), 1)) -> 0.33333333 | O19: 900 | P19: 900
A20: Eswatini | B20: 77.3 | C20: 3.7 | D20: 3.7 | E20: =(C20*D20) -> 13.69 | F20: =E20*12 -> 164.28 | G20: =IF(F20>=250, "Low reliability", IF(F20>=50, "Medium reliability", "High reliability")) -> Medium reliability | H20: =IF(F20>250, (1/3), IF(F20> 50, (2/3), 1)) -> 0.66666667 | I20: 2016 | J20: 2019 | K20: =F20 -> 164.28 | L20: =IF(F20>250, (1/3), IF(F20> 50, (2/3), 1)) -> 0.66666667 | O20: 49.4 | P20: 49.4
A21: Ethiopia | B21: 80 | C21: 8.2 | D21: 5.8 | E21: =(C21*D21) -> 47.56 | F21: =E21*12 -> 570.72 | G21: =IF(F21>=250, "Low reliability", IF(F21>=50, "Medium reliability", "High reliability")) -> Low reliability | H21: =IF(F21>250, (1/3), IF(F21> 50, (2/3), 1)) -> 0.33333333 | I21: 2015 | J21: Not Found | K21: =F21 -> 570.72 | L21: =IF(F21>250, (1/3), IF(F21> 50, (2/3), 1)) -> 0.33333333 | O21: Not Found | P21: Not Found
A22: Gabon | B22: 71.6 | C22: 4.6 | D22: 5.4 | E22: =(C22*D22) -> 24.84 | F22: =E22*12 -> 298.08 | G22: =IF(F22>=250, "Low reliability", IF(F22>=50, "Medium reliability", "High reliability")) -> Low reliability | H22: =IF(F22>250, (1/3), IF(F22> 50, (2/3), 1)) -> 0.33333333 | I22: 2009 | J22: 2019 | K22: =O22 -> 47.5 | L22: =IF(P22>20, (1/3), IF(P22>5, (2/3), 1)) -> 0.33333333 | O22: 47.5 | P22: 47.5
A23: Gambia | B23: 86.9 | C23: 7.6 | D23: 2.1 | E23: =(C23*D23) -> 15.96 | F23: =E23*12 -> 191.52 | G23: =IF(F23>=250, "Low reliability", IF(F23>=50, "Medium reliability", "High reliability")) -> Medium reliability | H23: =IF(F23>250, (1/3), IF(F23> 50, (2/3), 1)) -> 0.66666667 | I23: 2023 | J23: Not Found | K23: =F23 -> 191.52 | L23: =IF(F23>250, (1/3), IF(F23> 50, (2/3), 1)) -> 0.66666667 | O23: Not Found | P23: Not Found
A24: Ghana | B24: 73.8 | C24: 2.9 | D24: 3.1 | E24: =(C24*D24) -> 8.99 | F24: =E24*12 -> 107.88 | G24: =IF(F24>=250, "Low reliability", IF(F24>=50, "Medium reliability", "High reliability")) -> Medium reliability | H24: =IF(F24>250, (1/3), IF(F24> 50, (2/3), 1)) -> 0.66666667 | I24: 2023 | J24: 2019 | K24: =F24 -> 107.88 | L24: =IF(F24>250, (1/3), IF(F24> 50, (2/3), 1)) -> 0.66666667 | O24: 55.9 | P24: 55.9
A25: Guinea | B25: 84.2 | C25: 4.5 | D25: 3.2 | E25: =(C25*D25) -> 14.4 | F25: =E25*12 -> 172.8 | G25: =IF(F25>=250, "Low reliability", IF(F25>=50, "Medium reliability", "High reliability")) -> Medium reliability | H25: =IF(F25>250, (1/3), IF(F25> 50, (2/3), 1)) -> 0.66666667 | I25: 2016 | J25: Not Found | K25: =F25 -> 172.8 | L25: =IF(F25>250, (1/3), IF(F25> 50, (2/3), 1)) -> 0.66666667 | O25: Not Found | P25: Not Found
A26: Guinea-Bissau | B26: 57.1 | C26: 5.2 | D26: 17.9 | E26: =(C26*D26) -> 93.08 | F26: =E26*12 -> 1116.96 | G26: =IF(F26>=250, "Low reliability", IF(F26>=50, "Medium reliability", "High reliability")) -> Low reliability | H26: =IF(F26>250, (1/3), IF(F26> 50, (2/3), 1)) -> 0.33333333 | I26: 2006 | J26: Not Found | K26: =F26 -> 1116.96 | L26: =IF(F26>250, (1/3), IF(F26> 50, (2/3), 1)) -> 0.33333333 | O26: Not Found | P26: Not Found
A27: Kenya | B27: 82.8 | C27: 3.8 | D27: 5.8 | E27: =(C27*D27) -> 22.04 | F27: =E27*12 -> 264.48 | G27: =IF(F27>=250, "Low reliability", IF(F27>=50, "Medium reliability", "High reliability")) -> Low reliability | H27: =IF(F27>250, (1/3), IF(F27> 50, (2/3), 1)) -> 0.33333333 | I27: 2018 | J27: 2019 | K27: =F27 -> 264.48 | L27: =IF(F27>250, (1/3), IF(F27> 50, (2/3), 1)) -> 0.33333333 | O27: 12 | P27: 12
A28: Lesotho | B28: 64.6 | C28: 1.9 | D28: 4.3 | E28: =(C28*D28) -> 8.17 | F28: =E28*12 -> 98.04 | G28: =IF(F28>=250, "Low reliability", IF(F28>=50, "Medium reliability", "High reliability")) -> Medium reliability | H28: =IF(F28>250, (1/3), IF(F28> 50, (2/3), 1)) -> 0.66666667 | I28: 2023 | J28: Not Found | K28: =F28 -> 98.04 | L28: =IF(F28>250, (1/3), IF(F28> 50, (2/3), 1)) -> 0.66666667 | O28: Not Found | P28: Not Found
A29: Liberia | B29: 44.3 | C29: 4.5 | D29: 8.3 | E29: =(C29*D29) -> 37.35 | F29: =E29*12 -> 448.2 | G29: =IF(F29>=250, "Low reliability", IF(F29>=50, "Medium reliability", "High reliability")) -> Low reliability | H29: =IF(F29>250, (1/3), IF(F29> 50, (2/3), 1)) -> 0.33333333 | I29: 2017 | J29: 2016 | K29: =F29 -> 448.2 | L29: =IF(F29>250, (1/3), IF(F29> 50, (2/3), 1)) -> 0.33333333 | O29: 96.4 | P29: 96.4
A30: Libya | B30: Not Found | C30: Not Found | D30: Not Found | E30: Not Found | F30: Not Found | G30: Not Found | H30: Not Found | I30: Not Found | J30: 2015 | K30: =O30 -> 1883.4 | L30: =IF(P30>20, (1/3), IF(P30>5, (2/3), 1)) -> 0.33333333 | O30: 1883.4 | P30: 1883.4
A31: Madagascar | B31: 52.4 | C31: 6.3 | D31: 3.9 | E31: =(C31*D31) -> 24.57 | F31: =E31*12 -> 294.84 | G31: =IF(F31>=250, "Low reliability", IF(F31>=50, "Medium reliability", "High reliability")) -> Low reliability | H31: =IF(F31>250, (1/3), IF(F31> 50, (2/3), 1)) -> 0.33333333 | I31: 2022 | J31: Not Found | K31: =F31 -> 294.84 | L31: =IF(F31>250, (1/3), IF(F31> 50, (2/3), 1)) -> 0.33333333 | O31: Not Found | P31: Not Found
A32: Malawi | B32: 82.9 | C32: 6.7 | D32: 4.3 | E32: =(C32*D32) -> 28.81 | F32: =E32*12 -> 345.72 | G32: =IF(F32>=250, "Low reliability", IF(F32>=50, "Medium reliability", "High reliability")) -> Low reliability | H32: =IF(F32>250, (1/3), IF(F32> 50, (2/3), 1)) -> 0.33333333 | I32: 2014 | J32: Not Found | K32: =F32 -> 345.72 | L32: =IF(F32>250, (1/3), IF(F32> 50, (2/3), 1)) -> 0.33333333 | O32: Not Found | P32: Not Found
A33: Mali | B33: 86.6 | C33: 4.2 | D33: 5.1 | E33: =(C33*D33) -> 21.42 | F33: =E33*12 -> 257.04 | G33: =IF(F33>=250, "Low reliability", IF(F33>=50, "Medium reliability", "High reliability")) -> Low reliability | H33: =IF(F33>250, (1/3), IF(F33> 50, (2/3), 1)) -> 0.33333333 | I33: 2016 | J33: 2015 | K33: =F33 -> 257.04 | L33: =IF(F33>250, (1/3), IF(F33> 50, (2/3), 1)) -> 0.33333333 | O33: 168 | P33: 168
A34: Mauritania | B34: 90.7 | C34: 5.3 | D34: 2.6 | E34: =(C34*D34) -> 13.78 | F34: =E34*12 -> 165.36 | G34: =IF(F34>=250, "Low reliability", IF(F34>=50, "Medium reliability", "High reliability")) -> Medium reliability | H34: =IF(F34>250, (1/3), IF(F34> 50, (2/3), 1)) -> 0.66666667 | I34: 2014 | J34: Not Found | K34: =F34 -> 165.36 | L34: =IF(F34>250, (1/3), IF(F34> 50, (2/3), 1)) -> 0.66666667 | O34: Not Found | P34: Not Found
A35: Mauritius | B35: 40.4 | C35: 1 | D35: 4 | E35: =(C35*D35) -> 4 | F35: =E35*12 -> 48 | G35: =IF(F35>=250, "Low reliability", IF(F35>=50, "Medium reliability", "High reliability")) -> High reliability | H35: =IF(F35>250, (1/3), IF(F35> 50, (2/3), 1)) -> 1 | I35: 2023 | J35: 2019 | K35: =F35 -> 48 | L35: =IF(F35>250, (1/3), IF(F35> 50, (2/3), 1)) -> 1 | O35: 1.6 | P35: 1.6
A36: Morocco | B36: 10.9 | C36: 0.2 | D36: 0.3 | E36: =(C36*D36) -> 0.06 | F36: =E36*12 -> 0.72 | G36: =IF(F36>=250, "Low reliability", IF(F36>=50, "Medium reliability", "High reliability")) -> High reliability | H36: =IF(F36>250, (1/3), IF(F36> 50, (2/3), 1)) -> 1 | I36: 2023 | J36: 2019 | K36: =F36 -> 0.72 | L36: =IF(F36>250, (1/3), IF(F36> 50, (2/3), 1)) -> 1 | O36: 0.5 | P36: 0.5
A37: Mozambique | B37: 52.8 | C37: 1.6 | D37: 5.4 | E37: =(C37*D37) -> 8.64 | F37: =E37*12 -> 103.68 | G37: =IF(F37>=250, "Low reliability", IF(F37>=50, "Medium reliability", "High reliability")) -> Medium reliability | H37: =IF(F37>250, (1/3), IF(F37> 50, (2/3), 1)) -> 0.66666667 | I37: 2018 | J37: 2019 | K37: =F37 -> 103.68 | L37: =IF(F37>250, (1/3), IF(F37> 50, (2/3), 1)) -> 0.66666667 | O37: 80 | P37: 80
A38: Namibia | B38: 26.9 | C38: 0.6 | D38: 5.8 | E38: =(C38*D38) -> 3.48 | F38: =E38*12 -> 41.76 | G38: =IF(F38>=250, "Low reliability", IF(F38>=50, "Medium reliability", "High reliability")) -> High reliability | H38: =IF(F38>250, (1/3), IF(F38> 50, (2/3), 1)) -> 1 | I38: 2014 | J38: 2019 | K38: =F38 -> 41.76 | L38: =IF(F38>250, (1/3), IF(F38> 50, (2/3), 1)) -> 1 | O38: 0.5 | P38: 0.5
A39: Niger | B39: 78 | C39: 22 | D39: 5.2 | E39: =(C39*D39) -> 114.4 | F39: =E39*12 -> 1372.8 | G39: =IF(F39>=250, "Low reliability", IF(F39>=50, "Medium reliability", "High reliability")) -> Low reliability | H39: =IF(F39>250, (1/3), IF(F39> 50, (2/3), 1)) -> 0.33333333 | I39: 2017 | J39: 2019 | K39: =F39 -> 1372.8 | L39: =IF(F39>250, (1/3), IF(F39> 50, (2/3), 1)) -> 0.33333333 | O39: 165 | P39: 165
A40: Nigeria | B40: 77.6 | C40: 32.8 | D40: 11.6 | E40: =(C40*D40) -> 380.48 | F40: =E40*12 -> 4565.76 | G40: =IF(F40>=250, "Low reliability", IF(F40>=50, "Medium reliability", "High reliability")) -> Low reliability | H40: =IF(F40>250, (1/3), IF(F40> 50, (2/3), 1)) -> 0.33333333 | I40: 2014 | J40: Not Found | K40: =F40 -> 4565.76 | L40: =IF(F40>250, (1/3), IF(F40> 50, (2/3), 1)) -> 0.33333333 | O40: Not Found | P40: Not Found
A41: Rwanda | B41: 60.6 | C41: 1.8 | D41: 4.5 | E41: =(C41*D41) -> 8.1 | F41: =E41*12 -> 97.2 | G41: =IF(F41>=250, "Low reliability", IF(F41>=50, "Medium reliability", "High reliability")) -> Medium reliability | H41: =IF(F41>250, (1/3), IF(F41> 50, (2/3), 1)) -> 0.66666667 | I41: 2023 | J41: 2019 | K41: =F41 -> 97.2 | L41: =IF(F41>250, (1/3), IF(F41> 50, (2/3), 1)) -> 0.66666667 | O41: 2.8 | P41: 2.8
A42: Sao Tome & Principe | B42: Not Found | C42: Not Found | D42: Not Found | E42: Not Found | F42: Not Found | G42: Not Found | H42: Not Found | I42: Not Found | J42: Not Found | K42: Not Found | L42: Not Found | O42: Not Found | P42: Not Found
A43: Senegal | B43: 83.7 | C43: 6 | D43: 1.8 | E43: =(C43*D43) -> 10.8 | F43: =E43*12 -> 129.6 | G43: =IF(F43>=250, "Low reliability", IF(F43>=50, "Medium reliability", "High reliability")) -> Medium reliability | H43: =IF(F43>250, (1/3), IF(F43> 50, (2/3), 1)) -> 0.66666667 | I43: 2014 | J43: 2019 | K43: =F43 -> 129.6 | L43: =IF(F43>250, (1/3), IF(F43> 50, (2/3), 1)) -> 0.66666667 | O43: 17.4 | P43: 17.4
A44: Seychelles | B44: 38.3 | C44: 0.5 | D44: 4 | E44: =(C44*D44) -> 2 | F44: =E44*12 -> 24 | G44: =IF(F44>=250, "Low reliability", IF(F44>=50, "Medium reliability", "High reliability")) -> High reliability | H44: =IF(F44>250, (1/3), IF(F44> 50, (2/3), 1)) -> 1 | I44: 2023 | J44: 2019 | K44: =F44 -> 24 | L44: =IF(F44>250, (1/3), IF(F44> 50, (2/3), 1)) -> 1 | O44: 0.8 | P44: 0.8
A45: Sierra Leone | B45: 66.2 | C45: 4 | D45: 8.9 | E45: =(C45*D45) -> 35.6 | F45: =E45*12 -> 427.2 | G45: =IF(F45>=250, "Low reliability", IF(F45>=50, "Medium reliability", "High reliability")) -> Low reliability | H45: =IF(F45>250, (1/3), IF(F45> 50, (2/3), 1)) -> 0.33333333 | I45: 2023 | J45: 2019 | K45: =F45 -> 427.2 | L45: =IF(F45>250, (1/3), IF(F45> 50, (2/3), 1)) -> 0.33333333 | O45: 62.1 | P45: 62.1
A46: Somalia | B46: Not Found | C46: Not Found | D46: Not Found | E46: Not Found | F46: Not Found | G46: Not Found | H46: Not Found | I46: Not Found | J46: Not Found | K46: Not Found | L46: Not Found | O46: Not Found | P46: Not Found
A47: South Africa | B47: 92 | C47: 7.7 | D47: 2.3 | E47: =(C47*D47) -> 17.71 | F47: =E47*12 -> 212.52 | G47: =IF(F47>=250, "Low reliability", IF(F47>=50, "Medium reliability", "High reliability")) -> Medium reliability | H47: =IF(F47>250, (1/3), IF(F47> 50, (2/3), 1)) -> 0.66666667 | I47: 2020 | J47: 2019 | K47: =F47 -> 212.52 | L47: =IF(F47>250, (1/3), IF(F47> 50, (2/3), 1)) -> 0.66666667 | O47: 30.5 | P47: 30.5
A48: South Sudan | B48: 15.3 | C48: 1.5 | D48: 4.7 | E48: =(C48*D48) -> 7.05 | F48: =E48*12 -> 84.6 | G48: =IF(F48>=250, "Low reliability", IF(F48>=50, "Medium reliability", "High reliability")) -> Medium reliability | H48: =IF(F48>250, (1/3), IF(F48> 50, (2/3), 1)) -> 0.66666667 | I48: 2014 | J48: 2014 | K48: =F48 -> 84.6 | L48: =IF(F48>250, (1/3), IF(F48> 50, (2/3), 1)) -> 0.66666667 | O48: 1000 | P48: 1000
A49: Sudan | B49: 93.7 | C49: 3.4 | D49: 2.5 | E49: =(C49*D49) -> 8.5 | F49: =E49*12 -> 102 | G49: =IF(F49>=250, "Low reliability", IF(F49>=50, "Medium reliability", "High reliability")) -> Medium reliability | H49: =IF(F49>250, (1/3), IF(F49> 50, (2/3), 1)) -> 0.66666667 | I49: 2014 | J49: 2018 | K49: =F49 -> 102 | L49: =IF(F49>250, (1/3), IF(F49> 50, (2/3), 1)) -> 0.66666667 | O49: 58.6 | P49: 58.6
A50: Tanzania | B50: 34.1 | C50: 0.7 | D50: 6.4 | E50: =(C50*D50) -> 4.48 | F50: =E50*12 -> 53.76 | G50: =IF(F50>=250, "Low reliability", IF(F50>=50, "Medium reliability", "High reliability")) -> Medium reliability | H50: =IF(F50>250, (1/3), IF(F50> 50, (2/3), 1)) -> 0.66666667 | I50: 2023 | J50: 2019 | K50: =F50 -> 53.76 | L50: =IF(F50>250, (1/3), IF(F50> 50, (2/3), 1)) -> 0.66666667 | O50: 20.9 | P50: 20.9
A51: Togo | B51: 86.1 | C51: 2.7 | D51: 2.2 | E51: =(C51*D51) -> 5.94 | F51: =E51*12 -> 71.28 | G51: =IF(F51>=250, "Low reliability", IF(F51>=50, "Medium reliability", "High reliability")) -> Medium reliability | H51: =IF(F51>250, (1/3), IF(F51> 50, (2/3), 1)) -> 0.66666667 | I51: 2023 | J51: 2019 | K51: =F51 -> 71.28 | L51: =IF(F51>250, (1/3), IF(F51> 50, (2/3), 1)) -> 0.66666667 | O51: 81 | P51: 81
A52: Tunisia | B52: 40.2 | C52: 0.9 | D52: 3.9 | E52: =(C52*D52) -> 3.51 | F52: =E52*12 -> 42.12 | G52: =IF(F52>=250, "Low reliability", IF(F52>=50, "Medium reliability", "High reliability")) -> High reliability | H52: =IF(F52>250, (1/3), IF(F52> 50, (2/3), 1)) -> 1 | I52: 2020 | J52: 2019 | K52: =F52 -> 42.12 | L52: =IF(F52>250, (1/3), IF(F52> 50, (2/3), 1)) -> 1 | O52: 2.5 | P52: 2.5
A53: Uganda | B53: 81.5 | C53: 6.3 | D53: 10.1 | E53: =(C53*D53) -> 63.63 | F53: =E53*12 -> 763.56 | G53: =IF(F53>=250, "Low reliability", IF(F53>=50, "Medium reliability", "High reliability")) -> Low reliability | H53: =IF(F53>250, (1/3), IF(F53> 50, (2/3), 1)) -> 0.33333333 | I53: 2013 | J53: 2019 | K53: =F53 -> 763.56 | L53: =IF(F53>250, (1/3), IF(F53> 50, (2/3), 1)) -> 0.33333333 | O53: 61.7 | P53: 61.7
A54: Zambia | B54: 87.1 | C54: 13.3 | D54: 10.9 | E54: =(C54*D54) -> 144.97 | F54: =E54*12 -> 1739.64 | G54: =IF(F54>=250, "Low reliability", IF(F54>=50, "Medium reliability", "High reliability")) -> Low reliability | H54: =IF(F54>250, (1/3), IF(F54> 50, (2/3), 1)) -> 0.33333333 | I54: 2019 | J54: 2019 | K54: =F54 -> 1739.64 | L54: =IF(F54>250, (1/3), IF(F54> 50, (2/3), 1)) -> 0.33333333 | O54: 51.2 | P54: 51.2
A55: Zimbabwe | B55: 76.5 | C55: 4.5 | D55: 5.2 | E55: =(C55*D55) -> 23.4 | F55: =E55*12 -> 280.8 | G55: =IF(F55>=250, "Low reliability", IF(F55>=50, "Medium reliability", "High reliability")) -> Low reliability | H55: =IF(F55>250, (1/3), IF(F55> 50, (2/3), 1)) -> 0.33333333 | I55: 2016 | J55: 2017 | K55: =F55 -> 280.8 | L55: =IF(F55>250, (1/3), IF(F55> 50, (2/3), 1)) -> 0.33333333 | O55: 243.6 | P55: 243.6
B56: Note on use of SAIDI score
B57: Angola | C57: The World Bank Enterprise Survey data for Angola was last collected in 2010, whereas the System Average Interruption Duration Index (SAIDI) data is available through 2019. Due to the recency of the SAIDI measurements, this analysis utilizes the SAIDI data as the primary metric for evaluating power reliability.
B58: Cabo Verde | C58: The World Bank Enterprise Survey data for Cabo Verde was last collected in 2009, whereas the System Average Interruption Duration Index (SAIDI) data is available through 2019. Due to the recency of the SAIDI measurements, this analysis utilizes the SAIDI data as the primary metric for evaluating power reliability.
B59: Eritrea | C59: The World Bank Enterprise Survey data for Eritrea was last collected in 2009, whereas the System Average Interruption Duration Index (SAIDI) data is available through 2014. Due to the recency of the SAIDI measurements, this analysis utilizes the SAIDI data as the primary metric for evaluating power reliability
B60: Gabon | C60: The World Bank Enterprise Survey data for Gabon was last collected in 2009, whereas the System Average Interruption Duration Index (SAIDI) data is available through 2019. Due to the recency of the SAIDI measurements, this analysis utilizes the SAIDI data as the primary metric for evaluating power reliability
B61: Libya | C61: World Bank Enterprise Survey (WBES) data for Libya could not be sourced, whereas the System Average Interruption Duration Index (SAIDI) data is available through 2015. Due to the availability of SAIDI measurements, this analysis utilizes the SAIDI data as the primary metric for evaluating power reliability in Libya.
C63: Summary statistics [Yearly average time without electricity (hours)] | E63: Country name
C64: Max | D64: =max(F2:F55) -> 8849.4 | E64: Congo
C65: Min | D65: =MIN(F2:F55) -> 0.72 | E65: Morocco
C66: Average | D66: =AVERAGE(F2:F55) -> 718.395
C67: Median | D67: =MEDIAN(F2:F55) -> 234.78
C68: Standard deviation | D68: =STDEV(F2:F55) -> 1468.7766
C70: Link to methodology
C71: {={"INDICATOR INFORMATION"; "Index Category: "&CHAR(10)& "EV Readiness Index - Measures country preparedness to adopt EVs at large scale"; ""; "Sub-Category: "&CHAR(10)& "Grid Infrastructure"; ""; "Indicator Name: "&CHAR(10)& "Grid Reliability"; ""; "Description: "&CHAR(10)& "Measures the reliability of a country's electricity grid through average annual outage hours, indicating the grid's ability to maintain consistent power supply"; ""; "Primary Calculation Method: "&CHAR(10)& "See methodology note"; ""; "Summary Statistics: "&CHAR(10)& "• Maximum: 8,849 hours (Congo, Rep.)"&CHAR(10)& "• Minimum: 0.72 hours (Morocco)"&CHAR(10)& "• Average: 718 hours"&CHAR(10)& "• Median: 235 hours"&CHAR(10)& "• Standard Deviation: 1,469 hours"; ""; "Data Sources: "&CHAR(10)& "• Primary: World Bank Enterprise Surveys (consumer-reported data)"&CHAR(10)& "• Backup: World Bank SAIDI/SAIFI (utility-reported data)"&CHAR(10)& "Note: Combined approach used when primary data unavailable. World Bank Enterprise Surverys (WBES) used as primary source. SAIDI backup was used for the following countries: Algeria, Angola, Cabo Verde, Eswatini, Gabon, Libya"; ""; "Scoring Categories WBES & SAIDI: "&CHAR(10)& "• WBES: Low Reliability (>250 hours) = Low Readiness (1/3)"&CHAR(10)& "• WBES: Medium Reliability (150-249 hours) = Medium Readiness (2/3)"&CHAR(10)& "• WBES: High Reliability (0-149 hours) = High Readiness (3/3)"&CHAR(10)& "• SAIDI: Low Reliability (>20) = Low Readiness (1/3)"&CHAR(10)& "• SAIDI: Medium Reliability (5-20) = Medium Readiness (2/3)"&CHAR(10)& "• SAIDI: High Reliability (0-5) = High Readiness (3/3)"}} -> INDICATOR INFORMATION
C72: Index Category: EV Readiness Index - Measures country preparedness to adopt EVs at large scale
C74: Sub-Category: Grid Infrastructure
C76: Indicator Name: Grid Reliability
C78: Description: Measures the reliability of a country's electricity grid through average annual outage hours, indicating the grid's ability to maintain consistent power supply
C80: Primary Calculation Method: See methodology note
C82: Summary Statistics: • Maximum: 8,849 hours (Congo, Rep.) • Minimum: 0.72 hours (Morocco) • Average: 718 hours • Median: 235 hours • Standard Deviation: 1,469 hours
C84: Data Sources: • Primary: World Bank Enterprise Surveys (consumer-reported data) • Backup: World Bank SAIDI/SAIFI (utility-reported data) Note: Combined approach used when primary data unavailable. World Bank Enterprise Surverys (WBES) used as primary source. SAIDI backup was used for the following countries: Algeria, Angola, Cabo Verde, Eswatini, Gabon, Libya
C86: Scoring Categories WBES & SAIDI: • WBES: Low Reliability (>250 hours) = Low Readiness (1/3) • WBES: Medium Reliability (150-249 hours) = Medium Readiness (2/3) • WBES: High Reliability (0-149 hours) = High Readiness (3/3) • SAIDI: Low Reliability (>20) = Low Readiness (1/3) • SAIDI: Medium Reliability (5-20) = Medium Readiness (2/3) • SAIDI: High Reliability (0-5) = High Readiness (3/3)
A172: https://www.enterprisesurveys.org/en/data/exploretopics/infrastructure

Sheet Current Rate of Motorization
A1: Country | B1: Current rate of motorization (2016) (number of vehicles per 1000 people) | C1: Scoring: Low: <100, Medium: 100-200, High: >200 | D1: Score | E1: Source(s)
A2: Algeria | B2: 140.62437 | C2: =IF(B2<100, "Low motorization rate", IF(B2<200, "Medium motorization rate", "High motorization rate")) -> Medium motorization rate | D2: =IF(B2<100, (1/3), IF(B2<200, (2/3), 1)) -> 0.66666667 | E2: IRF, OICA, WHO, WorldData.info, Malawi Ministry of Transport, Agence Nationale de la Statistique et de la Demographie
A3: Angola | B3: 30.183765 | C3: =IF(B3<100, "Low motorization rate", IF(B3<200, "Medium motorization rate", "High motorization rate")) -> Low motorization rate | D3: =IF(B3<100, (1/3), IF(B3<200, (2/3), 1)) -> 0.33333333
A4: Benin | B4: 20.107308 | C4: =IF(B4<100, "Low motorization rate", IF(B4<200, "Medium motorization rate", "High motorization rate")) -> Low motorization rate | D4: =IF(B4<100, (1/3), IF(B4<200, (2/3), 1)) -> 0.33333333
A5: Botswana | B5: 198.19921 | C5: =IF(B5<100, "Low motorization rate", IF(B5<200, "Medium motorization rate", "High motorization rate")) -> Medium motorization rate | D5: =IF(B5<100, (1/3), IF(B5<200, (2/3), 1)) -> 0.66666667
A6: Burkina Faso | B6: 16.818502 | C6: =IF(B6<100, "Low motorization rate", IF(B6<200, "Medium motorization rate", "High motorization rate")) -> Low motorization rate | D6: =IF(B6<100, (1/3), IF(B6<200, (2/3), 1)) -> 0.33333333
A7: Burundi | B7: 4.0006138 | C7: =IF(B7<100, "Low motorization rate", IF(B7<200, "Medium motorization rate", "High motorization rate")) -> Low motorization rate | D7: =IF(B7<100, (1/3), IF(B7<200, (2/3), 1)) -> 0.33333333
A8: Cabo Verde | B8: 4.2896671 | C8: =IF(B8<100, "Low motorization rate", IF(B8<200, "Medium motorization rate", "High motorization rate")) -> Low motorization rate | D8: =IF(B8<100, (1/3), IF(B8<200, (2/3), 1)) -> 0.33333333
A9: Cameroon | B9: 116.32467 | C9: =IF(B9<100, "Low motorization rate", IF(B9<200, "Medium motorization rate", "High motorization rate")) -> Medium motorization rate | D9: =IF(B9<100, (1/3), IF(B9<200, (2/3), 1)) -> 0.66666667
A10: Central African Republic | B10: 7.6414452 | C10: =IF(B10<100, "Low motorization rate", IF(B10<200, "Medium motorization rate", "High motorization rate")) -> Low motorization rate | D10: =IF(B10<100, (1/3), IF(B10<200, (2/3), 1)) -> 0.33333333
A11: Chad | B11: 77.025421 | C11: =IF(B11<100, "Low motorization rate", IF(B11<200, "Medium motorization rate", "High motorization rate")) -> Low motorization rate | D11: =IF(B11<100, (1/3), IF(B11<200, (2/3), 1)) -> 0.33333333
A12: Comoros | B12: 46.765617 | C12: =IF(B12<100, "Low motorization rate", IF(B12<200, "Medium motorization rate", "High motorization rate")) -> Low motorization rate | D12: =IF(B12<100, (1/3), IF(B12<200, (2/3), 1)) -> 0.33333333
A13: Congo | B13: 4.3456265 | C13: =IF(B13<100, "Low motorization rate", IF(B13<200, "Medium motorization rate", "High motorization rate")) -> Low motorization rate | D13: =IF(B13<100, (1/3), IF(B13<200, (2/3), 1)) -> 0.33333333
A14: Côte d'Ivoire | B14: 3.0659601 | C14: =IF(B14<100, "Low motorization rate", IF(B14<200, "Medium motorization rate", "High motorization rate")) -> Low motorization rate | D14: =IF(B14<100, (1/3), IF(B14<200, (2/3), 1)) -> 0.33333333
... A55: Zimbabwe | B55: 71.795769 | C55: =IF(B55<100, "Low motorization rate", IF(B55<200, "Medium motorization rate", "High motorization rate")) -> Low motorization rate | D55: =IF(B55<100, (1/3), IF(B55<200, (2/3), 1)) -> 0.33333333
C57: Summary statistics Current rate of motorization (2016) (number of vehicles per 1000 people) | E57: Country name
C58: Max | D58: =MAX(B2:B55) -> 436.15322 | E58: Libya
C59: Min | D59: =MIN(B2:B55) -> 0.72683642 | E59: Djibouti
C60: Average | D60: =AVERAGE(B2:B55) -> 72.70643
C61: Median | D61: =MEDIAN(B2:B55) -> 32.86993
C62: Standard deviation | D62: =STDEV(B2:B55) -> 100.23583
C64: Link to methodology
C65: {={"INDICATOR INFORMATION"; "Index Category: "&CHAR(10)& "EV Readiness Index - Measures country preparedness to adopt EVs at large scale"; ""; "Sub-Category: "&CHAR(10)& "Market"; ""; "Indicator Name: "&CHAR(10)& "Current Rate of Motorization"; ""; "Description: "&CHAR(10)& "Measures vehicle ownership per 1,000 people, including all registered motor vehicles"; ""; "Calculation Method: "&CHAR(10)& "Motorization Rate = (Number of registered motor vehicles / Total population) × 1,000"&CHAR(10)& "• Base year: 2016"; ""; "Summary Statistics: "&CHAR(10)& "• Maximum: 436.15 (Libya)"&CHAR(10)& "• Minimum: 0.73 (Djibouti)"&CHAR(10)& "• Average: 72.71"&CHAR(10)& "• Median: 32.87"&CHAR(10)& "• Standard Deviation: 100.24"; ""; "Scoring Categories: "&CHAR(10)& "• Low (<100 vehicles/1000 people)"&CHAR(10)& "• Medium (100-200 vehicles/1000 people)"&CHAR(10)& "• High (>200 vehicles/1000 people)"; ""; "Reference Points: "&CHAR(10)& "• EU Average: 560"&CHAR(10)& "• India: 159"&CHAR(10)& "• China: 210"&CHAR(10)& "• Vietnam: 544"; ""; "Data Sources: "&CHAR(10)& "• Vehicle Data: Climate Compatible Growth Transport Starter Data Kits"&CHAR(10)& "• Population Data: World Bank (2016)"&CHAR(10)& "• Additional Sources: World Bank Global Road Safety Facility, CEIC Data, WHO"}} -> INDICATOR INFORMATION
C66: Index Category: EV Readiness Index - Measures country preparedness to adopt EVs at large scale
C68: Sub-Category: Market
C70: Indicator Name: Current Rate of Motorization
C72: Description: Measures vehicle ownership per 1,000 people, including all registered motor vehicles
C74: Calculation Method: Motorization Rate = (Number of registered motor vehicles / Total population) × 1,000 • Base year: 2016
C76: Summary Statistics: • Maximum: 436.15 (Libya) • Minimum: 0.73 (Djibouti) • Average: 72.71 • Median: 32.87 • Standard Deviation: 100.24
C78: Scoring Categories: • Low (<100 vehicles/1000 people) • Medium (100-200 vehicles/1000 people) • High (>200 vehicles/1000 people)
C80: Reference Points: • EU Average: 560 • India: 159 • China: 210 • Vietnam: 544
C82: Data Sources: • Vehicle Data: Climate Compatible Growth Transport Starter Data Kits • Population Data: World Bank (2016) • Additional Sources: World Bank Global Road Safety Facility, CEIC Data, WHO

Sheet EV Charging Infrastructure
A1: Country | B1: # Public Chargers | C1: Scoring: 0-9 (low), 10-30 (medium), >30 (high) | D1: Score | E1: Source(s)
A2: Algeria | B2: 6 | C2: =IF(B2<10, "Low", IF(B2<=30, "Medium", "High")) -> Low | D2: =IF(B2<=9, 0.33, IF(B2<=30, 0.67, 1)) -> 0.33 | E2: Electromaps
A3: Angola | B3: 2 | C3: =IF(B3<10, "Low", IF(B3<=30, "Medium", "High")) -> Low | D3: =IF(B3<=9, 0.33, IF(B3<=30, 0.67, 1)) -> 0.33 | E3: Chargemap
A4: Benin | B4: Not Found | C4: Not Found | D4: Not Found
A5: Botswana | B5: 3 | C5: =IF(B5<10, "Low", IF(B5<=30, "Medium", "High")) -> Low | D5: =IF(B5<=9, 0.33, IF(B5<=30, 0.67, 1)) -> 0.33
A6: Burkina Faso | B6: 1 | C6: =IF(B6<10, "Low", IF(B6<=30, "Medium", "High")) -> Low | D6: =IF(B6<=9, 0.33, IF(B6<=30, 0.67, 1)) -> 0.33
A7: Burundi | B7: Not Found | C7: Not Found | D7: Not Found
A8: Cabo Verde | B8: Not Found | C8: Not Found | D8: Not Found
A9: Cameroon | B9: 5 | C9: =IF(B9<10, "Low", IF(B9<=30, "Medium", "High")) -> Low | D9: =IF(B9<=9, 0.33, IF(B9<=30, 0.67, 1)) -> 0.33
A10: Central African Republic | B10: Not Found | C10: Not Found | D10: Not Found
A11: Chad | B11: Not Found | C11: Not Found | D11: Not Found
A12: Comoros | B12: Not Found | C12: Not Found | D12: Not Found
A13: Congo | B13: 1 | C13: =IF(B13<10, "Low", IF(B13<=30, "Medium", "High")) -> Low | D13: =IF(B13<=9, 0.33, IF(B13<=30, 0.67, 1)) -> 0.33
A14: Côte d'Ivoire | B14: 1 | C14: =IF(B14<10, "Low", IF(B14<=30, "Medium", "High")) -> Low | D14: =IF(B14<=9, 0.33, IF(B14<=30, 0.67, 1)) -> 0.33
A15: Djibouti | B15: Not Found | C15: Not Found | D15: Not Found
A16: DR Congo | B16: 1 | C16: =IF(B16<10, "Low", IF(B16<=30, "Medium", "High")) -> Low | D16: =IF(B16<=9, 0.33, IF(B16<=30, 0.67, 1)) -> 0.33
A17: Egypt | B17: 48 | C17: =IF(B17<10, "Low", IF(B17<=30, "Medium", "High")) -> High | D17: =IF(B17<=9, 0.33, IF(B17<=30, 0.67, 1)) -> 1
A18: Equatorial Guinea | B18: Not Found | C18: Not Found | D18: Not Found
A19: Eritrea | B19: 2 | C19: =IF(B19<10, "Low", IF(B19<=30, "Medium", "High")) -> Low | D19: =IF(B19<=9, 0.33, IF(B19<=30, 0.67, 1)) -> 0.33
A20: Eswatini | B20: Not Found | C20: Not Found | D20: Not Found
A21: Ethiopia | B21: 10 | C21: =IF(B21<10, "Low", IF(B21<=30, "Medium", "High")) -> Medium | D21: =IF(B21<=9, 0.33, IF(B21<=30, 0.67, 1)) -> 0.67
A22: Gabon | B22: Not Found | C22: Not Found | D22: Not Found
A23: Gambia | B23: Not Found | C23: Not Found | D23: Not Found
A24: Ghana | B24: 3 | C24: =IF(B24<10, "Low", IF(B24<=30, "Medium", "High")) -> Low | D24: =IF(B24<=9, 0.33, IF(B24<=30, 0.67, 1)) -> 0.33
A25: Guinea | B25: Not Found | C25: Not Found | D25: Not Found
A26: Guinea-Bissau | B26: Not Found | C26: Not Found | D26: Not Found
A27: Kenya | B27: 18 | C27: =IF(B27<10, "Low", IF(B27<=30, "Medium", "High")) -> Medium | D27: =IF(B27<=9, 0.33, IF(B27<=30, 0.67, 1)) -> 0.67
A28: Lesotho | B28: Not Found | C28: Not Found | D28: Not Found
A29: Liberia | B29: Not Found | C29: Not Found | D29: Not Found
A30: Libya | B30: 10 | C30: =IF(B30<10, "Low", IF(B30<=30, "Medium", "High")) -> Medium | D30: =IF(B30<=9, 0.33, IF(B30<=30, 0.67, 1)) -> 0.67
A31: Madagascar | B31: 2 | C31: =IF(B31<10, "Low", IF(B31<=30, "Medium", "High")) -> Low | D31: =IF(B31<=9, 0.33, IF(B31<=30, 0.67, 1)) -> 0.33
A32: Malawi | B32: Not Found | C32: Not Found | D32: Not Found
A33: Mali | B33: 2 | C33: =IF(B33<10, "Low", IF(B33<=30, "Medium", "High")) -> Low | D33: =IF(B33<=9, 0.33, IF(B33<=30, 0.67, 1)) -> 0.33
A34: Mauritania | B34: 5 | C34: =IF(B34<10, "Low", IF(B34<=30, "Medium", "High")) -> Low | D34: =IF(B34<=9, 0.33, IF(B34<=30, 0.67, 1)) -> 0.33
A35: Mauritius | B35: 31 | C35: =IF(B35<10, "Low", IF(B35<=30, "Medium", "High")) -> High | D35: =IF(B35<=9, 0.33, IF(B35<=30, 0.67, 1)) -> 1
A36: Morocco | B36: 86 | C36: =IF(B36<10, "Low", IF(B36<=30, "Medium", "High")) -> High | D36: =IF(B36<=9, 0.33, IF(B36<=30, 0.67, 1)) -> 1
A37: Mozambique | B37: Not Found | C37: Not Found | D37: Not Found
A38: Namibia | B38: 6 | C38: =IF(B38<10, "Low", IF(B38<=30, "Medium", "High")) -> Low | D38: =IF(B38<=9, 0.33, IF(B38<=30, 0.67, 1)) -> 0.33
A39: Niger | B39: 1 | C39: =IF(B39<10, "Low", IF(B39<=30, "Medium", "High")) -> Low | D39: =IF(B39<=9, 0.33, IF(B39<=30, 0.67, 1)) -> 0.33
A40: Nigeria | B40: 2 | C40: =IF(B40<10, "Low", IF(B40<=30, "Medium", "High")) -> Low | D40: =IF(B40<=9, 0.33, IF(B40<=30, 0.67, 1)) -> 0.33
A41: Rwanda | B41: 4 | C41: =IF(B41<10, "Low", IF(B41<=30, "Medium", "High")) -> Low | D41: =IF(B41<=9, 0.33, IF(B41<=30, 0.67, 1)) -> 0.33
A42: Sao Tome & Principe | B42: Not Found | C42: Not Found | D42: Not Found
A43: Senegal | B43: 4 | C43: =IF(B43<10, "Low", IF(B43<=30, "Medium", "High")) -> Low | D43: =IF(B43<=9, 0.33, IF(B43<=30, 0.67, 1)) -> 0.33
A44: Seychelles | B44: Not Found | C44: Not Found | D44: Not Found
A45: Sierra Leone | B45: Not Found | C45: Not Found | D45: Not Found
A46: Somalia | B46: 11 | C46: =IF(B46<10, "Low", IF(B46<=30, "Medium", "High")) -> Medium | D46: =IF(B46<=9, 0.33, IF(B46<=30, 0.67, 1)) -> 0.67
A47: South Africa | B47: 81 | C47: =IF(B47<10, "Low", IF(B47<=30, "Medium", "High")) -> High | D47: =IF(B47<=9, 0.33, IF(B47<=30, 0.67, 1)) -> 1
A48: South Sudan | B48: 1 | C48: =IF(B48<10, "Low", IF(B48<=30, "Medium", "High")) -> Low | D48: =IF(B48<=9, 0.33, IF(B48<=30, 0.67, 1)) -> 0.33
A49: Sudan | B49: Not Found | C49: Not Found | D49: Not Found
A50: Tanzania | B50: 2 | C50: =IF(B50<10, "Low", IF(B50<=30, "Medium", "High")) -> Low | D50: =IF(B50<=9, 0.33, IF(B50<=30, 0.67, 1)) -> 0.33
A51: Togo | B51: Not Found | C51: Not Found | D51: Not Found
A52: Tunisia | B52: 14 | C52: =IF(B52<10, "Low", IF(B52<=30, "Medium", "High")) -> Medium | D52: =IF(B52<=9, 0.33, IF(B52<=30, 0.67, 1)) -> 0.67
A53: Uganda | B53: 1 | C53: =IF(B53<10, "Low", IF(B53<=30, "Medium", "High")) -> Low | D53: =IF(B53<=9, 0.33, IF(B53<=30, 0.67, 1)) -> 0.33
A54: Zambia | B54: 4 | C54: =IF(B54<10, "Low", IF(B54<=30, "Medium", "High")) -> Low | D54: =IF(B54<=9, 0.33, IF(B54<=30, 0.67, 1)) -> 0.33
A55: Zimbabwe | B55: 1 | C55: =IF(B55<10, "Low", IF(B55<=30, "Medium", "High")) -> Low | D55: =IF(B55<=9, 0.33, IF(B55<=30, 0.67, 1)) -> 0.33
C57: Summary statistics Number of Public Chargers | E57: Country name
C58: Max | D58: =MAX(B2:B55) -> 86 | E58: Morocco
C59: Min | D59: =MIN(B2:B55) -> 1 | E59: Multiple
C60: Average | D60: =AVERAGE(B2:B55) -> 11.53125
C61: Median | D61: =MEDIAN(B2:B55) -> 3.5
C62: Standard deviation | D62: =STDEV(B2:B55) -> 21.272403
C64: Link to methodology
C65: {={"INDICATOR INFORMATION"; "Index Category: "&CHAR(10)& "EV Readiness Index - Measures country preparedness to adopt EVs at large scale"; ""; "Sub-Category: "&CHAR(10)& "Market"; ""; "Indicator Name: "&CHAR(10)& "EV Charging Infrastructure"; ""; "Description: "&CHAR(10)& "The number of public EV charging stations in a country"; ""; "Calculation Method: "&CHAR(10)& "Count of public EV charging stations"&CHAR(10)& "• Data extracted: July 2024"; ""; "Summary Statistics: "&CHAR(10)& "• Based on the spread of African EV charging point data"; ""; "Scoring Categories: "&CHAR(10)& "• Low (<10 charging stations)"&CHAR(10)& "• Medium (10-30 charging stations)"&CHAR(10)& "• High (>30 charging stations)"; ""; "Reference Points: "&CHAR(10)& "• Bounds are based on regional benchmarking"; ""; "Data Sources: "&CHAR(10)& "• Electromap"&CHAR(10)& "• ChargeMap"}} -> INDICATOR INFORMATION
C66: Index Category: EV Readiness Index - Measures country preparedness to adopt EVs at large scale
C68: Sub-Category: Market
C70: Indicator Name: EV Charging Infrastructure
C72: Description: The number of public EV charging stations in a country
C74: Calculation Method: Count of public EV charging stations • Data extracted: July 2024
C76: Summary Statistics: • Based on the spread of African EV charging point data
C78: Scoring Categories: • Low (<10 charging stations) • Medium (10-30 charging stations) • High (>30 charging stations)
C80: Reference Points: • Bounds are based on regional benchmarking
C82: Data Sources: • Electromap • ChargeMap

Sheet Electricity Regulatory Index
A1: Country | B1: ERI 2021 | C1: ERI 2022 | D1: Scoring: Low: 0-0.499, Medium: 0.500-0.799, High: 0.800+ | E1: Score | F1: Source(s)
A2: Algeria | B2: 0.6 | C2: 0.644 | D2: =IF(C2 <0.5, "Low", IF(C2 <0.8, "Medium", "High")) -> Medium | E2: =IF(C2 <0.5, (1/3), IF(C2 <0.8, (2/3), 1)) -> 0.66666667 | F2: AEP
A3: Angola | B3: 0.59 | C3: 0.608 | D3: =IF(C3 <0.5, "Low", IF(C3 <0.8, "Medium", "High")) -> Medium | E3: =IF(C3 <0.5, (1/3), IF(C3 <0.8, (2/3), 1)) -> 0.66666667
A4: Benin | B4: 0.53 | C4: 0.465 | D4: =IF(C4 <0.5, "Low", IF(C4 <0.8, "Medium", "High")) -> Low | E4: =IF(C4 <0.5, (1/3), IF(C4 <0.8, (2/3), 1)) -> 0.33333333
A5: Botswana | B5: 0.45 | C5: 0.527 | D5: =IF(C5 <0.5, "Low", IF(C5 <0.8, "Medium", "High")) -> Medium | E5: =IF(C5 <0.5, (1/3), IF(C5 <0.8, (2/3), 1)) -> 0.66666667
A6: Burkina Faso | B6: 0.48 | C6: 0.495 | D6: =IF(C6 <0.5, "Low", IF(C6 <0.8, "Medium", "High")) -> Low | E6: =IF(C6 <0.5, (1/3), IF(C6 <0.8, (2/3), 1)) -> 0.33333333
A7: Burundi | B7: 0.29 | C7: 0.284 | D7: =IF(C7 <0.5, "Low", IF(C7 <0.8, "Medium", "High")) -> Low | E7: =IF(C7 <0.5, (1/3), IF(C7 <0.8, (2/3), 1)) -> 0.33333333
A8: Cabo Verde | B8: 0.49 | C8: 0.515 | D8: =IF(C8 <0.5, "Low", IF(C8 <0.8, "Medium", "High")) -> Medium | E8: =IF(C8 <0.5, (1/3), IF(C8 <0.8, (2/3), 1)) -> 0.66666667
A9: Cameroon | B9: 0.56 | C9: 0.606 | D9: =IF(C9 <0.5, "Low", IF(C9 <0.8, "Medium", "High")) -> Medium | E9: =IF(C9 <0.5, (1/3), IF(C9 <0.8, (2/3), 1)) -> 0.66666667
A10: Central African Republic | B10: 0.12 | C10: 0.292 | D10: =IF(C10 <0.5, "Low", IF(C10 <0.8, "Medium", "High")) -> Low | E10: =IF(C10 <0.5, (1/3), IF(C10 <0.8, (2/3), 1)) -> 0.33333333
A11: Chad | B11: 0.24 | C11: 0.147 | D11: =IF(C11 <0.5, "Low", IF(C11 <0.8, "Medium", "High")) -> Low | E11: =IF(C11 <0.5, (1/3), IF(C11 <0.8, (2/3), 1)) -> 0.33333333
A12: Comoros | B12: Not Found | C12: Not Found | D12: Not Found | E12: Not Found
A13: Congo | B13: 0.11 | C13: 0.101 | D13: =IF(C13 <0.5, "Low", IF(C13 <0.8, "Medium", "High")) -> Low | E13: =IF(C13 <0.5, (1/3), IF(C13 <0.8, (2/3), 10)) -> 0.33333333
A14: Côte d'Ivoire | B14: 0.56 | C14: 0.573 | D14: =IF(C14 <0.5, "Low", IF(C14 <0.8, "Medium", "High")) -> Medium | E14: =IF(C14 <0.5, (1/3), IF(C14 <0.8, (2/3), 10)) -> 0.66666667
A15: Djibouti | B15: Not Found | C15: Not Found | D15: Not Found | E15: Not Found
A16: DR Congo | B16: 0.42 | C16: 0.527 | D16: =IF(C16 <0.5, "Low", IF(C16 <0.8, "Medium", "High")) -> Medium | E16: =IF(C16 <0.5, (1/3), IF(C16 <0.8, (2/3), 1)) -> 0.66666667
A17: Egypt | B17: 0.61 | C17: 0.785 | D17: =IF(C17 <0.5, "Low", IF(C17 <0.8, "Medium", "High")) -> Medium | E17: =IF(C17 <0.5, (1/3), IF(C17 <0.8, (2/3), 1)) -> 0.66666667
A18: Equatorial Guinea | B18: Not Found | C18: Not Found | D18: Not Found | E18: Not Found
A19: Eritrea | B19: Not Found | C19: Not Found | D19: Not Found | E19: Not Found
A20: Eswatini | B20: 0.6 | C20: 0.621 | D20: =IF(C20 <0.5, "Low", IF(C20 <0.8, "Medium", "High")) -> Medium | E20: =IF(C20 <0.5, (1/3), IF(C20 <0.8, (2/3), 1)) -> 0.66666667
A21: Ethiopia | B21: 0.57 | C21: 0.561 | D21: =IF(C21 <0.5, "Low", IF(C21 <0.8, "Medium", "High")) -> Medium | E21: =IF(C21 <0.5, (1/3), IF(C21 <0.8, (2/3), 1)) -> 0.66666667
A22: Gabon | B22: 0.18 | C22: 0.168 | D22: =IF(C22 <0.5, "Low", IF(C22 <0.8, "Medium", "High")) -> Low | E22: =IF(C22 <0.5, (1/3), IF(C22 <0.8, (2/3), 1)) -> 0.33333333
A23: Gambia | B23: 0.36 | C23: 0.298 | D23: =IF(C23 <0.5, "Low", IF(C23 <0.8, "Medium", "High")) -> Low | E23: =IF(C23 <0.5, (1/3), IF(C23 <0.8, (2/3), 1)) -> 0.33333333
A24: Ghana | B24: 0.6 | C24: 0.709 | D24: =IF(C24 <0.5, "Low", IF(C24 <0.8, "Medium", "High")) -> Medium | E24: =IF(C24 <0.5, (1/3), IF(C24 <0.8, (2/3), 1)) -> 0.66666667
A25: Guinea | B25: 0.31 | C25: 0.306 | D25: =IF(C25 <0.5, "Low", IF(C25 <0.8, "Medium", "High")) -> Low | E25: =IF(C25 <0.5, (1/3), IF(C25 <0.8, (2/3), 1)) -> 0.33333333
A26: Guinea-Bissau | B26: Not Found | C26: Not Found | D26: Not Found | E26: Not Found
A27: Kenya | B27: 0.69 | C27: 0.695 | D27: =IF(C27 <0.5, "Low", IF(C27 <0.8, "Medium", "High")) -> Medium | E27: =IF(C27 <0.5, (1/3), IF(C27 <0.8, (2/3), 1)) -> 0.66666667
A28: Lesotho | B28: 0.47 | C28: 0.49 | D28: =IF(C28 <0.5, "Low", IF(C28 <0.8, "Medium", "High")) -> Low | E28: =IF(C28 <0.5, (1/3), IF(C28 <0.8, (2/3), 1)) -> 0.33333333
A29: Liberia | B29: 0.22 | C29: 0.628 | D29: =IF(C29 <0.5, "Low", IF(C29 <0.8, "Medium", "High")) -> Medium | E29: =IF(C29 <0.5, (1/3), IF(C29 <0.8, (2/3), 1)) -> 0.66666667
A30: Libya | B30: Not Found | C30: Not Found | D30: Not Found | E30: Not Found
A31: Madagascar | B31: 0.21 | C31: 0.329 | D31: =IF(C31 <0.5, "Low", IF(C31 <0.8, "Medium", "High")) -> Low | E31: =IF(C31 <0.5, (1/3), IF(C31 <0.8, (2/3), 1)) -> 0.33333333
A32: Malawi | B32: 0.56 | C32: 0.479 | D32: =IF(C32 <0.5, "Low", IF(C32 <0.8, "Medium", "High")) -> Low | E32: =IF(C32 <0.5, (1/3), IF(C32 <0.8, (2/3), 1)) -> 0.33333333
A33: Mali | B33: 0.45 | C33: 0.45 | D33: =IF(C33 <0.5, "Low", IF(C33 <0.8, "Medium", "High")) -> Low | E33: =IF(C33 <0.5, (1/3), IF(C33 <0.8, (2/3), 1)) -> 0.33333333
A34: Mauritania | B34: 0.23 | C34: 0.226 | D34: Not Found | E34: Not Found
A35: Mauritius | B35: 0.17 | C35: 0.32 | D35: =IF(C35 <0.5, "Low", IF(C35 <0.8, "Medium", "High")) -> Low | E35: =IF(C35 <0.5, (1/3), IF(C35 <0.8, (2/3), 1)) -> 0.33333333
A36: Morocco | B36: 0.26 | C36: Not Found | D36: Not Found | E36: Not Found
A37: Mozambique | B37: 0.16 | C37: 0.372 | D37: =IF(C37 <0.5, "Low", IF(C37 <0.8, "Medium", "High")) -> Low | E37: =IF(C37 <0.5, (1/3), IF(C37 <0.8, (2/3), 1)) -> 0.33333333
A38: Namibia | B38: 0.66 | C38: 0.618 | D38: =IF(C38 <0.5, "Low", IF(C38 <0.8, "Medium", "High")) -> Medium | E38: =IF(C38 <0.5, (1/3), IF(C38 <0.8, (2/3), 1)) -> 0.66666667
A39: Niger | B39: 0.5 | C39: 0.478 | D39: =IF(C39 <0.5, "Low", IF(C39 <0.8, "Medium", "High")) -> Low | E39: =IF(C39 <0.5, (1/3), IF(C39 <0.8, (2/3), 1)) -> 0.33333333
A40: Nigeria | B40: 0.52 | C40: 0.588 | D40: =IF(C40 <0.5, "Low", IF(C40 <0.8, "Medium", "High")) -> Medium | E40: =IF(C40 <0.5, (1/3), IF(C40 <0.8, (2/3), 1)) -> 0.66666667
A41: Rwanda | B41: 0.6 | C41: 0.605 | D41: =IF(C41 <0.5, "Low", IF(C41 <0.8, "Medium", "High")) -> Medium | E41: =IF(C41 <0.5, (1/3), IF(C41 <0.8, (2/3), 1)) -> 0.66666667
A42: Sao Tome & Principe | B42: 0.3 | C42: 0.16 | D42: =IF(C42 <0.5, "Low", IF(C42 <0.8, "Medium", "High")) -> Low | E42: =IF(C42 <0.5, (1/3), IF(C42 <0.8, (2/3), 1)) -> 0.33333333
A43: Senegal | B43: 0.6 | C43: 0.71 | D43: =IF(C43 <0.5, "Low", IF(C43 <0.8, "Medium", "High")) -> Medium | E43: =IF(C43 <0.5, (1/3), IF(C43 <0.8, (2/3), 1)) -> 0.66666667
A44: Seychelles | B44: 0.22 | C44: 0.294 | D44: =IF(C44 <0.5, "Low", IF(C44 <0.8, "Medium", "High")) -> Low | E44: =IF(C44 <0.5, (1/3), IF(C44 <0.8, (2/3), 1)) -> 0.33333333
A45: Sierra Leone | B45: 0.57 | C45: 0.658 | D45: =IF(C45 <0.5, "Low", IF(C45 <0.8, "Medium", "High")) -> Medium | E45: =IF(C45 <0.5, (1/3), IF(C45 <0.8, (2/3), 1)) -> 0.66666667
A46: Somalia | B46: Not Found | C46: Not Found | D46: Not Found | E46: Not Found
A47: South Africa | B47: 0.58 | C47: 0.55 | D47: =IF(C47 <0.5, "Low", IF(C47 <0.8, "Medium", "High")) -> Medium | E47: =IF(C47 <0.5, (1/3), IF(C47 <0.8, (2/3), 1)) -> 0.66666667
A48: South Sudan | B48: Not Found | C48: Not Found | D48: Not Found | E48: Not Found
A49: Sudan | B49: Not Found | C49: Not Found | D49: Not Found | E49: Not Found
A50: Tanzania | B50: 0.67 | C50: 0.675 | D50: =IF(C50 <0.5, "Low", IF(C50 <0.8, "Medium", "High")) -> Medium | E50: =IF(C50 <0.5, (1/3), IF(C50 <0.8, (2/3), 1)) -> 0.66666667
A51: Togo | B51: 0.46 | C51: 0.622 | D51: =IF(C51 <0.5, "Low", IF(C51 <0.8, "Medium", "High")) -> Medium | E51: =IF(C51 <0.5, (1/3), IF(C51 <0.8, (2/3), 1)) -> 0.66666667
A52: Tunisia | B52: Not Found | C52: Not Found | D52: Not Found | E52: Not Found
A53: Uganda | B53: 0.82 | C53: 0.846 | D53: =IF(C53 <0.5, "Low", IF(C53 <0.8, "Medium", "High")) -> High | E53: =IF(C53 <0.5, (1/3), IF(C53 <0.8, (2/3), 1)) -> 1
A54: Zambia | B54: 0.59 | C54: 0.608 | D54: =IF(C54 <0.5, "Low", IF(C54 <0.8, "Medium", "High")) -> Medium | E54: =IF(C54 <0.5, (1/3), IF(C54 <0.8, (2/3), 1)) -> 0.66666667
A55: Zimbabwe | B55: 0.61 | C55: 0.686 | D55: =IF(C55 <0.5, "Low", IF(C55 <0.8, "Medium", "High")) -> Medium | E55: =IF(C55 <0.5, (1/3), IF(C55 <0.8, (2/3), 1)) -> 0.66666667
C57: Summary statistics ERI | E57: Country name
C58: Max | D58: =max(C2:C55) -> 0.846 | E58: Uganda
C59: Min | D59: =min(C2:C55) -> 0.101 | E59: Congo
C60: Average | D60: =AVERAGE(C2:C55) -> 0.4957907
C61: Median | D61: =median(C2:C55) -> 0.527
C62: Standard deviation | D62: =STDEV(C2:C55) -> 0.18526757
C64: Link to methodology
C65: {={"INDICATOR INFORMATION"; "Index Category: "&CHAR(10)& "EV Readiness Index - Measures country preparedness to adopt EVs at large scale"; ""; "Sub-Category: "&CHAR(10)& "Power Sector Maturity"; ""; "Indicator Name: "&CHAR(10)& "Electricity Regulatory Index (ERI)"; ""; "Description: "&CHAR(10)& "Annual index by African Development Bank (AfDB) that evaluates countries' regulatory and legal environment for electricity"; ""; "Scoring Categories: "&CHAR(10)& "• Low (<0.5) = Low Readiness (1/3)"&CHAR(10)& "• Medium (0.5-0.8) = Medium Readiness (2/3)"&CHAR(10)& "• High (>0.8) = High Readiness (3/3)"; ""; "Summary Statistics (2022): "&CHAR(10)& "• Maximum: 0.85 (Uganda)"&CHAR(10)& "• Minimum: 0.10 (Congo)"&CHAR(10)& "• Average: 0.50"&CHAR(10)& "• Median: 0.53"&CHAR(10)& "• Standard Deviation: 0.19"; ""; "Coverage Note: "&CHAR(10)& "• Data available for 43 countries"&CHAR(10)& "• 11 countries marked as 'Not Found'"; ""; "Methodology Note: "&CHAR(10)& "• Based on AfDB's ERI scoring system"&CHAR(10)& "• Medium category combines two original ERI medium categories"&CHAR(10)& "• Latest dataset from 2022"; ""; "Data Source: "&CHAR(10)& "• African Development Bank (AfDB)"}} -> INDICATOR INFORMATION
C66: Index Category: EV Readiness Index - Measures country preparedness to adopt EVs at large scale
C68: Sub-Category: Power Sector Maturity
C70: Indicator Name: Electricity Regulatory Index (ERI)
C72: Description: Annual index by African Development Bank (AfDB) that evaluates countries' regulatory and legal environment for electricity
C74: Scoring Categories: • Low (<0.5) = Low Readiness (1/3) • Medium (0.5-0.8) = Medium Readiness (2/3) • High (>0.8) = High Readiness (3/3)
C76: Summary Statistics (2022): • Maximum: 0.85 (Uganda) • Minimum: 0.10 (Congo) • Average: 0.50 • Median: 0.53 • Standard Deviation: 0.19
C78: Coverage Note: • Data available for 43 countries • 11 countries marked as 'Not Found'
C80: Methodology Note: • Based on AfDB's ERI scoring system • Medium category combines two original ERI medium categories • Latest dataset from 2022
C82: Data Source: • African Development Bank (AfDB)

Sheet  Utility Cost Recovery
A1: Country | B1: Utilitlty Financial Solvency (Operating and debt service cost recovery, including subsidies) | C1: Utility name | D1: Utility type | E1: Year | F1: Scoring: Low: <85%, Medium: 85%-100%, High: >100% | G1: Score | H1: Source(s)
A2: Algeria | B2: Not Found | C2: Not Found | D2: Not Found | E2: Not Found | F2: Not Found | G2: Not Found | H2: Not Found
A3: Angola | B3: =73.1342249/100 -> 0.73134225 | C3: ENDE | D3: Distribution | E3: 2019 | F3: =IF(B3 <0.85, "low", IF(B3 <=1, "medium", "high")) -> low | G3: =IF(B3<0.85, (1/3), IF(B3<1, (2/3), 1)) -> 0.33333333 | H3: https://utilityperformance.energydata.info/utilities/ENDE
A4: Benin | B4: =92.9579261/100 -> 0.92957926 | C4: SBEE | D4: VIU | E4: 2019 | F4: =IF(B4 <0.85, "low", IF(B4 <1, "medium", "high")) -> medium | G4: =IF(B4<0.85, (1/3), IF(B4<1, (2/3), 1)) -> 0.66666667 | H4: https://utilityperformance.energydata.info/utilities/SBEE
A5: Botswana | B5: =79.2663472/100 -> 0.79266347 | C5: BPC | D5: VIU | E5: 2019 | F5: =IF(B5 <0.85, "low", IF(B5 <=1, "medium", "high")) -> low | G5: =IF(B5<0.85, (1/3), IF(B5<1, (2/3), 1)) -> 0.33333333 | H5: https://utilityperformance.energydata.info/utilities/BPC
A6: Burkina Faso | B6: =104.1419136/100 -> 1.0414191 | C6: SONABEL | D6: VIU | E6: 2019 | F6: =IF(B6 <0.85, "low", IF(B6 <1, "medium", "high")) -> high | G6: =IF(B6<0.85, (1/3), IF(B6<1, (2/3), 1)) -> 1 | H6: https://utilityperformance.energydata.info/utilities/SONABEL
A7: Burundi | B7: =113.5604838/100 -> 1.1356048 | C7: REGIDESO | D7: VIU | E7: 2019 | F7: =IF(B7 <0.85, "low", IF(B7 <=1, "medium", "high")) -> high | G7: =IF(B7<0.85, (1/3), IF(B7<1, (2/3), 1)) -> 1 | H7: https://utilityperformance.energydata.info/utilities/REGIDESO
A8: Cabo Verde | B8: =96.0209376/100 -> 0.96020938 | C8: ELECTRA | D8: VIU | E8: 2019 | F8: =IF(B8 <0.85, "low", IF(B8 <1, "medium", "high")) -> medium | G8: =IF(B8<0.85, (1/3), IF(B8<1, (2/3), 1)) -> 0.66666667 | H8: https://utilityperformance.energydata.info/utilities/ELECTRA
A9: Cameroon | B9: =69.329753/100 -> 0.69329753 | C9: Eneo | D9: VIU | E9: 2019 | F9: =IF(B9 <0.85, "low", IF(B9 <=1, "medium", "high")) -> low | G9: =IF(B9<0.85, (1/3), IF(B9<1, (2/3), 1)) -> 0.33333333 | H9: https://utilityperformance.energydata.info/utilities/Eneo
A10: Central African Republic | B10: =44.2461284/100 -> 0.44246128 | C10: ENERCA | D10: VIU | E10: 2019 | F10: =IF(B10 <0.85, "low", IF(B10 <1, "medium", "high")) -> low | G10: =IF(B10<0.85, (1/3), IF(B10<1, (2/3), 1)) -> 0.33333333 | H10: https://utilityperformance.energydata.info/utilities/ENERCA
A11: Chad | B11: =85.1340734/100 -> 0.85134073 | C11: SNE | D11: VIU | E11: 2019 | F11: =IF(B11 <0.85, "low", IF(B11 <=1, "medium", "high")) -> medium | G11: =IF(B11<0.85, (1/3), IF(B11<1, (2/3), 1)) -> 0.66666667 | H11: https://utilityperformance.energydata.info/utilities/SNE
A12: Comoros | B12: =101.0569069/100 -> 1.0105691 | C12: SONELEC | D12: VIU | E12: 2021 | F12: =IF(B12 <0.85, "low", IF(B12 <1, "medium", "high")) -> high | G12: =IF(B12<0.85, (1/3), IF(B12<1, (2/3), 1)) -> 1 | H12: https://utilityperformance.energydata.info/utilities/SONELEC
A13: Congo | B13: Not Found | C13: Not Found | D13: Not Found | E13: Not Found | F13: Not Found | G13: Not Found | H13: Not Found
A14: Côte d'Ivoire | B14: =91.3290207/100 -> 0.91329021 | C14: CIE | D14: VIU | E14: 2019 | F14: =IF(B14 <0.85, "low", IF(B14 <1, "medium", "high")) -> medium | G14: =IF(B14<0.85, (1/3), IF(B14<1, (2/3), 1)) -> 0.66666667 | H14: https://utilityperformance.energydata.info/utilities/CIE
A15: Djibouti | B15: Not Found | C15: Not Found | D15: Not Found | E15: Not Found | F15: Not Found | G15: Not Found | H15: Not Found
A16: DR Congo | B16: =76.4701884/100 -> 0.76470188 | C16: SNEL | D16: VIU | E16: 2019 | F16: =IF(B16 <0.85, "low", IF(B16 <1, "medium", "high")) -> low | G16: =IF(B16<0.85, (1/3), IF(B16<1, (2/3), 1)) -> 0.33333333 | H16: https://utilityperformance.energydata.info/utilities/SNEL
A17: Egypt | B17: Not Found | C17: Not Found | D17: Not Found | E17: Not Found | F17: Not Found | G17: Not Found | H17: Not Found
A18: Equatorial Guinea | B18: Not Found | C18: Not Found | D18: Not Found | E18: Not Found | F18: Not Found | G18: Not Found | H18: Not Found
A19: Eritrea | B19: Not Found | C19: Not Found | D19: Not Found | E19: Not Found | F19: Not Found | G19: Not Found | H19: Not Found
A20: Eswatini | B20: =111.5748665/100 -> 1.1157487 | C20: EEC | D20: VIU | E20: 2019 | F20: =IF(B20 <0.85, "low", IF(B20 <1, "medium", "high")) -> high | G20: =IF(B20<0.85, (1/3), IF(B20<1, (2/3), 1)) -> 1 | H20: https://utilityperformance.energydata.info/utilities/EEC
A21: Ethiopia | B21: =102.7019179/100 -> 1.0270192 | C21: EEU | D21: Distribution | E21: 2019 | F21: =IF(B21 <0.85, "low", IF(B21 <=1, "medium", "high")) -> high | G21: =IF(B21<0.85, (1/3), IF(B21<1, (2/3), 1)) -> 1 | H21: https://utilityperformance.energydata.info/utilities/EEU
A22: Gabon | B22: =90.6808412/100 -> 0.90680841 | C22: SEEG | D22: VIU | E22: 2018 | F22: =IF(B22 <0.85, "low", IF(B22 <1, "medium", "high")) -> medium | G22: =IF(B22<0.85, (1/3), IF(B22<1, (2/3), 1)) -> 0.66666667 | H22: https://utilityperformance.energydata.info/utilities/SEEG
A23: Gambia | B23: =66.6773068/100 -> 0.66677307 | C23: NAWEC | D23: VIU | E23: 2019 | F23: =IF(B23 <0.85, "low", IF(B23 <=1, "medium", "high")) -> low | G23: =IF(B23<0.85, (1/3), IF(B23<1, (2/3), 1)) -> 0.33333333 | H23: https://utilityperformance.energydata.info/utilities/NAWEC
A24: Ghana | B24: =103.2875093/100 -> 1.0328751 | C24: ECG | D24: Distribution | E24: 2019 | F24: =IF(B24 <0.85, "low", IF(B24 <1, "medium", "high")) -> high | G24: =IF(B24<0.85, (1/3), IF(B24<1, (2/3), 1)) -> 1 | H24: https://utilityperformance.energydata.info/utilities/ECG
A25: Guinea | B25: =65.5307925/100 -> 0.65530793 | C25: EDG | D25: VIU | E25: 2019 | F25: =IF(B25 <0.85, "low", IF(B25 <=1, "medium", "high")) -> low | G25: =IF(B25<0.85, (1/3), IF(B25<1, (2/3), 1)) -> 0.33333333 | H25: https://utilityperformance.energydata.info/utilities/EDG
A26: Guinea-Bissau | B26: =81.999098/100 -> 0.81999098 | C26: EAGB | D26: VIU | E26: 2016 | F26: =IF(B26 <0.85, "low", IF(B26 <1, "medium", "high")) -> low | G26: =IF(B26<0.85, (1/3), IF(B26<1, (2/3), 1)) -> 0.33333333 | H26: https://utilityperformance.energydata.info/utilities/EAGB
A27: Kenya | B27: =89.3357422/100 -> 0.89335742 | C27: KPLC | D27: Transmission and Distribution | E27: 2019 | F27: =IF(B27 <0.85, "low", IF(B27 <=1, "medium", "high")) -> medium | G27: =IF(B27<0.85, (1/3), IF(B27<1, (2/3), 1)) -> 0.66666667 | H27: https://utilityperformance.energydata.info/utilities/KPLC
A28: Lesotho | B28: =98.3914297/100 -> 0.9839143 | C28: LEC | D28: VIU | E28: 2019 | F28: =IF(B28 <0.85, "low", IF(B28 <1, "medium", "high")) -> medium | G28: =IF(B28<0.85, (1/3), IF(B28<1, (2/3), 1)) -> 0.66666667 | H28: https://utilityperformance.energydata.info/utilities/LEC_Les
A29: Liberia | B29: =96.0666493/100 -> 0.96066649 | C29: LEC | D29: VIU | E29: 2019 | F29: =IF(B29 <0.85, "low", IF(B29 <=1, "medium", "high")) -> medium | G29: =IF(B29<0.85, (1/3), IF(B29<1, (2/3), 1)) -> 0.66666667 | H29: https://utilityperformance.energydata.info/utilities/LEC_Lib
A30: Libya | B30: Not Found | C30: Not Found | D30: Not Found | E30: Not Found | F30: Not Found | G30: Not Found | H30: Not Found
A31: Madagascar | B31: =66.3049268/100 -> 0.66304927 | C31: JIRAMA | D31: VIU | E31: 2019 | F31: =IF(B31 <0.85, "low", IF(B31 <=1, "medium", "high")) -> low | G31: =IF(B31<0.85, (1/3), IF(B31<1, (2/3), 1)) -> 0.33333333 | H31: https://utilityperformance.energydata.info/utilities/JIRAMA
A32: Malawi | B32: =92.4444204/100 -> 0.9244442 | C32: ESCOM | D32: VIU | E32: 2019 | F32: =IF(B32 <0.85, "low", IF(B32 <1, "medium", "high")) -> medium | G32: =IF(B32<0.85, (1/3), IF(B32<1, (2/3), 1)) -> 0.66666667 | H32: https://utilityperformance.energydata.info/utilities/ESCOM
A33: Mali | B33: =83.3038212/100 -> 0.83303821 | C33: EDM | D33: VIU | E33: 2019 | F33: =IF(B33 <0.85, "low", IF(B33 <=1, "medium", "high")) -> low | G33: =IF(B33<0.85, (1/3), IF(B33<1, (2/3), 1)) -> 0.33333333 | H33: https://utilityperformance.energydata.info/utilities/EDM_Mal
A34: Mauritania | B34: =46.4326049/100 -> 0.46432605 | C34: SOMELEC | D34: VIU | E34: 2019 | F34: =IF(B34 <0.85, "low", IF(B34 <1, "medium", "high")) -> low | G34: =IF(B34<0.85, (1/3), IF(B34<1, (2/3), 1)) -> 0.33333333 | H34: https://utilityperformance.energydata.info/utilities/SOMELEC
A35: Mauritius | B35: =105.516049/100 -> 1.0551605 | C35: CEB | D35: VIU | E35: 2019 | F35: =IF(B35 <0.85, "low", IF(B35 <=1, "medium", "high")) -> high | G35: =IF(B35<0.85, (1/3), IF(B35<1, (2/3), 1)) -> 1 | H35: https://utilityperformance.energydata.info/utilities/CEB
A36: Morocco | B36: =110.86/100 -> 1.1086 | C36: LYDEC | D36: Distribution | E36: 2019 | F36: =IF(B36 <0.85, "low", IF(B36 <1, "medium", "high")) -> high | G36: =IF(B36<0.85, (1/3), IF(B36<1, (2/3), 1)) -> 1 | H36: https://utilityperformance.energydata.info/utilities/LYDEC
A37: Mozambique | B37: =106.9415794/100 -> 1.0694158 | C37: EDM | D37: VIU | E37: 2019 | F37: =IF(B37 <0.85, "low", IF(B37 <=1, "medium", "high")) -> high | G37: =IF(B37<0.85, (1/3), IF(B37<1, (2/3), 1)) -> 1 | H37: https://utilityperformance.energydata.info/utilities/EDM_Moz
A38: Namibia | B38: =106.101749/100 -> 1.0610175 | C38: NamPower | D38: VIU | E38: 2019 | F38: =IF(B38 <0.85, "low", IF(B38 <1, "medium", "high")) -> high | G38: =IF(B38<0.85, (1/3), IF(B38<1, (2/3), 1)) -> 1 | H38: https://utilityperformance.energydata.info/utilities/NamPower
A39: Niger | B39: =102.0963214/100 -> 1.0209632 | C39: NIGELEC | D39: VIU | E39: 2019 | F39: =IF(B39 <0.85, "low", IF(B39 <=1, "medium", "high")) -> high | G39: =IF(B39<0.85, (1/3), IF(B39<1, (2/3), 1)) -> 1 | H39: https://utilityperformance.energydata.info/utilities/NIGELEC
A40: Nigeria | B40: 0.9611 | C40: AEDC, BEDC, EEDC, EKEDC, IBEDC, Ikeja, Jos, KEDCO, Kaduna, PHED, YEDC | D40: Distribution | E40: 2019 | F40: =IF(B40 <0.85, "poor", IF(B40 <=1, "fair", "good")) -> fair | G40: =IF(B40<0.85, (1/3), IF(B40<1, (2/3), 1)) -> 0.66666667 | H40: https://utilityperformance.energydata.info/utilities/AEDC_N https://utilityperformance.energydata.info/utilities/BEDC https://utilityperformance.energydata.info/utilities/EEDC https://utilityperformance.energydata.info/utilities/EKEDC https://utilityperformance.energydata.info/utilities/IBEDC https://utilityperformance.energydata.info/utilities/Ikeja https://utilityperformance.energydata.info/utilities/Jos https://utilityperformance.energydata.info/utilities/KEDCO https://utilityperformance.energydata.info/utilities/Kaduna https://utilityperformance.energydata.info/utilities/PHED https://utilityperformance.energydata.info/utilities/YEDC
A41: Rwanda | B41: =89.1224733/100 -> 0.89122473 | C41: EUCL | D41: VIU | E41: 2019 | F41: =IF(B41 <0.85, "poor", IF(B41 <=1, "fair", "good")) -> fair | G41: =IF(B41<0.85, (1/3), IF(B41<1, (2/3), 1)) -> 0.66666667 | H41: https://utilityperformance.energydata.info/utilities/EUCL
A42: Sao Tome & Principe | B42: =51.2028141/100 -> 0.51202814 | C42: EMAE | D42: VIU | E42: 2019 | F42: =IF(B42 <0.85, "poor", IF(B42 <=1, "fair", "good")) -> poor | G42: =IF(B42<0.85, (1/3), IF(B42<1, (2/3), 1)) -> 0.33333333 | H42: https://utilityperformance.energydata.info/utilities/EMAE
A43: Senegal | B43: =83.3238998/100 -> 0.833239 | C43: Senelec | D43: VIU | E43: 2019 | F43: =IF(B43 <0.85, "poor", IF(B43 <=1, "fair", "good")) -> poor | G43: =IF(B43<0.85, (1/3), IF(B43<1, (2/3), 1)) -> 0.33333333 | H43: https://utilityperformance.energydata.info/utilities/Senelec
A44: Seychelles | B44: =107.602501/100 -> 1.076025 | C44: PUC | D44: VIU | E44: 2019 | F44: =IF(B44 <0.85, "poor", IF(B44 <=1, "fair", "good")) -> good | G44: =IF(B44<0.85, (1/3), IF(B44<1, (2/3), 1)) -> 1 | H44: https://utilityperformance.energydata.info/utilities/PUC_S
A45: Sierra Leone | B45: =71.3136506/100 -> 0.71313651 | C45: EDSA | D45: VIU | E45: 2019 | F45: =IF(B45 <0.85, "poor", IF(B45 <=1, "fair", "good")) -> poor | G45: =IF(B45<0.85, (1/3), IF(B45<1, (2/3), 1)) -> 0.33333333 | H45: https://utilityperformance.energydata.info/utilities/EDSA
A46: Somalia | B46: Not Found | C46: Not Found | D46: Not Found | E46: Not Found | F46: Not Found | G46: Not Found | H46: Not Found
A47: South Africa | B47: =86.0239951/100 -> 0.86023995 | C47: ESKOM | D47: VIU | E47: 2019 | F47: =IF(B47 <0.85, "poor", IF(B47 <=1, "fair", "good")) -> fair | G47: =IF(B47<0.85, (1/3), IF(B47<1, (2/3), 1)) -> 0.66666667 | H47: https://utilityperformance.energydata.info/utilities/ESKOM
A48: South Sudan | B48: Not Found | C48: Not Found | D48: Not Found | E48: Not Found | F48: Not Found | G48: Not Found | H48: Not Found
A49: Sudan | B49: =69.9607103/100 -> 0.6996071 | C49: SEDC | D49: Distribution | E49: 2019 | F49: =IF(B49 <0.85, "poor", IF(B49 <=1, "fair", "good")) -> poor | G49: =IF(B49<0.85, (1/3), IF(B49<1, (2/3), 1)) -> 0.33333333 | H49: https://utilityperformance.energydata.info/utilities/SEDC
A50: Tanzania | B50: =108.5930145/100 -> 1.0859301 | C50: TANESCO | D50: VIU | E50: 2019 | F50: =IF(B50 <0.85, "poor", IF(B50 <=1, "fair", "good")) -> good | G50: =IF(B50<0.85, (1/3), IF(B50<1, (2/3), 1)) -> 1 | H50: https://utilityperformance.energydata.info/utilities/TANESCO
A51: Togo | B51: =92.3892723/100 -> 0.92389272 | C51: CEET | D51: VIU | E51: 2019 | F51: =IF(B51 <0.85, "poor", IF(B51 <=1, "fair", "good")) -> fair | G51: =IF(B51<0.85, (1/3), IF(B51<1, (2/3), 1)) -> 0.66666667 | H51: https://utilityperformance.energydata.info/utilities/CEET
A52: Tunisia | B52: =71.7/100 -> 0.717 | C52: STEG | D52: VIU | E52: 2019 | F52: =IF(B52 <0.85, "poor", IF(B52 <=1, "fair", "good")) -> poor | G52: =IF(B52<0.85, (1/3), IF(B52<1, (2/3), 1)) -> 0.33333333 | H52: https://utilityperformance.energydata.info/utilities/STEG
A53: Uganda | B53: =101.8420241/100 -> 1.0184202 | C53: UMEME | D53: Distribution | E53: 2019 | F53: =IF(B53 <0.85, "poor", IF(B53 <=1, "fair", "good")) -> good | G53: =IF(B53<0.85, (1/3), IF(B53<1, (2/3), 1)) -> 1 | H53: https://utilityperformance.energydata.info/utilities/UMEME
A54: Zambia | B54: =53.7115117/100 -> 0.53711512 | C54: ZESCO | D54: VIU | E54: 2019 | F54: =IF(B54 <0.85, "poor", IF(B54 <=1, "fair", "good")) -> poor | G54: =IF(B54<0.85, (1/3), IF(B54<1, (2/3), 1)) -> 0.33333333 | H54: https://utilityperformance.energydata.info/utilities/ZESCO
A55: Zimbabwe | B55: =61.835259/100 -> 0.61835259 | C55: ZETDC | D55: Transmission and Distribution | E55: 2019 | F55: =IF(B55 <0.85, "poor", IF(B55 <=1, "fair", "good")) -> poor | G55: =IF(B55<0.85, (1/3), IF(B55<1, (2/3), 1)) -> 0.33333333 | H55: https://utilityperformance.energydata.info/utilities/ZETDC
C57: Summary statistics Operating and Debt Service Cost Recovery Including Subsidies | E57: Country name
C58: Max | D58: =max(B2:B55) -> 1.1356048 | E58: Burundi
C59: Min | D59: =min(B2:B55) -> 0.44246128 | E59: Central African Republic
C60: Average | D60: =AVERAGE(B2:B55) -> 0.86613926
C61: Median | D61: =median(B2:B55) -> 0.90680841
C62: Standard deviation | D62: =STDEV(B2:B55) -> 0.18545561
C64: Link to methodology
C65: {={"INDICATOR INFORMATION"; "Index Category: "&CHAR(10)& "EV Readiness Index - Measures country preparedness to adopt EVs at large scale"; ""; "Sub-Category: "&CHAR(10)& "Power Sector Maturity"; ""; "Indicator Name: "&CHAR(10)& "Utility Cost Recovery"; ""; "Description: "&CHAR(10)& "Measures operating and debt service cost recovery (including subsidies) for largest national utility"; ""; "Scoring Categories: "&CHAR(10)& "• Low (<85%) = Low Readiness (1/3)"&CHAR(10)& "• Medium (85-100%) = Medium Readiness (2/3)"&CHAR(10)& "• High (>100%) = High Readiness (3/3)"; ""; "Summary Statistics: "&CHAR(10)& "• Maximum: 113.56% (Burundi)"&CHAR(10)& "• Minimum: 44.25% (Central African Republic)"&CHAR(10)& "• Average: 87%"&CHAR(10)& "• Median: 90.68%"&CHAR(10)& "• Standard Deviation: 0.19"; ""; "Methodology Note: "&CHAR(10)& "• 100% = Breaking even"&CHAR(10)& "• >100% = Operating surplus"&CHAR(10)& "• <100% = Operating loss"&CHAR(10)& "• Data includes VIU, Distribution, or Transmission and Distribution utilities"; ""; "Rationale: "&CHAR(10)& "• Aligned with World Bank UPBEAT report findings"&CHAR(10)& "• Reflects conventional cost recovery bounds"&CHAR(10)& "• Incorporates profitable breaking point into index"; ""; "Data Source: "&CHAR(10)& "• World Bank Utility Performance and Behavior Transformation (UPBEAT) Database"}} -> INDICATOR INFORMATION
C66: Index Category: EV Readiness Index - Measures country preparedness to adopt EVs at large scale
C68: Sub-Category: Power Sector Maturity
C70: Indicator Name: Utility Cost Recovery
C72: Description: Measures operating and debt service cost recovery (including subsidies) for largest national utility
C74: Scoring Categories: • Low (<85%) = Low Readiness (1/3) • Medium (85-100%) = Medium Readiness (2/3) • High (>100%) = High Readiness (3/3)
C76: Summary Statistics: • Maximum: 113.56% (Burundi) • Minimum: 44.25% (Central African Republic) • Average: 87% • Median: 90.68% • Standard Deviation: 0.19
C78: Methodology Note: • 100% = Breaking even • >100% = Operating surplus • <100% = Operating loss • Data includes VIU, Distribution, or Transmission and Distribution utilities
C80: Rationale: • Aligned with World Bank UPBEAT report findings • Reflects conventional cost recovery bounds • Incorporates profitable breaking point into index
C82: Data Source: • World Bank Utility Performance and Behavior Transformation (UPBEAT) Database

Sheet Relative Affordability
A1: Country | B1: Commercial electricity price ($/kWh) - 2022 | C1: Gasoline pump price ($/L) - 2022 | D1: ICE fuel cost | E1: EV fuel cost | F1: EV Charging Relative Affordability | G1: Scoring: EV pricier (>1) Comparable (0.75-1) , EV cheaper (<0.75) | H1: Score | I1: Source(s)
A2: Algeria | B2: 0.034 | C2: 0.336 | D2: 4.102896 | E2: 1.0708647 | F2: =E2/D2 -> 0.26100215 | G2: =IF(F2<0.75,"EV cheaper",IF(AND(F2>=0.75,F2<=1),"Comparable","EV pricier")) -> EV cheaper | H2: =IF(F2<0.75, (1), IF(F2<1, (2/3), (1/3))) -> 1 | I2: Climatescope, BloombergNEF, GlobalPetrolPrices, United States Environmental Protection Agency (EPA), 2017 Ford Focus Electric efficiency data, 2017 Ford Focus FWD regular gasoline efficiency data, Kenya energy regulatory authority
A3: Angola | B3: 0.012 | C3: 0.364 | D3: 4.444804 | E3: 0.37795224 | F3: =E3/D3 -> 0.085032375 | G3: =IF(F3<0.75,"EV cheaper",IF(AND(F3>=0.75,F3<=1),"Comparable","EV pricier")) -> EV cheaper | H3: =IF(F3<0.75, 1, IF(F3<1, (2/3), (1/3))) -> 1
A4: Benin | B4: 0.036 | C4: 1.121 | D4: 13.688531 | E4: 1.1338567 | F4: =E4/D4 -> 0.082832608 | G4: =IF(F4<0.75,"EV cheaper",IF(AND(F4>=0.75,F4<=1),"Comparable","EV pricier")) -> EV cheaper | H4: =IF(F4<0.75, (1), IF(F4<1, (2/3), (1/3))) -> 1
A5: Botswana | B5: 0.112 | C5: 1.075 | D5: 13.126825 | E5: 3.5275542 | F5: =E5/D5 -> 0.26872867 | G5: =IF(F5<0.75,"EV cheaper",IF(AND(F5>=0.75,F5<=1),"Comparable","EV pricier")) -> EV cheaper | H5: =IF(F5<0.75, 1, IF(F5<1, (2/3), (1/3))) -> 1
A6: Burkina Faso | B6: 0.449 | C6: 1.401 | D6: 17.107611 | E6: 14.141713 | F6: =E6/D6 -> 0.82663283 | G6: =IF(F6<0.75,"EV cheaper",IF(AND(F6>=0.75,F6<=1),"Comparable","EV pricier")) -> Comparable | H6: =IF(F6<0.75, (1), IF(F6<1, (2/3), (1/3))) -> 0.66666667
A7: Burundi | B7: 0.158 | C7: 1.409 | D7: 17.205299 | E7: 4.9763712 | F7: =E7/D7 -> 0.2892348 | G7: =IF(F7<0.75,"EV cheaper",IF(AND(F7>=0.75,F7<=1),"Comparable","EV pricier")) -> EV cheaper | H7: =IF(F7<0.75, 1, IF(F7<1, (2/3), (1/3))) -> 1
A8: Cabo Verde | B8: 0.152 | C8: 1.203 | D8: 14.689833 | E8: 4.787395 | F8: =E8/D8 -> 0.32589853 | G8: =IF(F8<0.75,"EV cheaper",IF(AND(F8>=0.75,F8<=1),"Comparable","EV pricier")) -> EV cheaper | H8: =IF(F8<0.75, (1), IF(F8<1, (2/3), (1/3))) -> 1
A9: Cameroon | B9: 0.199 | C9: 1.444 | D9: 17.632684 | E9: 6.267708 | F9: =E9/D9 -> 0.35545967 | G9: =IF(F9<0.75,"EV cheaper",IF(AND(F9>=0.75,F9<=1),"Comparable","EV pricier")) -> EV cheaper | H9: =IF(F9<0.75, 1, IF(F9<1, (2/3), (1/3))) -> 1
A10: Central African Republic | B10: 0.152 | C10: 1.813 | D10: 22.138543 | E10: 4.787395 | F10: =E10/D10 -> 0.21624707 | G10: =IF(F10<0.75,"EV cheaper",IF(AND(F10>=0.75,F10<=1),"Comparable","EV pricier")) -> EV cheaper | H10: =IF(F10<0.75, (1), IF(F10<1, (2/3), (1/3))) -> 1
A11: Chad | B11: 0.153 | C11: 0.83 | D11: 10.13513 | E11: 4.8188911 | F11: =E11/D11 -> 0.47546416 | G11: =IF(F11<0.75,"EV cheaper",IF(AND(F11>=0.75,F11<=1),"Comparable","EV pricier")) -> EV cheaper | H11: =IF(F11<0.75, 1, IF(F11<1, (2/3), (1/3))) -> 1
A12: Comoros | B12: 0.298 | C12: 1.36 | D12: 16.60696 | E12: 9.385814 | F12: =E12/D12 -> 0.56517352 | G12: =IF(F12<0.75,"EV cheaper",IF(AND(F12>=0.75,F12<=1),"Comparable","EV pricier")) -> EV cheaper | H12: =IF(F12<0.75, (1), IF(F12<1, (2/3), (1/3))) -> 1
A13: Congo | B13: 0.091 | C13: 0.9 | D13: 10.9899 | E13: 2.8661378 | F13: =E13/D13 -> 0.26079744 | G13: =IF(F13<0.75,"EV cheaper",IF(AND(F13>=0.75,F13<=1),"Comparable","EV pricier")) -> EV cheaper | H13: =IF(F13<0.75, 1, IF(F13<1, (2/3), (1/3))) -> 1
A14: Côte d'Ivoire | B14: 0.203 | C14: 1.343 | D14: 16.399373 | E14: 6.3936921 | F14: =E14/D14 -> 0.38987418 | G14: =IF(F14<0.75,"EV cheaper",IF(AND(F14>=0.75,F14<=1),"Comparable","EV pricier")) -> EV cheaper | H14: =IF(F14<0.75, (1), IF(F14<1, (2/3), (1/3))) -> 1
A15: Djibouti | B15: 0.28 | C15: 1.32 | D15: 16.11852 | E15: 8.8188856 | F15: =E15/D15 -> 0.5471275 | G15: =IF(F15<0.75,"EV cheaper",IF(AND(F15>=0.75,F15<=1),"Comparable","EV pricier")) -> EV cheaper | H15: =IF(F15<0.75, 1, IF(F15<1, (2/3), (1/3))) -> 1
A16: DR Congo | B16: 0.078 | C16: 1.208 | D16: 14.750888 | E16: 2.4566896 | F16: =E16/D16 -> 0.1665452 | G16: =IF(F16<0.75,"EV cheaper",IF(AND(F16>=0.75,F16<=1),"Comparable","EV pricier")) -> EV cheaper | H16: =IF(F16<0.75, (1), IF(F16<1, (2/3), (1/3))) -> 1
A17: Egypt | B17: 0.037 | C17: 0.372 | D17: 4.542492 | E17: 1.1653527 | F17: =E17/D17 -> 0.25654481 | G17: =IF(F17<0.75,"EV cheaper",IF(AND(F17>=0.75,F17<=1),"Comparable","EV pricier")) -> EV cheaper | H17: =IF(F17<0.75, 1, IF(F17<1, (2/3), (1/3))) -> 1
A18: Equatorial Guinea | B18: 0.17 | C18: 0.72 | D18: 8.79192 | E18: 5.3543234 | F18: =E18/D18 -> 0.60900502 | G18: =IF(F18<0.75,"EV cheaper",IF(AND(F18>=0.75,F18<=1),"Comparable","EV pricier")) -> EV cheaper | H18: =IF(F18<0.75, (1), IF(F18<1, (2/3), (1/3))) -> 1
A19: Eritrea | B19: 0.24 | C19: 2 | D19: 24.422 | E19: 7.5590448 | F19: =E19/D19 -> 0.30951784 | G19: =IF(F19<0.75,"EV cheaper",IF(AND(F19>=0.75,F19<=1),"Comparable","EV pricier")) -> EV cheaper | H19: =IF(F19<0.75, 1, IF(F19<1, (2/3), (1/3))) -> 1
A20: Eswatini | B20: 0.062 | C20: 1.123 | D20: 13.712953 | E20: 1.9527532 | F20: =E20/D20 -> 0.1424021 | G20: =IF(F20<0.75,"EV cheaper",IF(AND(F20>=0.75,F20<=1),"Comparable","EV pricier")) -> EV cheaper | H20: =IF(F20<0.75, (1), IF(F20<1, (2/3), (1/3))) -> 1
A21: Ethiopia | B21: 0.023 | C21: 1.259 | D21: 15.373649 | E21: 0.72440846 | F21: =E21/D21 -> 0.047120138 | G21: =IF(F21<0.75,"EV cheaper",IF(AND(F21>=0.75,F21<=1),"Comparable","EV pricier")) -> EV cheaper | H21: =IF(F21<0.75, 1, IF(F21<1, (2/3), (1/3))) -> 1
A22: Gabon | B22: 0.19 | C22: 0.997 | D22: 12.174367 | E22: 5.9842438 | F22: =E22/D22 -> 0.49154455 | G22: =IF(F22<0.75,"EV cheaper",IF(AND(F22>=0.75,F22<=1),"Comparable","EV pricier")) -> EV cheaper | H22: =IF(F22<0.75, (1), IF(F22<1, (2/3), (1/3))) -> 1
A23: Gambia | B23: 0.2 | C23: 1.18 | D23: 14.40898 | E23: 6.299204 | F23: =E23/D23 -> 0.4371721 | G23: =IF(F23<0.75,"EV cheaper",IF(AND(F23>=0.75,F23<=1),"Comparable","EV pricier")) -> EV cheaper | H23: =IF(F23<0.75, 1, IF(F23<1, (2/3), (1/3))) -> 1
A24: Ghana | B24: 0.089 | C24: 1.164 | D24: 14.213604 | E24: 2.8031458 | F24: =E24/D24 -> 0.19721569 | G24: =IF(F24<0.75,"EV cheaper",IF(AND(F24>=0.75,F24<=1),"Comparable","EV pricier")) -> EV cheaper | H24: =IF(F24<0.75, (1), IF(F24<1, (2/3), (1/3))) -> 1
A25: Guinea | B25: 0.185 | C25: 1.13 | D25: 13.79843 | E25: 5.8267637 | F25: =E25/D25 -> 0.4222773 | G25: =IF(F25<0.75,"EV cheaper",IF(AND(F25>=0.75,F25<=1),"Comparable","EV pricier")) -> EV cheaper | H25: =IF(F25<0.75, 1, IF(F25<1, (2/3), (1/3))) -> 1
A26: Guinea-Bissau | B26: 0.38 | C26: 1.11 | D26: 13.55421 | E26: 11.968488 | F26: =E26/D26 -> 0.88300887 | G26: =IF(F26<0.75,"EV cheaper",IF(AND(F26>=0.75,F26<=1),"Comparable","EV pricier")) -> Comparable | H26: =IF(F26<0.75, (1), IF(F26<1, (2/3), (1/3))) -> 0.66666667
A27: Kenya | B27: 0.143 | C27: 1.352 | D27: 16.509272 | E27: 4.5039309 | F27: =E27/D27 -> 0.2728122 | G27: =IF(F27<0.75,"EV cheaper",IF(AND(F27>=0.75,F27<=1),"Comparable","EV pricier")) -> EV cheaper | H27: =IF(F27<0.75, 1, IF(F27<1, (2/3), (1/3))) -> 1
A28: Lesotho | B28: 0.019 | C28: 1.133 | D28: 13.835063 | E28: 0.59842438 | F28: =E28/D28 -> 0.043254185 | G28: =IF(F28<0.75,"EV cheaper",IF(AND(F28>=0.75,F28<=1),"Comparable","EV pricier")) -> EV cheaper | H28: =IF(F28<0.75, (1), IF(F28<1, (2/3), (1/3))) -> 1
A29: Liberia | B29: 0.242 | C29: 0.94 | D29: 11.47834 | E29: 7.6220368 | F29: =E29/D29 -> 0.66403651 | G29: =IF(F29<0.75,"EV cheaper",IF(AND(F29>=0.75,F29<=1),"Comparable","EV pricier")) -> EV cheaper | H29: =IF(F29<0.75, 1, IF(F29<1, (2/3), (1/3))) -> 1
A30: Libya | B30: 0.041 | C30: 0.031 | D30: 0.378541 | E30: 1.2913368 | F30: =E30/D30 -> 3.4113526 | G30: =IF(F30<0.75,"EV cheaper",IF(AND(F30>=0.75,F30<=1),"Comparable","EV pricier")) -> EV pricier | H30: =IF(F30<0.75, (1), IF(F30<1, (2/3), (1/3))) -> 0.33333333
A31: Madagascar | B31: 0.098 | C31: 1.306 | D31: 15.947566 | E31: 3.08661 | F31: =E31/D31 -> 0.1935474 | G31: =IF(F31<0.75,"EV cheaper",IF(AND(F31>=0.75,F31<=1),"Comparable","EV pricier")) -> EV cheaper | H31: =IF(F31<0.75, 1, IF(F31<1, (2/3), (1/3))) -> 1
A32: Malawi | B32: 0.144 | C32: 1.61 | D32: 19.65971 | E32: 4.5354269 | F32: =E32/D32 -> 0.23069653 | G32: =IF(F32<0.75,"EV cheaper",IF(AND(F32>=0.75,F32<=1),"Comparable","EV pricier")) -> EV cheaper | H32: =IF(F32<0.75, (1), IF(F32<1, (2/3), (1/3))) -> 1
A33: Mali | B33: 0.156 | C33: 1.427 | D33: 17.425097 | E33: 4.9133791 | F33: =E33/D33 -> 0.28197141 | G33: =IF(F33<0.75,"EV cheaper",IF(AND(F33>=0.75,F33<=1),"Comparable","EV pricier")) -> EV cheaper | H33: =IF(F33<0.75, 1, IF(F33<1, (2/3), (1/3))) -> 1
A34: Mauritania | B34: 0.162 | C34: 1.13 | D34: 13.79843 | E34: 5.1023552 | F34: =E34/D34 -> 0.36977796 | G34: =IF(F34<0.75,"EV cheaper",IF(AND(F34>=0.75,F34<=1),"Comparable","EV pricier")) -> EV cheaper | H34: =IF(F34<0.75, (1), IF(F34<1, (2/3), (1/3))) -> 1
A35: Mauritius | B35: 0.119 | C35: 1.516 | D35: 18.511876 | E35: 3.7480264 | F35: =E35/D35 -> 0.20246605 | G35: =IF(F35<0.75,"EV cheaper",IF(AND(F35>=0.75,F35<=1),"Comparable","EV pricier")) -> EV cheaper | H35: =IF(F35<0.75, 1, IF(F35<1, (2/3), (1/3))) -> 1
A36: Morocco | B36: 0.106 | C36: 1.481 | D36: 18.084491 | E36: 3.3385781 | F36: =E36/D36 -> 0.18461001 | G36: =IF(F36<0.75,"EV cheaper",IF(AND(F36>=0.75,F36<=1),"Comparable","EV pricier")) -> EV cheaper | H36: =IF(F36<0.75, (1), IF(F36<1, (2/3), (1/3))) -> 1
A37: Mozambique | B37: 0.08 | C37: 1.35 | D37: 16.48485 | E37: 2.5196816 | F37: =E37/D37 -> 0.15284832 | G37: =IF(F37<0.75,"EV cheaper",IF(AND(F37>=0.75,F37<=1),"Comparable","EV pricier")) -> EV cheaper | H37: =IF(F37<0.75, 1, IF(F37<1, (2/3), (1/3))) -> 1
A38: Namibia | B38: 0.148 | C38: 1.328 | D38: 16.216208 | E38: 4.661411 | F38: =E38/D38 -> 0.28745382 | G38: =IF(F38<0.75,"EV cheaper",IF(AND(F38>=0.75,F38<=1),"Comparable","EV pricier")) -> EV cheaper | H38: =IF(F38<0.75, (1), IF(F38<1, (2/3), (1/3))) -> 1
A39: Niger | B39: 0.236 | C39: 0.87 | D39: 10.62357 | E39: 7.4330607 | F39: =E39/D39 -> 0.69967635 | G39: =IF(F39<0.75,"EV cheaper",IF(AND(F39>=0.75,F39<=1),"Comparable","EV pricier")) -> EV cheaper | H39: =IF(F39<0.75, 1, IF(F39<1, (2/3), (1/3))) -> 1
A40: Nigeria | B40: 0.145 | C40: 0.799 | D40: 9.756589 | E40: 4.5669229 | F40: =E40/D40 -> 0.46808602 | G40: =IF(F40<0.75,"EV cheaper",IF(AND(F40>=0.75,F40<=1),"Comparable","EV pricier")) -> EV cheaper | H40: =IF(F40<0.75, (1), IF(F40<1, (2/3), (1/3))) -> 1
A41: Rwanda | B41: 0.081 | C41: 1.376 | D41: 16.802336 | E41: 2.5511776 | F41: =E41/D41 -> 0.1518347 | G41: =IF(F41<0.75,"EV cheaper",IF(AND(F41>=0.75,F41<=1),"Comparable","EV pricier")) -> EV cheaper | H41: =IF(F41<0.75, 1, IF(F41<1, (2/3), (1/3))) -> 1
A42: Sao Tome & Principe | B42: 0.18 | C42: 1.66 | D42: 20.27026 | E42: 5.6692836 | F42: =E42/D42 -> 0.2796848 | G42: =IF(F42<0.75,"EV cheaper",IF(AND(F42>=0.75,F42<=1),"Comparable","EV pricier")) -> EV cheaper | H42: =IF(F42<0.75, (1), IF(F42<1, (2/3), (1/3))) -> 1
A43: Senegal | B43: 0.21 | C43: 1.631 | D43: 19.916141 | E43: 6.6141642 | F43: =E43/D43 -> 0.33210069 | G43: =IF(F43<0.75,"EV cheaper",IF(AND(F43>=0.75,F43<=1),"Comparable","EV pricier")) -> EV cheaper | H43: =IF(F43<0.75, 1, IF(F43<1, (2/3), (1/3))) -> 1
A44: Seychelles | B44: 0.293 | C44: 1.573 | D44: 19.207903 | E44: 9.2283339 | F44: =E44/D44 -> 0.48044463 | G44: =IF(F44<0.75,"EV cheaper",IF(AND(F44>=0.75,F44<=1),"Comparable","EV pricier")) -> EV cheaper | H44: =IF(F44<0.75, (1), IF(F44<1, (2/3), (1/3))) -> 1
A45: Sierra Leone | B45: 0.171 | C45: 1.27 | D45: 15.50797 | E45: 5.3858194 | F45: =E45/D45 -> 0.34729364 | G45: =IF(F45<0.75,"EV cheaper",IF(AND(F45>=0.75,F45<=1),"Comparable","EV pricier")) -> EV cheaper | H45: =IF(F45<0.75, 1, IF(F45<1, (2/3), (1/3))) -> 1
A46: Somalia | B46: 0.079 | C46: 1.03 | D46: 12.57733 | E46: 2.4881856 | F46: =E46/D46 -> 0.19783098 | G46: =IF(F46<0.75,"EV cheaper",IF(AND(F46>=0.75,F46<=1),"Comparable","EV pricier")) -> EV cheaper | H46: =IF(F46<0.75, (1), IF(F46<1, (2/3), (1/3))) -> 1
A47: South Africa | B47: 0.072 | C47: 1.216 | D47: 14.848576 | E47: 2.2677134 | F47: =E47/D47 -> 0.15272262 | G47: =IF(F47<0.75,"EV cheaper",IF(AND(F47>=0.75,F47<=1),"Comparable","EV pricier")) -> EV cheaper | H47: =IF(F47<0.75, 1, IF(F47<1, (2/3), (1/3))) -> 1
A48: South Sudan | B48: 0.42 | C48: 1.4 | D48: 17.0954 | E48: 13.228328 | F48: =E48/D48 -> 0.77379461 | G48: =IF(F48<0.75,"EV cheaper",IF(AND(F48>=0.75,F48<=1),"Comparable","EV pricier")) -> Comparable | H48: =IF(F48<0.75, (1), IF(F48<1, (2/3), (1/3))) -> 0.66666667
A49: Sudan | B49: 0.044 | C49: 1.062 | D49: 12.968082 | E49: 1.3858249 | F49: =E49/D49 -> 0.10686429 | G49: =IF(F49<0.75,"EV cheaper",IF(AND(F49>=0.75,F49<=1),"Comparable","EV pricier")) -> EV cheaper | H49: =IF(F49<0.75, 1, IF(F49<1, (2/3), (1/3))) -> 1
A50: Tanzania | B50: 0.095 | C50: 1.28 | D50: 15.63008 | E50: 2.9921219 | F50: =E50/D50 -> 0.19143356 | G50: =IF(F50<0.75,"EV cheaper",IF(AND(F50>=0.75,F50<=1),"Comparable","EV pricier")) -> EV cheaper | H50: =IF(F50<0.75, (1), IF(F50<1, (2/3), (1/3))) -> 1
A51: Togo | B51: 0.176 | C51: 1.153 | D51: 14.079283 | E51: 5.5432995 | F51: =E51/D51 -> 0.3937203 | G51: =IF(F51<0.75,"EV cheaper",IF(AND(F51>=0.75,F51<=1),"Comparable","EV pricier")) -> EV cheaper | H51: =IF(F51<0.75, 1, IF(F51<1, (2/3), (1/3))) -> 1
A52: Tunisia | B52: 0.114 | C52: 0.816 | D52: 9.964176 | E52: 3.5905463 | F52: =E52/D52 -> 0.36034553 | G52: =IF(F52<0.75,"EV cheaper",IF(AND(F52>=0.75,F52<=1),"Comparable","EV pricier")) -> EV cheaper | H52: =IF(F52<0.75, (1), IF(F52<1, (2/3), (1/3))) -> 1
A53: Uganda | B53: 0.13 | C53: 1.274 | D53: 15.556814 | E53: 4.0944826 | F53: =E53/D53 -> 0.26319545 | G53: =IF(F53<0.75,"EV cheaper",IF(AND(F53>=0.75,F53<=1),"Comparable","EV pricier")) -> EV cheaper | H53: =IF(F53<0.75, 1, IF(F53<1, (2/3), (1/3))) -> 1
A54: Zambia | B54: 0.043 | C54: 1.277 | D54: 15.593447 | E54: 1.3543289 | F54: =E54/D54 -> 0.086852436 | G54: =IF(F54<0.75,"EV cheaper",IF(AND(F54>=0.75,F54<=1),"Comparable","EV pricier")) -> EV cheaper | H54: =IF(F54<0.75, (1), IF(F54<1, (2/3), (1/3))) -> 1
A55: Zimbabwe | B55: 0.112 | C55: 1.61 | D55: 19.65971 | E55: 3.5275542 | F55: =E55/D55 -> 0.17943063 | G55: =IF(F55<0.75,"EV cheaper",IF(AND(F55>=0.75,F55<=1),"Comparable","EV pricier")) -> EV cheaper | H55: =IF(F55<0.75, 1, IF(F55<1, (2/3), (1/3))) -> 1
C57: Summary statistics EV Charging Relative Affordability | E57: Country name
C58: Max | D58: =MAX(F2:F55) -> 3.4113526 | E58: Libya
C59: Min | D59: =MIN(F2:F55) -> 0.043254185 | E59: Lesotho
C60: Average | D60: =AVERAGE(F2:F55) -> 0.38281477
C61: Median | D61: =MEDIAN(F2:F55) -> 0.2808281
C62: Standard deviation | D62: =STDEV(F2:F55) -> 0.46341251
C64: Link to methodology
C65: {={"INDICATOR INFORMATION"; "Index Category: "&CHAR(10)& "EV Readiness Index - Measures country preparedness to adopt EVs at large scale"; ""; "Sub-Category: "&CHAR(10)& "EV Affordability"; ""; "Indicator Name: "&CHAR(10)& "Relative Affordability"; ""; "Description: "&CHAR(10)& "Compares the cost of operating an EV versus an ICE vehicle over 100 miles, expressed as a ratio of EV to ICE fuel costs"; ""; "Calculation Method: "&CHAR(10)& "See methodology note"; ""; "Scoring Categories: "&CHAR(10)& "• EV Pricier (>1) = Low Readiness (1/3)"&CHAR(10)& "• Comparable (0.75-1) = Medium Readiness (2/3)"&CHAR(10)& "• EV Cheaper (<0.75) = High Readiness (3/3)"; ""; "Summary Statistics: "&CHAR(10)& "• Maximum: 3.41 (Libya)"&CHAR(10)& "• Minimum: 0.04 (Lesotho)"&CHAR(10)& "• Average: 0.38"&CHAR(10)& "• Median: 0.28"&CHAR(10)& "• Standard Deviation: 0.46"; ""; "Interpretation: "&CHAR(10)& "• Ratio <0.75: EV costs 25% less than ICE"&CHAR(10)& "• Ratio 0.75-1: EV and ICE costs comparable"&CHAR(10)& "• Ratio >1: EV costs more than ICE"; ""; "Data Sources: "&CHAR(10)& "• Commercial electricity prices (2022)"&CHAR(10)& "• Gasoline pump prices (2022)"}} -> INDICATOR INFORMATION
C66: Index Category: EV Readiness Index - Measures country preparedness to adopt EVs at large scale
C68: Sub-Category: EV Affordability
C70: Indicator Name: Relative Affordability
C72: Description: Compares the cost of operating an EV versus an ICE vehicle over 100 miles, expressed as a ratio of EV to ICE fuel costs
C74: Calculation Method: See methodology note
C76: Scoring Categories: • EV Pricier (>1) = Low Readiness (1/3) • Comparable (0.75-1) = Medium Readiness (2/3) • EV Cheaper (<0.75) = High Readiness (3/3)
C78: Summary Statistics: • Maximum: 3.41 (Libya) • Minimum: 0.04 (Lesotho) • Average: 0.38 • Median: 0.28 • Standard Deviation: 0.46
C80: Interpretation: • Ratio <0.75: EV costs 25% less than ICE • Ratio 0.75-1: EV and ICE costs comparable • Ratio >1: EV costs more than ICE
C82: Data Sources: • Commercial electricity prices (2022) • Gasoline pump prices (2022)

Sheet Access to Finance
A1: Country | B1: Year | C1: Access to Finance (Borrowed any money from a formal financial institution or using a mobile money account (% age 15+)) | D1: Scoring: Low:<20%, Medium: 20-40%, High: >40% | E1: Score | F1: Source
A2: Algeria | B2: 2021 | C2: 0.04 | D2: =IF(C2 <0.2, "Low", IF(C2 < 0.4, "Medium", "High")) -> Low | E2: =IF(C2 <0.2, (1/3), IF(C2 <0.4, (2/3), 1)) -> 0.33333333 | F2: World Bank Global Findex, 2021
A3: Angola | C3: Not Found | D3: Not Found | E3: Not Found
A4: Benin | B4: 2021 | C4: 0.11 | D4: =IF(C4 <0.2, "Low", IF(C4 < 0.4, "Medium", "High")) -> Low | E4: =IF(C4 <0.2, (1/3), IF(C4 <0.4, (2/3), 1)) -> 0.33333333
A5: Botswana | B5: 2022 | C5: 0.11 | D5: =IF(C5 <0.2, "Low", IF(C5 < 0.4, "Medium", "High")) -> Low | E5: =IF(C5 <0.2, (1/3), IF(C5 <0.4, (2/3), 1)) -> 0.33333333
A6: Burkina Faso | B6: 2021 | C6: 0.09 | D6: =IF(C6 <0.2, "Low", IF(C6 < 0.4, "Medium", "High")) -> Low | E6: =IF(C6 <0.2, (1/3), IF(C6 <0.4, (2/3), 1)) -> 0.33333333
A7: Burundi | B7: 2014 | C7: Not Found | D7: Not Found | E7: Not Found
A8: Cabo Verde | C8: Not Found | D8: Not Found | E8: Not Found
A9: Cameroon | B9: 2021 | C9: 0.11 | D9: =IF(C9 <0.2, "Low", IF(C9 < 0.4, "Medium", "High")) -> Low | E9: =IF(C9 <0.2, (1/3), IF(C9 <0.4, (2/3), 1)) -> 0.33333333
A10: Central African Republic | B10: 2017 | C10: Not Found | D10: Not Found | E10: Not Found
A11: Chad | B11: 2022 | C11: 0.1 | D11: =IF(C11 <0.2, "Low", IF(C11 < 0.4, "Medium", "High")) -> Low | E11: =IF(C11 <0.2, (1/3), IF(C11 <0.4, (2/3), 1)) -> 0.33333333
A12: Comoros | B12: 2022 | C12: 0.09 | D12: =IF(C12 <0.2, "Low", IF(C12 < 0.4, "Medium", "High")) -> Low | E12: =IF(C12 <0.2, (1/3), IF(C12 <0.4, (2/3), 1)) -> 0.33333333
A13: Congo | B13: 2021 | C13: 0.1 | D13: =IF(C13 <0.2, "Low", IF(C13 < 0.4, "Medium", "High")) -> Low | E13: =IF(C13 <0.2, (1/3), IF(C13 <0.4, (2/3), 1)) -> 0.33333333
A14: Côte d'Ivoire | B14: 2021 | C14: 0.08 | D14: =IF(C14 <0.2, "Low", IF(C14 < 0.4, "Medium", "High")) -> Low | E14: =IF(C14 <0.2, (1/3), IF(C14 <0.4, (2/3), 1)) -> 0.33333333
A15: Djibouti | B15: 2011 | C15: Not Found | D15: Not Found | E15: Not Found
A16: DR Congo | B16: 2022 | C16: 0.05 | D16: =IF(C16 <0.2, "Low", IF(C16 < 0.4, "Medium", "High")) -> Low | E16: =IF(C16 <0.2, (1/3), IF(C16 <0.4, (2/3), 1)) -> 0.33333333
A17: Egypt | B17: 2021 | C17: 0.08 | D17: =IF(C17 <0.2, "Low", IF(C17 < 0.4, "Medium", "High")) -> Low | E17: =IF(C17 <0.2, (1/3), IF(C17 <0.4, (2/3), 1)) -> 0.33333333
A18: Equatorial Guinea | C18: Not Found | D18: Not Found | E18: Not Found
A19: Eritrea | C19: Not Found | D19: Not Found | E19: Not Found
A20: Eswatini | B20: 2022 | C20: 0.33 | D20: =IF(C20 <0.2, "Low", IF(C20 < 0.4, "Medium", "High")) -> Medium | E20: =IF(C20 <0.2, (1/3), IF(C20 <0.4, (2/3), 1)) -> 0.66666667
A21: Ethiopia | B21: 2022 | C21: 0.05 | D21: =IF(C21 <0.2, "Low", IF(C21 < 0.4, "Medium", "High")) -> Low | E21: =IF(C21 <0.2, (1/3), IF(C21 <0.4, (2/3), 1)) -> 0.33333333
A22: Gabon | B22: 2021 | C22: 0.12 | D22: =IF(C22 <0.2, "Low", IF(C22 < 0.4, "Medium", "High")) -> Low | E22: =IF(C22 <0.2, (1/3), IF(C22 <0.4, (2/3), 1)) -> 0.33333333
A23: Gambia | B23: 2022 | C23: 0.06 | D23: =IF(C23 <0.2, "Low", IF(C23 < 0.4, "Medium", "High")) -> Low | E23: =IF(C23 <0.2, (1/3), IF(C23 <0.4, (2/3), 1)) -> 0.33333333
A24: Ghana | B24: 2021 | C24: 0.17 | D24: =IF(C24 <0.2, "Low", IF(C24 < 0.4, "Medium", "High")) -> Low | E24: =IF(C24 <0.2, (1/3), IF(C24 <0.4, (2/3), 1)) -> 0.33333333
A25: Guinea | B25: 2021 | C25: 0.08 | D25: =IF(C25 <0.2, "Low", IF(C25 < 0.4, "Medium", "High")) -> Low | E25: =IF(C25 <0.2, (1/3), IF(C25 <0.4, (2/3), 1)) -> 0.33333333
A26: Guinea-Bissau | C26: Not Found | D26: Not Found | E26: Not Found
A27: Kenya | B27: 2021 | C27: 0.4 | D27: =IF(C27 <0.2, "Low", IF(C27 < 0.4, "Medium", "High")) -> High | E27: =IF(C27 <0.2, (1/3), IF(C27 <0.4, (2/3), 1)) -> 1
A28: Lesotho | B28: 2022 | C28: 0.19 | D28: =IF(C28 <0.2, "Low", IF(C28 < 0.4, "Medium", "High")) -> Low | E28: =IF(C28 <0.2, (1/3), IF(C28 <0.4, (2/3), 1)) -> 0.33333333
A29: Liberia | B29: 2021 | C29: 0.17 | D29: =IF(C29 <0.2, "Low", IF(C29 < 0.4, "Medium", "High")) -> Low | E29: =IF(C29 <0.2, (1/3), IF(C29 <0.4, (2/3), 1)) -> 0.33333333
A30: Libya | B30: 2017 | C30: Not Found | D30: Not Found | E30: Not Found
A31: Madagascar | B31: 2022 | C31: 0.09 | D31: =IF(C31 <0.2, "Low", IF(C31 < 0.4, "Medium", "High")) -> Low | E31: =IF(C31 <0.2, (1/3), IF(C31 <0.4, (2/3), 1)) -> 0.33333333
A32: Malawi | B32: 2021 | C32: 0.1 | D32: =IF(C32 <0.2, "Low", IF(C32 < 0.4, "Medium", "High")) -> Low | E32: =IF(C32 <0.2, (1/3), IF(C32 <0.4, (2/3), 1)) -> 0.33333333
A33: Mali | B33: 2021 | C33: 0.13 | D33: =IF(C33 <0.2, "Low", IF(C33 < 0.4, "Medium", "High")) -> Low | E33: =IF(C33 <0.2, (1/3), IF(C33 <0.4, (2/3), 1)) -> 0.33333333
A34: Mauritania | B34: 2022 | C34: 0.12 | D34: =IF(C34 <0.2, "Low", IF(C34 < 0.4, "Medium", "High")) -> Low | E34: =IF(C34 <0.2, (1/3), IF(C34 <0.4, (2/3), 1)) -> 0.33333333
A35: Mauritius | B35: 2021 | C35: 0.2 | D35: =IF(C35 <0.2, "Low", IF(C35 < 0.4, "Medium", "High")) -> Medium | E35: =IF(C35 <0.2, (1/3), IF(C35 <0.4, (2/3), 1)) -> 0.66666667
A36: Morocco | B36: 2021 | C36: 0.05 | D36: =IF(C36 <0.2, "Low", IF(C36 < 0.4, "Medium", "High")) -> Low | E36: =IF(C36 <0.2, (1/3), IF(C36 <0.4, (2/3), 1)) -> 0.33333333
A37: Mozambique | B37: 2021 | C37: 0.15 | D37: =IF(C37 <0.2, "Low", IF(C37 < 0.4, "Medium", "High")) -> Low | E37: =IF(C37 <0.2, (1/3), IF(C37 <0.4, (2/3), 1)) -> 0.33333333
A38: Namibia | B38: 2021 | C38: 0.23 | D38: =IF(C38 <0.2, "Low", IF(C38 < 0.4, "Medium", "High")) -> Medium | E38: =IF(C38 <0.2, (1/3), IF(C38 <0.4, (2/3), 1)) -> 0.66666667
A39: Niger | B39: 2022 | C39: 0.04 | D39: =IF(C39 <0.2, "Low", IF(C39 < 0.4, "Medium", "High")) -> Low | E39: =IF(C39 <0.2, (1/3), IF(C39 <0.4, (2/3), 1)) -> 0.33333333
A40: Nigeria | B40: 2021 | C40: 0.07 | D40: =IF(C40 <0.2, "Low", IF(C40 < 0.4, "Medium", "High")) -> Low | E40: =IF(C40 <0.2, (1/3), IF(C40 <0.4, (2/3), 1)) -> 0.33333333
A41: Rwanda | B41: 2017 | C41: Not Found | D41: Not Found | E41: Not Found
A42: Sao Tome & Principe | C42: Not Found | D42: Not Found | E42: Not Found
A43: Senegal | B43: 2021 | C43: 0.13 | D43: =IF(C43 <0.2, "Low", IF(C43 < 0.4, "Medium", "High")) -> Low | E43: =IF(C43 <0.2, (1/3), IF(C43 <0.4, (2/3), 1)) -> 0.33333333
A44: Seychelles | C44: Not Found | D44: Not Found | E44: Not Found
A45: Sierra Leone | B45: 2021 | C45: 0.06 | D45: =IF(C45 <0.2, "Low", IF(C45 < 0.4, "Medium", "High")) -> Low | E45: =IF(C45 <0.2, (1/3), IF(C45 <0.4, (2/3), 1)) -> 0.33333333
A46: Somalia | B46: 2014 | C46: Not Found | D46: Not Found | E46: Not Found
A47: South Africa | B47: 2021 | C47: 0.19 | D47: =IF(C47 <0.2, "Low", IF(C47 < 0.4, "Medium", "High")) -> Low | E47: =IF(C47 <0.2, (1/3), IF(C47 <0.4, (2/3), 1)) -> 0.33333333
A48: South Sudan | B48: 2021 | C48: 0.03 | D48: =IF(C48 <0.2, "Low", IF(C48 < 0.4, "Medium", "High")) -> Low | E48: =IF(C48 <0.2, (1/3), IF(C48 <0.4, (2/3), 1)) -> 0.33333333
A49: Sudan | B49: 2014 | C49: Not Found | D49: Not Found | E49: Not Found
A50: Tanzania | B50: 2021 | C50: 0.13 | D50: =IF(C50 <0.2, "Low", IF(C50 < 0.4, "Medium", "High")) -> Low | E50: =IF(C50 <0.2, (1/3), IF(C50 <0.4, (2/3), 1)) -> 0.33333333
A51: Togo | B51: 2021 | C51: 0.08 | D51: =IF(C51 <0.2, "Low", IF(C51 < 0.4, "Medium", "High")) -> Low | E51: =IF(C51 <0.2, (1/3), IF(C51 <0.4, (2/3), 1)) -> 0.33333333
A52: Tunisia | B52: 2021 | C52: 0.1 | D52: =IF(C52 <0.2, "Low", IF(C52 < 0.4, "Medium", "High")) -> Low | E52: =IF(C52 <0.2, (1/3), IF(C52 <0.4, (2/3), 1)) -> 0.33333333
A53: Uganda | B53: 2021 | C53: 0.29 | D53: =IF(C53 <0.2, "Low", IF(C53 < 0.4, "Medium", "High")) -> Medium | E53: =IF(C53 <0.2, (1/3), IF(C53 <0.4, (2/3), 1)) -> 0.66666667
A54: Zambia | B54: 2021 | C54: 0.15 | D54: =IF(C54 <0.2, "Low", IF(C54 < 0.4, "Medium", "High")) -> Low | E54: =IF(C54 <0.2, (1/3), IF(C54 <0.4, (2/3), 1)) -> 0.33333333
A55: Zimbabwe | B55: 2021 | C55: 0.15 | D55: =IF(C55 <0.2, "Low", IF(C55 < 0.4, "Medium", "High")) -> Low | E55: =IF(C55 <0.2, (1/3), IF(C55 <0.4, (2/3), 1)) -> 0.33333333
C57: Summary statistics Borrowed any money from a formal financial institution or using a mobile money account (% age 15+) | E57: Country name
C58: Max | D58: =max(C2:C55) -> 0.4 | E58: Kenya
C59: Min | D59: =min(C2:C55) -> 0.03 | E59: South Sudan
C60: Average | D60: =AVERAGE(C2:C55) -> 0.1255
C61: Median | D61: =MEDIAN(C2:C55) -> 0.105
C62: Standard deviation | D62: =STDEV(C2:C55) -> 0.078901107
C64: Link to methodology
C65: {={"INDICATOR INFORMATION"; "Index Category: "&CHAR(10)& "EV Readiness Index - Measures country preparedness to adopt EVs at large scale"; ""; "Sub-Category: "&CHAR(10)& "EV Affordability"; ""; "Indicator Name: "&CHAR(10)& "Access to Finance"; ""; "Description: "&CHAR(10)& "Measures the percentage of adults (age 15+) who have borrowed money from a formal financial institution or using a mobile money account"; ""; "Scoring Categories: "&CHAR(10)& "• Low (<20%) = Low Readiness (1/3)"&CHAR(10)& "• Medium (20-40%) = Medium Readiness (2/3)"&CHAR(10)& "• High (>40%) = High Readiness (3/3)"; ""; "Summary Statistics: "&CHAR(10)& "• Maximum: 40.0% (Kenya)"&CHAR(10)& "• Minimum: 3.0% (South Sudan)"&CHAR(10)& "• Average: 12.6%"&CHAR(10)& "• Median: 10.5%"&CHAR(10)& "• Standard Deviation: 7.9%"; ""; "Scoring Rationale: "&CHAR(10)& "• World average: 30%"&CHAR(10)& "• High-income countries average: 56%"&CHAR(10)& "• Regional benchmarks: Middle East (11%), South Asia (12%), SSA (14%)"; ""; "Data Coverage: "&CHAR(10)& "• Latest available data (primarily 2021-2022)"&CHAR(10)& "• Some countries have older or no data"; ""; "Data Source: "&CHAR(10)& "• World Bank Global Findex Database"}} -> INDICATOR INFORMATION
C66: Index Category: EV Readiness Index - Measures country preparedness to adopt EVs at large scale
C68: Sub-Category: EV Affordability
C70: Indicator Name: Access to Finance
C72: Description: Measures the percentage of adults (age 15+) who have borrowed money from a formal financial institution or using a mobile money account
C74: Scoring Categories: • Low (<20%) = Low Readiness (1/3) • Medium (20-40%) = Medium Readiness (2/3) • High (>40%) = High Readiness (3/3)
C76: Summary Statistics: • Maximum: 40.0% (Kenya) • Minimum: 3.0% (South Sudan) • Average: 12.6% • Median: 10.5% • Standard Deviation: 7.9%
C78: Scoring Rationale: • World average: 30% • High-income countries average: 56% • Regional benchmarks: Middle East (11%), South Asia (12%), SSA (14%)
C80: Data Coverage: • Latest available data (primarily 2021-2022) • Some countries have older or no data
C82: Data Source: • World Bank Global Findex Database

Sheet Electricity Generated from Clea
A1: Country | B1: Electricity net generation (billion kWh) | C1: Nuclear | D1: Renewables | E1: Fossil Fuels | F1: % Clean | G1: % Dirty | H1: Scoring: Low: <33%, Medium:33%-66%, High: >66% | I1: Score | J1: Source(s)
A2: Algeria | B2: 77.530727 | C2: 0 | D2: 0.90686 | E2: 76.623867 | F2: =(C2+D2)/B2 -> 0.011696782 | G2: =E2/B2 -> 0.98830322 | H2: =IF(F2<(1/3), "Low", IF(F2<(2/3), "Medium", "High")) -> Low | I2: =IF(F2<(1/3), (1/3), IF(F2<(2/3), (2/3), 1)) -> 0.33333333 | J2: U.S. Energy Information Administration
A3: Angola | B3: 16.429392 | C3: 0 | D3: 11.718 | E3: 4.711392 | F3: =(C3+D3)/B3 -> 0.71323394 | G3: =E3/B3 -> 0.28676606 | H3: =IF(F3<(1/3), "Low", IF(F3<(2/3), "Medium", "High")) -> High | I3: =IF(F3<(1/3), (1/3), IF(F3<(2/3), (2/3), 1)) -> 1
A4: Benin | B4: 0.24109728 | C4: 0 | D4: 0.00806 | E4: 0.23303728 | F4: =(C4+D4)/B4 -> 0.033430489 | G4: =E4/B4 -> 0.96656951 | H4: =IF(F4<(1/3), "Low", IF(F4<(2/3), "Medium", "High")) -> Low | I4: =IF(F4<(1/3), (1/3), IF(F4<(2/3), (2/3), 1)) -> 0.33333333
A5: Botswana | B5: 2.1823482 | C5: 0 | D5: 0.006 | E5: 2.1763482 | F5: =(C5+D5)/B5 -> 0.0027493322 | G5: =E5/B5 -> 0.99725067 | H5: =IF(F5<(1/3), "Low", IF(F5<(2/3), "Medium", "High")) -> Low | I5: =IF(F5<(1/3), (1/3), IF(F5<(2/3), (2/3), 1)) -> 0.33333333
A6: Burkina Faso | B6: 1.7612097 | C6: 0 | D6: 0.23422797 | E6: 1.5269817 | F6: =(C6+D6)/B6 -> 0.13299267 | G6: =E6/B6 -> 0.86700733 | H6: =IF(F6<(1/3), "Low", IF(F6<(2/3), "Medium", "High")) -> Low | I6: =IF(F6<(1/3), (1/3), IF(F6<(2/3), (2/3), 1)) -> 0.33333333
A7: Burundi | B7: 0.35799164 | C7: 0 | D7: 0.233788 | E7: 0.12420364 | F7: =(C7+D7)/B7 -> 0.65305436 | G7: =E7/B7 -> 0.34694564 | H7: =IF(F7<(1/3), "Low", IF(F7<(2/3), "Medium", "High")) -> Medium | I7: =IF(F7<(1/3), (1/3), IF(F7<(2/3), (2/3), 1)) -> 0.66666667
A8: Cabo Verde | B8: 0.45688711 | C8: 0 | D8: 0.073 | E8: 0.38388711 | F8: =(C8+D8)/B8 -> 0.15977689 | G8: =E8/B8 -> 0.84022311 | H8: =IF(F8<(1/3), "Low", IF(F8<(2/3), "Medium", "High")) -> Low | I8: =IF(F8<(1/3), (1/3), IF(F8<(2/3), (2/3), 1)) -> 0.33333333
A9: Cameroon | B9: 8.0454749 | C9: 0 | D9: 5.02 | E9: 3.0254749 | F9: =(C9+D9)/B9 -> 0.62395322 | G9: =E9/B9 -> 0.37604678 | H9: =IF(F9<(1/3), "Low", IF(F9<(2/3), "Medium", "High")) -> Medium | I9: =IF(F9<(1/3), (1/3), IF(F9<(2/3), (2/3), 1)) -> 0.66666667
A10: Central African Republic | B10: 0.151064 | C10: 0 | D10: 0.15 | E10: 0.001064 | F10: =(C10+D10)/B10 -> 0.99295663 | G10: =E10/B10 -> 0.0070433723 | H10: =IF(F10<(1/3), "Low", IF(F10<(2/3), "Medium", "High")) -> High | I10: =IF(F10<(1/3), (1/3), IF(F10<(2/3), (2/3), 1)) -> 1
A11: Chad | B11: 0.31243118 | C11: 0 | D11: 0.019 | E11: 0.29343118 | F11: =(C11+D11)/B11 -> 0.060813393 | G11: =E11/B11 -> 0.93918661 | H11: =IF(F11<(1/3), "Low", IF(F11<(2/3), "Medium", "High")) -> Low | I11: =IF(F11<(1/3), (1/3), IF(F11<(2/3), (2/3), 1)) -> 0.33333333
A12: Comoros | B12: 0.13832 | C12: 0 | D12: 0 | E12: 0.13832 | F12: =(C12+D12)/B12 -> 0 | G12: =E12/B12 -> 1 | H12: =IF(F12<(1/3), "Low", IF(F12<(2/3), "Medium", "High")) -> Low | I12: =IF(F12<(1/3), (1/3), IF(F12<(2/3), (2/3), 1)) -> 0.33333333
A13: Congo | B13: 4.0202615 | C13: 0 | D13: 0.90122 | E13: 3.1190415 | F13: =(C13+D13)/B13 -> 0.2241695 | G13: =E13/B13 -> 0.7758305 | H13: =IF(F13<(1/3), "Low", IF(F13<(2/3), "Medium", "High")) -> Low | I13: =IF(F13<(1/3), (1/3), IF(F13<(2/3), (2/3), 1)) -> 0.33333333
A14: Côte d'Ivoire | B14: 10.982227 | C14: 0 | D14: 3.311 | E14: 7.6712272 | F14: =(C14+D14)/B14 -> 0.30148712 | G14: =E14/B14 -> 0.69851288 | H14: =IF(F14<(1/3), "Low", IF(F14<(2/3), "Medium", "High")) -> Low | I14: =IF(F14<(1/3), (1/3), IF(F14<(2/3), (2/3), 1)) -> 0.33333333
... A55: Zimbabwe | B55: 8.030894 | C55: 0 | D55: 4.141269 | E55: 3.889625 | F55: =(C55+D55)/B55 -> 0.51566724 | G55: =E55/B55 -> 0.48433276 | H55: =IF(F55<(1/3), "Low", IF(F55<(2/3), "Medium", "High")) -> Medium | I55: =IF(F55<(1/3), (1/3), IF(F55<(2/3), (2/3), 1)) -> 0.66666667
C57: Summary statistics Electricity Generated from Clean Energy | E57: Country name
C58: Max | D58: =max(F2:F55) -> 1 | E58: Lesotho
C59: Min | D59: =min(F2:F55) -> 0 | E59: Botswana
C60: Average | D60: =AVERAGE(F2:F55) -> 0.39477013
C61: Median | D61: =median(F2:F55) -> 0.28536955
C62: Standard deviation | D62: =stdev(F2:F55) -> 0.34555902
C64: Link to methodology
C65: {={"INDICATOR INFORMATION"; "Index Category: "&CHAR(10)& "EV Impact Index - Measures broader benefits of EV adoption"; ""; "Sub-Category: "&CHAR(10)& "Climate"; ""; "Indicator Name: "&CHAR(10)& "Electricity Generated from Clean Energy"; ""; "Description: "&CHAR(10)& "Measures the percentage of total electricity generation from clean energy sources (nuclear and renewables) across African countries"; ""; "Calculation Method: "&CHAR(10)& "Clean Energy % = (Nuclear + Renewables Generation) ÷ Total Electricity Generation × 100"; ""; "Scoring Categories: "&CHAR(10)& "• Low (<33.33%) = Low Impact (1/3)"&CHAR(10)& "• Medium (33.33-66.67%) = Medium Impact (2/3)"&CHAR(10)& "• High (>66.67%) = High Impact (3/3)"; ""; "Summary Statistics: "&CHAR(10)& "• Maximum: 100.0% (Lesotho)"&CHAR(10)& "• Minimum: 0.0% (Botswana)"&CHAR(10)& "• Average: 39.5%"&CHAR(10)& "• Median: 28.5%"&CHAR(10)& "• Standard Deviation: 34.6%"; ""; "Scoring Rationale: "&CHAR(10)& "• Equal thirds distribution chosen over global benchmarks"&CHAR(10)& "• Global benchmarks (2021 IRENA data):"&CHAR(10)& " - 33rd percentile: 12.67%"&CHAR(10)& " - 66th percentile: 42.51%"; ""; "Data Source: "&CHAR(10)& "• U.S. Energy Information Administration (EIA)"}} -> INDICATOR INFORMATION
C66: Index Category: EV Impact Index - Measures broader benefits of EV adoption
C68: Sub-Category: Climate
C70: Indicator Name: Electricity Generated from Clean Energy
C72: Description: Measures the percentage of total electricity generation from clean energy sources (nuclear and renewables) across African countries
C74: Calculation Method: Clean Energy % = (Nuclear + Renewables Generation) ÷ Total Electricity Generation × 100
C76: Scoring Categories: • Low (<33.33%) = Low Impact (1/3) • Medium (33.33-66.67%) = Medium Impact (2/3) • High (>66.67%) = High Impact (3/3)
C78: Summary Statistics: • Maximum: 100.0% (Lesotho) • Minimum: 0.0% (Botswana) • Average: 39.5% • Median: 28.5% • Standard Deviation: 34.6%
C80: Scoring Rationale: • Equal thirds distribution chosen over global benchmarks • Global benchmarks (2021 IRENA data): - 33rd percentile: 12.67% - 66th percentile: 42.51%
C82: Data Source: • U.S. Energy Information Administration (EIA)

Sheet CO2 from Transportation
A1: Country | B1: Year | C1: CO2 from fuel combustion | D1: Transport CO2 | E1: % of CO2 from Transport | F1: Scoring: Low: 0-33%, Medium: 33%-66.67%, High: 66.67%-100% | G1: Score | H1: Source(s)
A2: Algeria | B2: 2020 | C2: 134515.1 | D2: 40465.9 | E2: =D2/C2 -> 0.30082794 | F2: =IF(E2 <(1/3), "Low", IF(E2 <(2/3), "Medium", "High")) -> Low | G2: =IF(E2<(1/3), (1/3), IF(E2<=(2/3), (2/3), 1)) -> 0.33333333 | H2: Greenhouse Gas Emissions from Energy, IEA
A3: Angola | B3: 2020 | C3: 15141.6 | D3: 5632.1 | E3: =D3/C3 -> 0.37196201 | F3: =IF(E3 <(1/3), "Low", IF(E3 <(2/3), "Medium", "High")) -> Medium | G3: =IF(E3 <(1/3), (1/3), IF(E3 <=(2/3), (2/3), 1)) -> 0.66666667 | H3: World Energy Balances, IEA
A4: Benin | B4: 2020 | C4: 7611.4 | D4: 6170.7 | E4: =D4/C4 -> 0.81071813 | F4: =IF(E4 <(1/3), "Low", IF(E4 <(2/3), "Medium", "High")) -> High | G4: =IF(E4<(1/3), (1/3), IF(E4<=(2/3), (2/3), 1)) -> 1
A5: Botswana | B5: 2020 | C5: 5760.2 | D5: 2126.7 | E5: =D5/C5 -> 0.36920593 | F5: =IF(E5 <(1/3), "Low", IF(E5 <(2/3), "Medium", "High")) -> Medium | G5: =IF(E5 <(1/3), (1/3), IF(E5 <=(2/3), (2/3), 1)) -> 0.66666667
A6: Burkina Faso | B6: 2020 | C6: 4608.1 | D6: 2524.5 | E6: =D6/C6 -> 0.54783967 | F6: =IF(E6 <(1/3), "Low", IF(E6 <(2/3), "Medium", "High")) -> Medium | G6: =IF(E6<(1/3), (1/3), IF(E6<=(2/3), (2/3), 1)) -> 0.66666667
A7: Burundi | B7: 2020 | C7: 710.5 | D7: 568.3 | E7: =D7/C7 -> 0.79985925 | F7: =IF(E7 <(1/3), "Low", IF(E7 <(2/3), "Medium", "High")) -> High | G7: =IF(E7 <(1/3), (1/3), IF(E7 <=(2/3), (2/3), 1)) -> 1
A8: Cabo Verde | B8: 2020 | C8: 620.6 | D8: 287 | E8: =D8/C8 -> 0.46245569 | F8: =IF(E8 <(1/3), "Low", IF(E8 <(2/3), "Medium", "High")) -> Medium | G8: =IF(E8<(1/3), (1/3), IF(E8<=(2/3), (2/3), 1)) -> 0.66666667
A9: Cameroon | B9: 2020 | C9: 6835.8 | D9: 3424.1 | E9: =D9/C9 -> 0.50090699 | F9: =IF(E9 <(1/3), "Low", IF(E9 <(2/3), "Medium", "High")) -> Medium | G9: =IF(E9 <(1/3), (1/3), IF(E9 <=(2/3), (2/3), 1)) -> 0.66666667
A10: Central African Republic | B10: 2020 | C10: 236.6 | D10: 216 | E10: =D10/C10 -> 0.91293322 | F10: =IF(E10 <(1/3), "Low", IF(E10 <(2/3), "Medium", "High")) -> High | G10: =IF(E10<(1/3), (1/3), IF(E10<=(2/3), (2/3), 1)) -> 1
A11: Chad | B11: 2020 | C11: 1432.8 | D11: 1091.9 | E11: =D11/C11 -> 0.76207426 | F11: =IF(E11 <(1/3), "Low", IF(E11 <(2/3), "Medium", "High")) -> High | G11: =IF(E11 <(1/3), (1/3), IF(E11 <=(2/3), (2/3), 1)) -> 1
A12: Comoros | B12: 2020 | C12: 328.2 | D12: 185.8 | E12: =D12/C12 -> 0.56611822 | F12: =IF(E12 <(1/3), "Low", IF(E12 <(2/3), "Medium", "High")) -> Medium | G12: =IF(E12<(1/3), (1/3), IF(E12<=(2/3), (2/3), 1)) -> 0.66666667
A13: Congo | B13: 2020 | C13: 3543.8 | D13: 1147.9 | E13: =D13/C13 -> 0.32391783 | F13: =IF(E13 <(1/3), "Low", IF(E13 <(2/3), "Medium", "High")) -> Low | G13: =IF(E13 <(1/3), (1/3), IF(E13 <=(2/3), (2/3), 1)) -> 0.33333333
A14: Côte d'Ivoire | B14: 2020 | C14: 10805.5 | D14: 4162 | E14: =D14/C14 -> 0.38517422 | F14: =IF(E14 <(1/3), "Low", IF(E14 <(2/3), "Medium", "High")) -> Medium | G14: =IF(E14<(1/3), (1/3), IF(E14<=(2/3), (2/3), 1)) -> 0.66666667
A15: Djibouti | B15: 2020 | C15: 334.7 | D15: 138.6 | E15: =D15/C15 -> 0.41410218 | F15: =IF(E15 <(1/3), "Low", IF(E15 <(2/3), "Medium", "High")) -> Medium | G15: =IF(E15 <(1/3), (1/3), IF(E15 <=(2/3), (2/3), 1)) -> 0.66666667
A16: DR Congo | B16: 2020 | C16: 2329.5 | D16: 2320.9 | E16: =D16/C16 -> 0.99630822 | F16: =IF(E16 <(1/3), "Low", IF(E16 <(2/3), "Medium", "High")) -> High | G16: =IF(E16<(1/3), (1/3), IF(E16<=(2/3), (2/3), 1)) -> 1
A17: Egypt | B17: 2020 | C17: 188372.4 | D17: 51566.4 | E17: =D17/C17 -> 0.27374711 | F17: =IF(E17 <(1/3), "Low", IF(E17 <(2/3), "Medium", "High")) -> Low | G17: =IF(E17 <(1/3), (1/3), IF(E17 <=(2/3), (2/3), 1)) -> 0.33333333
A18: Equatorial Guinea | B18: 2020 | C18: 3806.7 | D18: 432.7 | E18: =D18/C18 -> 0.11366801 | F18: =IF(E18 <(1/3), "Low", IF(E18 <(2/3), "Medium", "High")) -> Low | G18: =IF(E18<(1/3), (1/3), IF(E18<=(2/3), (2/3), 1)) -> 0.33333333
A19: Eritrea | B19: 2020 | C19: 597.9 | D19: 217.5 | E19: =D19/C19 -> 0.36377321 | F19: =IF(E19 <(1/3), "Low", IF(E19 <(2/3), "Medium", "High")) -> Medium | G19: =IF(E19 <(1/3), (1/3), IF(E19 <=(2/3), (2/3), 1)) -> 0.66666667
A20: Eswatini | B20: 2020 | C20: 1147.7 | D20: 709.9 | E20: =D20/C20 -> 0.61854143 | F20: =IF(E20 <(1/3), "Low", IF(E20 <(2/3), "Medium", "High")) -> Medium | G20: =IF(E20<(1/3), (1/3), IF(E20<=(2/3), (2/3), 1)) -> 0.66666667
A21: Ethiopia | B21: 2020 | C21: 14339 | D21: 7397.6 | E21: =D21/C21 -> 0.51590766 | F21: =IF(E21 <(1/3), "Low", IF(E21 <(2/3), "Medium", "High")) -> Medium | G21: =IF(E21 <(1/3), (1/3), IF(E21 <=(2/3), (2/3), 1)) -> 0.66666667
A22: Gabon | B22: 2020 | C22: 2523.2 | D22: 189.4 | E22: =D22/C22 -> 0.075063412 | F22: =IF(E22 <(1/3), "Low", IF(E22 <(2/3), "Medium", "High")) -> Low | G22: =IF(E22<(1/3), (1/3), IF(E22<=(2/3), (2/3), 1)) -> 0.33333333
A23: Gambia | B23: 2020 | C23: 611.4 | D23: 81.3 | E23: =D23/C23 -> 0.1329735 | F23: =IF(E23 <(1/3), "Low", IF(E23 <(2/3), "Medium", "High")) -> Low | G23: =IF(E23 <(1/3), (1/3), IF(E23 <=(2/3), (2/3), 1)) -> 0.33333333
A24: Ghana | B24: 2020 | C24: 19035.4 | D24: 9160.7 | E24: =D24/C24 -> 0.48124547 | F24: =IF(E24 <(1/3), "Low", IF(E24 <(2/3), "Medium", "High")) -> Medium | G24: =IF(E24<(1/3), (1/3), IF(E24<=(2/3), (2/3), 1)) -> 0.66666667
A25: Guinea | B25: 2020 | C25: 4537.9 | D25: 2064.3 | E25: =D25/C25 -> 0.45490205 | F25: =IF(E25 <(1/3), "Low", IF(E25 <(2/3), "Medium", "High")) -> Medium | G25: =IF(E25 <(1/3), (1/3), IF(E25 <=(2/3), (2/3), 1)) -> 0.66666667
A26: Guinea-Bissau | B26: 2020 | C26: 329 | D26: 118.8 | E26: =D26/C26 -> 0.36109422 | F26: =IF(E26 <(1/3), "Low", IF(E26 <(2/3), "Medium", "High")) -> Medium | G26: =IF(E26<(1/3), (1/3), IF(E26<=(2/3), (2/3), 1)) -> 0.66666667
A27: Kenya | B27: 2020 | C27: 15754.8 | D27: 10399.5 | E27: =D27/C27 -> 0.66008455 | F27: =IF(E27 <(1/3), "Low", IF(E27 <(2/3), "Medium", "High")) -> Medium | G27: =IF(E27 <(1/3), (1/3), IF(E27 <=(2/3), (2/3), 1)) -> 0.66666667
A28: Lesotho | B28: 2020 | C28: 2311.9 | D28: 538.1 | E28: =D28/C28 -> 0.23275228 | F28: =IF(E28 <(1/3), "Low", IF(E28 <(2/3), "Medium", "High")) -> Low | G28: =IF(E28<(1/3), (1/3), IF(E28<=(2/3), (2/3), 1)) -> 0.33333333
A29: Liberia | B29: 2020 | C29: 1018.3 | D29: 622.4 | E29: =D29/C29 -> 0.61121477 | F29: =IF(E29 <(1/3), "Low", IF(E29 <(2/3), "Medium", "High")) -> Medium | G29: =IF(E29 <(1/3), (1/3), IF(E29 <=(2/3), (2/3), 1)) -> 0.66666667
A30: Libya | B30: 2020 | C30: 39159.4 | D30: 16710.5 | E30: =D30/C30 -> 0.42673024 | F30: =IF(E30 <(1/3), "Low", IF(E30 <(2/3), "Medium", "High")) -> Medium | G30: =IF(E30<(1/3), (1/3), IF(E30<=(2/3), (2/3), 1)) -> 0.66666667
A31: Madagascar | B31: 2020 | C31: 2706.7 | D31: 1192 | E31: =D31/C31 -> 0.44038867 | F31: =IF(E31 <(1/3), "Low", IF(E31 <(2/3), "Medium", "High")) -> Medium | G31: =IF(E31 <(1/3), (1/3), IF(E31 <=(2/3), (2/3), 1)) -> 0.66666667
A32: Malawi | B32: 2020 | C32: 1538.3 | D32: 1158.4 | E32: =D32/C32 -> 0.75303907 | F32: =IF(E32 <(1/3), "Low", IF(E32 <(2/3), "Medium", "High")) -> High | G32: =IF(E32<(1/3), (1/3), IF(E32<=(2/3), (2/3), 1)) -> 1
A33: Mali | B33: 2020 | C33: 3569.5 | D33: 1499.2 | E33: =D33/C33 -> 0.4200028 | F33: =IF(E33 <(1/3), "Low", IF(E33 <(2/3), "Medium", "High")) -> Medium | G33: =IF(E33 <(1/3), (1/3), IF(E33 <=(2/3), (2/3), 1)) -> 0.66666667
A34: Mauritania | B34: 2020 | C34: 3847.1 | D34: 1701.7 | E34: =D34/C34 -> 0.44233319 | F34: =IF(E34 <(1/3), "Low", IF(E34 <(2/3), "Medium", "High")) -> Medium | G34: =IF(E34<(1/3), (1/3), IF(E34<=(2/3), (2/3), 1)) -> 0.66666667
A35: Mauritius | B35: 2020 | C35: 3720.2 | D35: 1012.3 | E35: =D35/C35 -> 0.27210903 | F35: =IF(E35 <(1/3), "Low", IF(E35 <(2/3), "Medium", "High")) -> Low | G35: =IF(E35 <(1/3), (1/3), IF(E35 <=(2/3), (2/3), 1)) -> 0.33333333
A36: Morocco | B36: 2020 | C36: 62229.5 | D36: 16639.9 | E36: =D36/C36 -> 0.26739569 | F36: =IF(E36 <(1/3), "Low", IF(E36 <(2/3), "Medium", "High")) -> Low | G36: =IF(E36<(1/3), (1/3), IF(E36<=(2/3), (2/3), 1)) -> 0.33333333
A37: Mozambique | B37: 2020 | C37: 5848.2 | D37: 3275.9 | E37: =D37/C37 -> 0.56015526 | F37: =IF(E37 <(1/3), "Low", IF(E37 <(2/3), "Medium", "High")) -> Medium | G37: =IF(E37 <(1/3), (1/3), IF(E37 <=(2/3), (2/3), 1)) -> 0.66666667
A38: Namibia | B38: 2020 | C38: 3484.3 | D38: 1862.4 | E38: =D38/C38 -> 0.53451195 | F38: =IF(E38 <(1/3), "Low", IF(E38 <(2/3), "Medium", "High")) -> Medium | G38: =IF(E38<(1/3), (1/3), IF(E38<=(2/3), (2/3), 1)) -> 0.66666667
A39: Niger | B39: 2020 | C39: 2108.3 | D39: 1129.4 | E39: =D39/C39 -> 0.53569226 | F39: =IF(E39 <(1/3), "Low", IF(E39 <(2/3), "Medium", "High")) -> Medium | G39: =IF(E39 <(1/3), (1/3), IF(E39 <=(2/3), (2/3), 1)) -> 0.66666667
A40: Nigeria | B40: 2020 | C40: 88117.7 | D40: 50984.8 | E40: =D40/C40 -> 0.57859885 | F40: =IF(E40 <(1/3), "Low", IF(E40 <(2/3), "Medium", "High")) -> Medium | G40: =IF(E40<(1/3), (1/3), IF(E40<=(2/3), (2/3), 1)) -> 0.66666667
A41: Rwanda | B41: 2020 | C41: 1232.6 | D41: 580.9 | E41: =D41/C41 -> 0.47128022 | F41: =IF(E41 <(1/3), "Low", IF(E41 <(2/3), "Medium", "High")) -> Medium | G41: =IF(E41 <(1/3), (1/3), IF(E41 <=(2/3), (2/3), 1)) -> 0.66666667
A42: Sao Tome & Principe | B42: 2020 | C42: 141.1 | D42: 34.5 | E42: =D42/C42 -> 0.24450744 | F42: =IF(E42 <(1/3), "Low", IF(E42 <(2/3), "Medium", "High")) -> Low | G42: =IF(E42<(1/3), (1/3), IF(E42<=(2/3), (2/3), 1)) -> 0.33333333
A43: Senegal | B43: 2020 | C43: 7968.2 | D43: 2865.9 | E43: =D43/C43 -> 0.35966718 | F43: =IF(E43 <(1/3), "Low", IF(E43 <(2/3), "Medium", "High")) -> Medium | G43: =IF(E43 <(1/3), (1/3), IF(E43 <=(2/3), (2/3), 1)) -> 0.66666667
A44: Seychelles | B44: 2020 | C44: 598.7 | D44: 172.3 | E44: =D44/C44 -> 0.28779021 | F44: =IF(E44 <(1/3), "Low", IF(E44 <(2/3), "Medium", "High")) -> Low | G44: =IF(E44<(1/3), (1/3), IF(E44<=(2/3), (2/3), 1)) -> 0.33333333
A45: Sierra Leone | B45: 2020 | C45: 1048 | D45: 672.1 | E45: =D45/C45 -> 0.64131679 | F45: =IF(E45 <(1/3), "Low", IF(E45 <(2/3), "Medium", "High")) -> Medium | G45: =IF(E45 <(1/3), (1/3), IF(E45 <=(2/3), (2/3), 1)) -> 0.66666667
A46: Somalia | B46: 2020 | C46: 660.4 | D46: 142.2 | E46: =D46/C46 -> 0.21532405 | F46: =IF(E46 <(1/3), "Low", IF(E46 <(2/3), "Medium", "High")) -> Low | G46: =IF(E46<(1/3), (1/3), IF(E46<=(2/3), (2/3), 1)) -> 0.33333333
A47: South Africa | B47: 2020 | C47: 388114.5 | D47: 45038.8 | E47: =D47/C47 -> 0.11604514 | F47: =IF(E47 <(1/3), "Low", IF(E47 <(2/3), "Medium", "High")) -> Low | G47: =IF(E47 <(1/3), (1/3), IF(E47 <=(2/3), (2/3), 1)) -> 0.33333333
A48: South Sudan | B48: 2020 | C48: 1742.7 | D48: 900.1 | E48: =D48/C48 -> 0.51649739 | F48: =IF(E48 <(1/3), "Low", IF(E48 <(2/3), "Medium", "High")) -> Medium | G48: =IF(E48<(1/3), (1/3), IF(E48<=(2/3), (2/3), 1)) -> 0.66666667
A49: Sudan | B49: 2020 | C49: 18675.8 | D49: 10384.6 | E49: =D49/C49 -> 0.55604579 | F49: =IF(E49 <(1/3), "Low", IF(E49 <(2/3), "Medium", "High")) -> Medium | G49: =IF(E49 <(1/3), (1/3), IF(E49 <=(2/3), (2/3), 1)) -> 0.66666667
A50: Tanzania | B50: 2020 | C50: 11918.5 | D50: 6611 | E50: =D50/C50 -> 0.55468389 | F50: =IF(E50 <(1/3), "Low", IF(E50 <(2/3), "Medium", "High")) -> Medium | G50: =IF(E50<(1/3), (1/3), IF(E50<=(2/3), (2/3), 1)) -> 0.66666667
A51: Togo | B51: 2020 | C51: 1550.8 | D51: 1096.5 | E51: =D51/C51 -> 0.70705442 | F51: =IF(E51 <(1/3), "Low", IF(E51 <(2/3), "Medium", "High")) -> High | G51: =IF(E51 <(1/3), (1/3), IF(E51 <=(2/3), (2/3), 1)) -> 1
A52: Tunisia | B52: 2020 | C52: 25178.2 | D52: 7085 | E52: =D52/C52 -> 0.28139422 | F52: =IF(E52 <(1/3), "Low", IF(E52 <(2/3), "Medium", "High")) -> Low | G52: =IF(E52<(1/3), (1/3), IF(E52<=(2/3), (2/3), 1)) -> 0.33333333
A53: Uganda | B53: 2020 | C53: 5142.2 | D53: 3391.3 | E53: =D53/C53 -> 0.65950371 | F53: =IF(E53 <(1/3), "Low", IF(E53 <(2/3), "Medium", "High")) -> Medium | G53: =IF(E53 <(1/3), (1/3), IF(E53 <=(2/3), (2/3), 1)) -> 0.66666667
A54: Zambia | B54: 2020 | C54: 6677.1 | D54: 2489.5 | E54: =D54/C54 -> 0.3728415 | F54: =IF(E54 <(1/3), "Low", IF(E54 <(2/3), "Medium", "High")) -> Medium | G54: =IF(E54<(1/3), (1/3), IF(E54<=(2/3), (2/3), 1)) -> 0.66666667
A55: Zimbabwe | B55: 2020 | C55: 7816.5 | D55: 2069.9 | E55: =D55/C55 -> 0.26481162 | F55: =IF(E55 <(1/3), "Low", IF(E55 <(2/3), "Medium", "High")) -> Low | G55: =IF(E55 <(1/3), (1/3), IF(E55 <=(2/3), (2/3), 1)) -> 0.33333333
C57: Summary statistics CO2 from Transportation | E57: Country name
C58: Max | D58: =max(E3:E55) -> 0.99630822 | E58: DR Congo
C59: Min | D59: =min(E3:E55) -> 0.075063412 | E59: Gabon
C60: Average | D60: =average(E3:E55) -> 0.46411819
C61: Median | D61: =median(E3:E55) -> 0.45490205
C62: Standard deviation | D62: =stdev(E3:E55) -> 0.20337483
C64: Link to methodology
